Workbook

Sheet RAW DATA
A1: ID Karyawan (Auto Generate) | B1: Nama Karyawan (sesuai KTP) | C1: Alamat sesuai KTP | D1: Tanggal Lahir | E1: Kota Kelahiran | F1: Pendidikan Terakhir | G1: No WA (Aktif) | H1: Alamat Email (Aktif) | I1: Nama Jabatan | J1: Nama Lokasi kerja (jika promotor sebutkan nama toko penempatan) | K1: Nama Kota/ Kabupaten Lokasi Kerja | L1: No Rekening BCA (Aktif) | M1: Tgl join di Mito | N1: Tgl awal kontrak (dg Damarindo) | O1: Tgl akhir kontrak (StaffInc) | P1: Nama Cabang (Cost Center) | Q1: Entity | R1: Skema Penggajian | S1: Nominal UMK yang dipakai | T1: Amount Gaji Pokok | U1: Amount Insentif 30% | V1: Remarks | W1: Basic Salary (StaffInc) | X1: Tunjangan (StaffInc) | Y1: Total
A2: DM20260001 | B2: Abel Saskia Putri | C2: =vlookup(B2,Sheet3!B:C,2,0) -> Jln. Jelawat | D2: =vlookup(B2,Sheet3!B:D,3,0) -> 39148 | E2: =vlookup(B2,Sheet3!B:F,5,0) -> Samarinda | F2: =vlookup(B2,Sheet3!B:H,7,0) -> SLTA | G2: =vlookup(B2,Sheet3!B:I,8,0) -> 088705334961 | H2: =vlookup(B2,Sheet3!B:J,9,0) -> bypisbel7@gmail.com | I2: SPB/SPG Toko | J2: =vlookup(B2,Sheet2!B:D,3,0) -> MAMASUKA | K2: =vlookup(A2,Sheet2!A:E,5,0) -> SAMARINDA | L2: =VLOOKUP(B2,Sheet3!B:L,11,0) -> 8355484218 | M2: 46280 | N2: 46280 | P2: =VLOOKUP(A2,Sheet2!A:F,6,0) -> SAMARINDA | Q2: PT. Mahakarya Sukses Indonesia | R2: 70/30 | S2: 3984000 | T2: 2788800 | U2: 1195200 | V2: Resign per 20/9 | Y2: =W2+X2 -> 0
A3: DM20260002 | B3: Adelina Astuti | C3: =vlookup(B3,Sheet3!B:C,2,0) -> Dusun Tamansari RT 012 / RW 004 ,kel. Kertahayu kec. Pamarican | D3: =vlookup(B3,Sheet3!B:D,3,0) -> 33737 | E3: =vlookup(B3,Sheet3!B:F,5,0) -> CIAMIS | F3: =vlookup(B3,Sheet3!B:H,7,0) -> SLTA | G3: =vlookup(B3,Sheet3!B:I,8,0) -> 085849233099 | H3: =vlookup(B3,Sheet3!B:J,9,0) -> Adelinemeidian@gmail.com | I3: SPB/SPG Outlet | J3: =vlookup(B3,Sheet2!B:D,3,0) -> MALL KELAPA GADING | K3: =vlookup(A3,Sheet2!A:E,5,0) -> JAKARTA | L3: =VLOOKUP(B3,Sheet3!B:L,11,0) -> 5910185235 | M3: 44852 | N3: 46266 | O3: 46265 | P3: =VLOOKUP(A3,Sheet2!A:F,6,0) -> JAKARTA | Q3: PT. Mahakarya Sukses Indonesia | R3: Khusus | S3: 5730000 | T3: 5730000 | W3: 5729876 | X3: 600000 | Y3: =W3+X3 -> 6329876
A4: DM20260003 | B4: Agustia Ningrum | C4: =vlookup(B4,Sheet3!B:C,2,0) -> JL.KASAN REJO 2 | D4: =vlookup(B4,Sheet3!B:D,3,0) -> 36395 | E4: =vlookup(B4,Sheet3!B:F,5,0) -> JEPARA | F4: =vlookup(B4,Sheet3!B:H,7,0) -> SLTA | G4: =vlookup(B4,Sheet3!B:I,8,0) -> 0811522178 | H4: =vlookup(B4,Sheet3!B:J,9,0) -> ningrumtia03@gmail.com | I4: SPB/SPG Toko | J4: =vlookup(B4,Sheet2!B:D,3,0) -> NUANSA PANGKALANBUN | K4: =vlookup(A4,Sheet2!A:E,5,0) -> KOTAWARINGIN BARAT | L4: =VLOOKUP(B4,Sheet3!B:L,11,0) -> 8585226544 | M4: =vlookup(B4,'data staffinc_3'!B:I,7,0) -> 45546 | N4: 46266 | O4: =vlookup(B4,'data staffinc_3'!B:I,8,0) -> 46265 | P4: =VLOOKUP(A4,Sheet2!A:F,6,0) -> BANJARMASIN | Q4: PT. Mahakarya Sukses Indonesia | R4: 70/30 | S4: 3910000 | T4: 2737000 | U4: 1173000 | W4: 3909005 | X4: 0 | Y4: =W4+X4 -> 3909005
A5: DM20260004 | B5: Agustina Galuh Prihaningtyas | C5: =vlookup(B5,Sheet3!B:C,2,0) -> Jl jagalan no 65 | D5: =vlookup(B5,Sheet3!B:D,3,0) -> 31634 | E5: =vlookup(B5,Sheet3!B:F,5,0) -> Yogyakarta | F5: =vlookup(B5,Sheet3!B:H,7,0) -> SLTA | G5: =vlookup(B5,Sheet3!B:I,8,0) -> 087814045446 | H5: =vlookup(B5,Sheet3!B:J,9,0) -> galuh8893@gmail.com | I5: SPB/SPG Toko | J5: =vlookup(B5,Sheet2!B:D,3,0) -> UFO YOGYAKARTA JOKTENG | K5: =vlookup(A5,Sheet2!A:E,5,0) -> YOGYAKARTA | L5: =VLOOKUP(B5,Sheet3!B:L,11,0) -> 1690194631 | M5: 45819 | N5: 46266 | O5: 46265 | P5: =VLOOKUP(A5,Sheet2!A:F,6,0) -> SEMARANG | Q5: PT. Mahakarya Sukses Indonesia | R5: 70/30 | S5: 2828000 | T5: 1979600 | U5: 848400 | W5: 2827593 | X5: 0 | Y5: =W5+X5 -> 2827593
A6: DM20260005 | B6: Ainun Jariah | C6: =vlookup(B6,Sheet3!B:C,2,0) -> Jl. Kelayan A | Gang Sidodadi RT.11 RW.01 No.18 | D6: =vlookup(B6,Sheet3!B:D,3,0) -> 34822 | E6: =vlookup(B6,Sheet3!B:F,5,0) -> Banjarmasin | F6: =vlookup(B6,Sheet3!B:H,7,0) -> SLTA | G6: =vlookup(B6,Sheet3!B:I,8,0) -> 0895608199789 | H6: =vlookup(B6,Sheet3!B:J,9,0) -> program.ainun@gmail.com | I6: SPB/SPG Toko | J6: =vlookup(B6,Sheet2!B:D,3,0) -> GOLDEN 10 | K6: =vlookup(A6,Sheet2!A:E,5,0) -> BANJARMASIN | L6: =VLOOKUP(B6,Sheet3!B:L,11,0) -> 7820819785 | M6: =vlookup(B6,'data staffinc_3'!B:I,7,0) -> 45685 | N6: 46266 | O6: =vlookup(B6,'data staffinc_3'!B:I,8,0) -> 46265 | P6: =VLOOKUP(A6,Sheet2!A:F,6,0) -> BANJARMASIN | Q6: PT. Mahakarya Sukses Indonesia | R6: 70/30 | S6: 3856000 | T6: 2699200 | U6: 1156800 | W6: 3855894 | X6: 0 | Y6: =W6+X6 -> 3855894
A7: DM20260006 | B7: Anggiza Gana Pawestri | C7: =vlookup(B7,Sheet3!B:C,2,0) -> Jl.Buni Malaka Rt06/08 no 15 kel.munjul kec. Cipayung Jakarta Timur | D7: =vlookup(B7,Sheet3!B:D,3,0) -> 31659 | E7: =vlookup(B7,Sheet3!B:F,5,0) -> Jakarta | F7: =vlookup(B7,Sheet3!B:H,7,0) -> SLTA | G7: =vlookup(B7,Sheet3!B:I,8,0) -> 087887345099 | H7: =vlookup(B7,Sheet3!B:J,9,0) -> Anggipawestri04@gmail.com | I7: SPB/SPG Toko | J7: =vlookup(B7,Sheet2!B:D,3,0) -> HARAPAN BARU | K7: JAKARTA | L7: =VLOOKUP(B7,Sheet3!B:L,11,0) -> 8691115984 | M7: 43409 | N7: 46266 | O7: 46265 | P7: =VLOOKUP(A7,Sheet2!A:F,6,0) -> JAKARTA | Q7: PT. Mahakarya Sukses Indonesia | R7: 70/30 | S7: 5730000 | T7: 4011000 | U7: 1719000 | W7: 5729876 | X7: 0 | Y7: =W7+X7 -> 5729876
A8: DM20260007 | B8: Anisa Nurajijah | C8: =vlookup(B8,Sheet3!B:C,2,0) -> jl.lingkar kota | D8: =vlookup(B8,Sheet3!B:D,3,0) -> 38319 | E8: =vlookup(B8,Sheet3!B:F,5,0) -> subang, jawa barat | F8: =vlookup(B8,Sheet3!B:H,7,0) -> SLTA | G8: =vlookup(B8,Sheet3!B:I,8,0) -> 089524367514 | H8: =vlookup(B8,Sheet3!B:J,9,0) -> uchanel1983@gmail.com | I8: SPB/SPG Toko | J8: =vlookup(B8,Sheet2!B:D,3,0) -> OSCAR GEMILANG | K8: =vlookup(A8,Sheet2!A:E,5,0) -> KETAPANG | M8: 45957 | N8: 46266 | O8: 46265 | P8: =VLOOKUP(A8,Sheet2!A:F,6,0) -> PONTIANAK | Q8: PT. Mahakarya Sukses Indonesia | R8: 70/30 | S8: 3562000 | T8: 2493400 | U8: 1068600 | W8: 3561801 | X8: 0 | Y8: =W8+X8 -> 3561801
A9: DM20260008 | B9: Annisa | C9: =vlookup(B9,Sheet3!B:C,2,0) -> Jl.keramat gg satu dua rt.10 no.37d kelurahan sungai bilu kecamatan banjarmasin timur banjarmasin 70236 | D9: =vlookup(B9,Sheet3!B:D,3,0) -> 33553 | E9: =vlookup(B9,Sheet3!B:F,5,0) -> Banjarmasin | F9: =vlookup(B9,Sheet3!B:H,7,0) -> SLTA | G9: =vlookup(B9,Sheet3!B:I,8,0) -> 085754771101 | H9: =vlookup(B9,Sheet3!B:J,9,0) -> Annisaauliani11@gmail.com | I9: SPB/SPG Toko | J9: =vlookup(B9,Sheet2!B:D,3,0) -> POS ELEKTRONIK | K9: =vlookup(A9,Sheet2!A:E,5,0) -> BANJARMASIN | L9: =VLOOKUP(B9,Sheet3!B:L,11,0) -> 0511915910 | M9: 42826 | N9: 46266 | O9: 46265 | P9: =VLOOKUP(A9,Sheet2!A:F,6,0) -> BANJARMASIN | Q9: PT. Mahakarya Sukses Indonesia | R9: 70/30 | S9: 3856000 | T9: 2699200 | U9: 1156800 | W9: 3855894 | X9: 0 | Y9: =W9+X9 -> 3855894
A10: DM20260009 | B10: Ardi Basri | C10: =vlookup(B10,Sheet3!B:C,2,0) -> Vila Mutiara Asri VII No.12 | D10: =vlookup(B10,Sheet3!B:D,3,0) -> 34283 | E10: =vlookup(B10,Sheet3!B:F,5,0) -> Makassar | F10: =vlookup(B10,Sheet3!B:H,7,0) -> S1 | G10: =vlookup(B10,Sheet3!B:I,8,0) -> 085756517715 | H10: =vlookup(B10,Sheet3!B:J,9,0) -> ardibasri948@gmail.com | I10: GTM | J10: =vlookup(B10,Sheet2!B:D,3,0) -> MAKASSAR | K10: =vlookup(A10,Sheet2!A:E,5,0) -> MAKASSAR | L10: =VLOOKUP(B10,Sheet3!B:L,11,0) -> 0251548799 | M10: =vlookup(B10,'data staffinc_3'!B:I,7,0) -> 46175 | N10: 46266 | O10: =vlookup(B10,'data staffinc_3'!B:I,8,0) -> 46265 | P10: =VLOOKUP(A10,Sheet2!A:F,6,0) -> MAKASSAR | Q10: PT. Mahakarya Sukses Indonesia | R10: Khusus | T10: 5128000 | W10: 4977815 | X10: 150000 | Y10: =W10+X10 -> 5127815
A11: DM20260010 | B11: Arenta putri Widyaningsih | C11: =vlookup(B11,Sheet3!B:C,2,0) -> Jl.margoyoso IV rt 6/4 | D11: =vlookup(B11,Sheet3!B:D,3,0) -> 38188 | E11: =vlookup(B11,Sheet3!B:F,5,0) -> Semarang | F11: =vlookup(B11,Sheet3!B:H,7,0) -> SLTA | G11: =vlookup(B11,Sheet3!B:I,8,0) -> 08973123823 | H11: =vlookup(B11,Sheet3!B:J,9,0) -> arentaputriwidyaningsih200704@gmail.com | I11: SPB/SPG Toko | J11: =vlookup(B11,Sheet2!B:D,3,0) -> ADA SILIWANGI | K11: =vlookup(A11,Sheet2!A:E,5,0) -> SEMARANG | L11: =VLOOKUP(B11,Sheet3!B:L,11,0) -> 8715675648 | M11: 46146 | N11: 46266 | O11: 46265 | P11: =VLOOKUP(A11,Sheet2!A:F,6,0) -> SEMARANG | Q11: PT. Mahakarya Sukses Indonesia | R11: 70/30 | S11: 3702000 | T11: 2591400 | U11: 1110600 | W11: 3701709 | X11: 0 | Y11: =W11+X11 -> 3701709
A12: DM20260011 | B12: Ari Kusumawati | C12: =vlookup(B12,Sheet3!B:C,2,0) -> Jl.Gunung Sahari 9 RT.005 RW.004 Kel.Gunung Sahari Utara, kec.Sawah besar, Jakarta pusat | D12: =vlookup(B12,Sheet3!B:D,3,0) -> 32778 | E12: =vlookup(B12,Sheet3!B:F,5,0) -> Jakarta | F12: =vlookup(B12,Sheet3!B:H,7,0) -> SLTA | G12: =vlookup(B12,Sheet3!B:I,8,0) -> 085780008440 | H12: =vlookup(B12,Sheet3!B:J,9,0) -> nayarengganis25@gmail.com | I12: SPB/SPG Outlet | J12: =vlookup(B12,Sheet2!B:D,3,0) -> MALL KELAPA GADING | K12: =vlookup(A12,Sheet2!A:E,5,0) -> JAKARTA | L12: =VLOOKUP(B12,Sheet3!B:L,11,0) -> 6840428964 | M12: 44844 | N12: 46266 | O12: 46265 | P12: =VLOOKUP(A12,Sheet2!A:F,6,0) -> JAKARTA | Q12: PT. Mahakarya Sukses Indonesia | R12: Khusus | S12: 5730000 | T12: 5730000 | W12: 5729876 | X12: 600000 | Y12: =W12+X12 -> 6329876
A13: DM20260012 | B13: Ayu Novitaningsih | C13: =vlookup(B13,Sheet3!B:C,2,0) -> Dusun bringin RT02 RW01 Desa Karangwaluh kecamatan Sampung Kabupaten Ponorogo | D13: =vlookup(B13,Sheet3!B:D,3,0) -> 35012 | E13: =vlookup(B13,Sheet3!B:F,5,0) -> Ponorogo | F13: =vlookup(B13,Sheet3!B:H,7,0) -> SLTA | G13: =vlookup(B13,Sheet3!B:I,8,0) -> 082141638390 | H13: =vlookup(B13,Sheet3!B:J,9,0) -> ayumamay09@gmail.com | I13: SPB/SPG Toko | J13: =vlookup(B13,Sheet2!B:D,3,0) -> CV SAMI JAYA | K13: =vlookup(A13,Sheet2!A:E,5,0) -> PONOROGO | L13: =VLOOKUP(B13,Sheet3!B:L,11,0) -> 2891046822 | M13: 46015 | N13: 46266 | O13: 46265 | P13: =VLOOKUP(A13,Sheet2!A:F,6,0) -> SURABAYA | Q13: PT. Mahakarya Sukses Indonesia | R13: 70/30 | S13: 2550000 | T13: 1785000 | U13: 765000 | W13: 2549876 | X13: 0 | Y13: =W13+X13 -> 2549876
A14: DM20260013 | B14: Bagus Dwi Ardiansyah | C14: =vlookup(B14,Sheet3!B:C,2,0) -> PONDOK BENOWO INDAH BO 14 SURABAYA | D14: =vlookup(B14,Sheet3!B:D,3,0) -> 35663 | E14: =vlookup(B14,Sheet3!B:F,5,0) -> SURABAYA | F14: =vlookup(B14,Sheet3!B:H,7,0) -> S1 | G14: =vlookup(B14,Sheet3!B:I,8,0) -> 081283148912 | H14: =vlookup(B14,Sheet3!B:J,9,0) -> bagusdwiar@gmail.com | I14: SPB/SPG MT | J14: =vlookup(B14,Sheet2!B:D,3,0) -> HARTONO BUKIT DARMO | K14: =vlookup(A14,Sheet2!A:E,5,0) -> SURABAYA | L14: =VLOOKUP(B14,Sheet3!B:L,11,0) -> 2582405442 | M14: 46047 | N14: 46266 | O14: 46265 | P14: =VLOOKUP(A14,Sheet2!A:F,6,0) -> SURABAYA | Q14: PT. Mahakarya Sukses Indonesia | R14: Khusus | S14: 5289000 | T14: 5289000 | W14: 5288796 | X14: 0 | Y14: =W14+X14 -> 5288796
A15: DM20260014 | B15: Balqis Ayudia Pramesti | C15: =vlookup(B15,Sheet3!B:C,2,0) -> pandak rt 04 rw 02 jatipandak sambeng | D15: =vlookup(B15,Sheet3!B:D,3,0) -> 38044 | E15: =vlookup(B15,Sheet3!B:F,5,0) -> sidoarjo | F15: =vlookup(B15,Sheet3!B:H,7,0) -> SLTA | G15: =vlookup(B15,Sheet3!B:I,8,0) -> 089514649794 | H15: =vlookup(B15,Sheet3!B:J,9,0) -> balqisayudia123@gmail.com | I15: SPB/SPG MT | J15: =vlookup(B15,Sheet2!B:D,3,0) -> HARTONO BUKIT DARMO | K15: =vlookup(A15,Sheet2!A:E,5,0) -> SURABAYA | L15: =VLOOKUP(B15,Sheet3!B:L,11,0) -> 5065480881 | P15: =VLOOKUP(A15,Sheet2!A:F,6,0) -> SURABAYA | Q15: PT. Stein Perkasa Internasional | R15: Khusus | S15: 5289000 | T15: 5289000
A16: DM20260015 | B16: Chamida Ananda Septiani | C16: =vlookup(B16,Sheet3!B:C,2,0) -> Dusun 1 Kasimbar Tengah Desa Kasimbar Kecamatan Kasimbar | D16: =vlookup(B16,Sheet3!B:D,3,0) -> 36429 | E16: =vlookup(B16,Sheet3!B:F,5,0) -> Parigi | F16: =vlookup(B16,Sheet3!B:H,7,0) -> SLTA | G16: =vlookup(B16,Sheet3!B:I,8,0) -> 085298512206 | H16: =vlookup(B16,Sheet3!B:J,9,0) -> chamidaananda@gmail.com | I16: SPB/SPG Toko | J16: =vlookup(B16,Sheet2!B:D,3,0) -> SMART KITCHEN | K16: =vlookup(A16,Sheet2!A:E,5,0) -> PALU | M16: 46240 | N16: 46266 | O16: 46265 | P16: =VLOOKUP(A16,Sheet2!A:F,6,0) -> MAKASSAR | Q16: PT. Mahakarya Sukses Indonesia | R16: 70/30 | S16: 4149000 | T16: 2904300 | U16: 1244700 | W16: 4148179 | X16: 0 | Y16: =W16+X16 -> 4148179
A17: DM20260016 | B17: Charles Setiawan | C17: =vlookup(B17,Sheet3!B:C,2,0) -> DUSUN TERATAI INDAH | D17: =vlookup(B17,Sheet3!B:D,3,0) -> 34794 | E17: =vlookup(B17,Sheet3!B:F,5,0) -> KETAPANG | F17: =vlookup(B17,Sheet3!B:H,7,0) -> SLTA | G17: =vlookup(B17,Sheet3!B:I,8,0) -> 085651034052 | H17: =vlookup(B17,Sheet3!B:J,9,0) -> cs5657394@gmail.com | I17: SPB/SPG Toko | J17: =vlookup(B17,Sheet2!B:D,3,0) -> TOKO PUTRA ELEKTRONIK | K17: =vlookup(A17,Sheet2!A:E,5,0) -> PONTIANAK | L17: =VLOOKUP(B17,Sheet3!B:L,11,0) -> 1711654599 | M17: 45845 | N17: 46266 | O17: 46265 | P17: =VLOOKUP(A17,Sheet2!A:F,6,0) -> PONTIANAK | Q17: PT. Mahakarya Sukses Indonesia | R17: 70/30 | S17: 3206000 | T17: 2244200 | U17: 961800 | W17: 3205220 | X17: 0 | Y17: =W17+X17 -> 3205220
A18: DM20260017 | B18: Christiana Dwi Jayanti | C18: =vlookup(B18,Sheet3!B:C,2,0) -> KARANGPUTIH TLOGO PRAMBANAN KLATEN RT 009 RW 006 | D18: =vlookup(B18,Sheet3!B:D,3,0) -> 35980 | E18: =vlookup(B18,Sheet3!B:F,5,0) -> KLATEN | F18: =vlookup(B18,Sheet3!B:H,7,0) -> SLTA | G18: =vlookup(B18,Sheet3!B:I,8,0) -> 085174367440 | H18: =vlookup(B18,Sheet3!B:J,9,0) -> christianadwijayanti78@gmail.com | I18: SPB/SPG Toko | J18: =vlookup(B18,Sheet2!B:D,3,0) -> A TAKRIB LIFE STYLE | K18: =vlookup(A18,Sheet2!A:E,5,0) -> YOGYAKARTA | L18: =VLOOKUP(B18,Sheet3!B:L,11,0) -> 0601290102 | M18: 45627 | N18: 46266 | O18: 46265 | P18: =VLOOKUP(A18,Sheet2!A:F,6,0) -> SEMARANG | Q18: PT. Mahakarya Sukses Indonesia | R18: 70/30 | S18: 2828000 | T18: 1979600 | U18: 848400 | W18: 2827593 | X18: 0 | Y18: =W18+X18 -> 2827593
A19: DM20260018 | B19: Darussalam | C19: =vlookup(B19,Sheet3!B:C,2,0) -> Dsn Dendelu. kel Tarobok. kec baebubta . luwu utara | D19: =vlookup(B19,Sheet3!B:D,3,0) -> 34354 | E19: =vlookup(B19,Sheet3!B:F,5,0) -> luwu utara | F19: =vlookup(B19,Sheet3!B:H,7,0) -> SLTA | G19: =vlookup(B19,Sheet3!B:I,8,0) -> 089501607968 | H19: =vlookup(B19,Sheet3!B:J,9,0) -> salamdarulmito26@gmail.com | I19: SPB/SPG Toko | J19: =vlookup(B19,Sheet2!B:D,3,0) -> GRAND TOSERBA PENGAYOMAN | K19: =vlookup(A19,Sheet2!A:E,5,0) -> MAKASSAR | L19: =VLOOKUP(B19,Sheet3!B:L,11,0) -> 7990187805 | M19: 45803 | N19: 46266 | O19: 46265 | P19: =VLOOKUP(A19,Sheet2!A:F,6,0) -> MAKASSAR | Q19: PT. Mahakarya Sukses Indonesia | R19: 70/30 | S19: 4149000 | T19: 2904300 | U19: 1244700 | W19: 4148179 | X19: 0 | Y19: =W19+X19 -> 4148179
A20: DM20260019 | B20: Deni Lindiansah | C20: =vlookup(B20,Sheet3!B:C,2,0) -> Jln Panyandaan rt 3 rw 07 Kel mandalamekar Kec Cimenyan Kab Bandung | D20: =vlookup(B20,Sheet3!B:D,3,0) -> 36862 | E20: =vlookup(B20,Sheet3!B:F,5,0) -> Bandung | F20: =vlookup(B20,Sheet3!B:H,7,0) -> SLTA | G20: =vlookup(B20,Sheet3!B:I,8,0) -> 089670444004 | H20: =vlookup(B20,Sheet3!B:J,9,0) -> denilnndsh@gmail.com | I20: SPB/SPG MT | J20: =vlookup(B20,Sheet2!B:D,3,0) -> HARTONO BANDUNG | K20: =vlookup(A20,Sheet2!A:E,5,0) -> BANDUNG | L20: =VLOOKUP(B20,Sheet3!B:L,11,0) -> 2832076288 | M20: 46036 | N20: 46266 | O20: 46265 | P20: =VLOOKUP(A20,Sheet2!A:F,6,0) -> BANDUNG | Q20: PT. Mahakarya Sukses Indonesia | R20: Khusus | S20: 4738000 | T20: 4738000 | W20: 4737678 | X20: 0 | Y20: =W20+X20 -> 4737678
A21: DM20260020 | B21: Devi Eriyanti | C21: =vlookup(B21,Sheet3!B:C,2,0) -> Jl Moh Roem | D21: =vlookup(B21,Sheet3!B:D,3,0) -> 34969 | E21: =vlookup(B21,Sheet3!B:F,5,0) -> Bontang | F21: =vlookup(B21,Sheet3!B:H,7,0) -> SLTA | G21: =vlookup(B21,Sheet3!B:I,8,0) -> 08135054923 | H21: =vlookup(B21,Sheet3!B:J,9,0) -> Vira08359@gmail.com | I21: SPB/SPG Toko | J21: =vlookup(B21,Sheet2!B:D,3,0) -> PONDOK ELEKTRONIK BANJARBARU | K21: =vlookup(A21,Sheet2!A:E,5,0) -> BANJARMASIN | L21: =VLOOKUP(B21,Sheet3!B:L,11,0) -> 6705117156 | M21: 46008 | N21: 46266 | O21: 46265 | P21: =VLOOKUP(A21,Sheet2!A:F,6,0) -> BANJARMASIN | Q21: PT. Mahakarya Sukses Indonesia | R21: 70/30 | S21: 3856000 | T21: 2699200 | U21: 1156800 | W21: 3843037 | X21: 0 | Y21: =W21+X21 -> 3843037
A22: DM20260021 | B22: Devi Isvaradilla Agrully | C22: =vlookup(B22,Sheet3!B:C,2,0) -> Jl MINANGKABAU NO 101 RT 04 BATU AMPAR | D22: =vlookup(B22,Sheet3!B:D,3,0) -> 37134 | E22: =vlookup(B22,Sheet3!B:F,5,0) -> Balikpapan | F22: =vlookup(B22,Sheet3!B:H,7,0) -> SLTA | G22: =vlookup(B22,Sheet3!B:I,8,0) -> 085656950939 | H22: =vlookup(B22,Sheet3!B:J,9,0) -> deviisvaradilla16@gmail.com | I22: SPB/SPG Toko | J22: =vlookup(B22,Sheet2!B:D,3,0) -> NUANSA BALIKPAPAN | K22: =vlookup(A22,Sheet2!A:E,5,0) -> BALIKPAPAN | L22: =VLOOKUP(B22,Sheet3!B:L,11,0) -> 7810287131 | M22: 45824 | N22: 46266 | O22: 46265 | P22: =VLOOKUP(A22,Sheet2!A:F,6,0) -> SAMARINDA | Q22: PT. Mahakarya Sukses Indonesia | R22: 70/30 | S22: 3857000 | T22: 2699900 | U22: 1157100 | W22: 3856694 | X22: 0 | Y22: =W22+X22 -> 3856694
A23: DM20260022 | B23: Dewi Pramudita | C23: =vlookup(B23,Sheet3!B:C,2,0) -> PALEMBANG, PLAJU | D23: =vlookup(B23,Sheet3!B:D,3,0) -> 39415 | E23: =vlookup(B23,Sheet3!B:F,5,0) -> Palembang | F23: =vlookup(B23,Sheet3!B:H,7,0) -> SLTA | G23: =vlookup(B23,Sheet3!B:I,8,0) -> 0895320866466 | H23: =vlookup(B23,Sheet3!B:J,9,0) -> pramudithadewi62@gmail.com | I23: SPB/SPG Toko | J23: =vlookup(B23,Sheet2!B:D,3,0) -> DAPOER MUTIARA (CV PELITA MAS) | K23: =vlookup(A23,Sheet2!A:E,5,0) -> PALEMBANG | L23: =VLOOKUP(B23,Sheet3!B:L,11,0) -> 1160615202 | M23: 46256 | N23: 46266 | O23: 46265 | P23: =VLOOKUP(A23,Sheet2!A:F,6,0) -> PALEMBANG | Q23: PT. Mahakarya Sukses Indonesia | R23: 70/30 | S23: 4193000 | T23: 2935100 | U23: 1257900 | W23: 4192837 | X23: 0 | Y23: =W23+X23 -> 4192837
A24: DM20260023 | B24: Diah Catur Apriani | C24: =vlookup(B24,Sheet3!B:C,2,0) -> Grecol, rt1 rw3 Kalimanah Kab purbalingga | D24: =vlookup(B24,Sheet3!B:D,3,0) -> 34432 | E24: =vlookup(B24,Sheet3!B:F,5,0) -> Banyumas | F24: =vlookup(B24,Sheet3!B:H,7,0) -> SLTA | G24: =vlookup(B24,Sheet3!B:I,8,0) -> 081568400117 | H24: =vlookup(B24,Sheet3!B:J,9,0) -> caturdiah95@gmail.com | I24: SPB/SPG Toko | J24: =vlookup(B24,Sheet2!B:D,3,0) -> DEPO PELITA | K24: SEMARANG | L24: =VLOOKUP(B24,Sheet3!B:L,11,0) -> 3581118790 | M24: 45714 | N24: 46266 | O24: 46265 | P24: =VLOOKUP(A24,Sheet2!A:F,6,0) -> SEMARANG | Q24: PT. Mahakarya Sukses Indonesia | R24: 70/30 | S24: 3702000 | T24: 2591400 | U24: 1110600 | W24: 2474598 | X24: 0 | Y24: =W24+X24 -> 2474598
A25: DM20260024 | B25: Dimas Setya Nugraha | C25: =vlookup(B25,Sheet3!B:C,2,0) -> Dusun Ngabeyan, Desa Nguwet, RT/Rw 002/002 Kecamatan Kranggan, Kabupaten Temanggung | D25: =vlookup(B25,Sheet3!B:D,3,0) -> 37094 | E25: =vlookup(B25,Sheet3!B:F,5,0) -> Temanggung | F25: =vlookup(B25,Sheet3!B:H,7,0) -> S1 | G25: =vlookup(B25,Sheet3!B:I,8,0) -> 085713753192 | H25: =vlookup(B25,Sheet3!B:J,9,0) -> setyadimas021@gmail.com | I25: SPB/SPG Toko | J25: =vlookup(B25,Sheet2!B:D,3,0) -> CANDI ELEKTRONIK | K25: =vlookup(A25,Sheet2!A:E,5,0) -> SUKOHARJO | L25: 1541007488 | P25: =VLOOKUP(A25,Sheet2!A:F,6,0) -> SEMARANG | Q25: PT. Mahakarya Sukses Indonesia | R25: 70/30 | S25: 2500000 | T25: 1750000 | U25: 750000
A26: DM20260025 | B26: Dinda Sri Rahayu | C26: =vlookup(B26,Sheet3!B:C,2,0) -> kp. pangsor rt.08/10 sukamantri, paseh | D26: =vlookup(B26,Sheet3!B:D,3,0) -> 36483 | E26: =vlookup(B26,Sheet3!B:F,5,0) -> Bandung | F26: =vlookup(B26,Sheet3!B:H,7,0) -> SLTA | G26: =vlookup(B26,Sheet3!B:I,8,0) -> 089659753361 | H26: =vlookup(B26,Sheet3!B:J,9,0) -> dindasrirahayu9@gmail.com | I26: SPB/SPG Toko | J26: =vlookup(B26,Sheet2!B:D,3,0) -> LOGIN MEGASTORE (ABC) | K26: =vlookup(A26,Sheet2!A:E,5,0) -> BANDUNG | L26: =VLOOKUP(B26,Sheet3!B:L,11,0) -> 3760618135 | M26: 45576 | N26: 46266 | O26: 46265 | P26: =VLOOKUP(A26,Sheet2!A:F,6,0) -> BANDUNG | Q26: PT. Mahakarya Sukses Indonesia | R26: 70/30 | S26: 4738000 | T26: 3316600 | U26: 1421400 | W26: 4737678 | X26: 0 | Y26: =W26+X26 -> 4737678
A27: DM20260026 | B27: Ela Siska Ariatun | C27: =vlookup(B27,Sheet3!B:C,2,0) -> JLN. MODANG GG.RUKUN | D27: =vlookup(B27,Sheet3!B:D,3,0) -> 37477 | E27: =vlookup(B27,Sheet3!B:F,5,0) -> MOJOKERTO | F27: =vlookup(B27,Sheet3!B:H,7,0) -> SLTA | G27: =vlookup(B27,Sheet3!B:I,8,0) -> 082358812078 | H27: =vlookup(B27,Sheet3!B:J,9,0) -> elasiska01@gmail.com | I27: SPB/SPG Toko | J27: =vlookup(B27,Sheet2!B:D,3,0) -> NUANSA ELEKTRONIC TANAH GROGOT | K27: =vlookup(A27,Sheet2!A:E,5,0) -> PASER | L27: =VLOOKUP(B27,Sheet3!B:L,11,0) -> 7815831241 | M27: 45647 | N27: 46266 | O27: 46265 | P27: =VLOOKUP(A27,Sheet2!A:F,6,0) -> SAMARINDA | Q27: PT. Mahakarya Sukses Indonesia | R27: 70/30 | S27: 3777000 | T27: 2643900 | U27: 1133100 | W27: 3776998 | X27: 0 | Y27: =W27+X27 -> 3776998
A28: DM20260027 | B28: Elisa Putra Afdiono | C28: =vlookup(B28,Sheet3!B:C,2,0) -> Margorejo 2G nomer 32 | D28: =vlookup(B28,Sheet3!B:D,3,0) -> 35132 | E28: =vlookup(B28,Sheet3!B:F,5,0) -> Surabaya | F28: =vlookup(B28,Sheet3!B:H,7,0) -> SLTA | G28: =vlookup(B28,Sheet3!B:I,8,0) -> 089686949505 | H28: =vlookup(B28,Sheet3!B:J,9,0) -> zolla041123@gmail.com | I28: SPB/SPG Toko | J28: =vlookup(B28,Sheet2!B:D,3,0) -> TOENG MARKET JAKSA AGUNG SUPRAPTO | K28: =vlookup(A28,Sheet2!A:E,5,0) -> SURABAYA | L28: =VLOOKUP(B28,Sheet3!B:L,11,0) -> 5600289308 | M28: 44077 | N28: 46266 | O28: 46265 | P28: =VLOOKUP(A28,Sheet2!A:F,6,0) -> SURABAYA | Q28: PT. Mahakarya Sukses Indonesia | R28: 70/30 | S28: 5289000 | T28: 3702300 | U28: 1586700 | W28: 5288796 | X28: 0 | Y28: =W28+X28 -> 5288796
A29: DM20260028 | B29: Elisabeth Noviyanti Ayu N | C29: =vlookup(B29,Sheet3!B:C,2,0) -> Dusun Meno, rt003/rw004 Desa Rhee Loka Kecamatan Rhee Kabupaten Sumbawa | D29: =vlookup(B29,Sheet3!B:D,3,0) -> 35751 | E29: =vlookup(B29,Sheet3!B:F,5,0) -> Sumbawa | F29: =vlookup(B29,Sheet3!B:H,7,0) -> S1 | G29: =vlookup(B29,Sheet3!B:I,8,0) -> 087865850309 | H29: =vlookup(B29,Sheet3!B:J,9,0) -> elisabethayu1997@gmail.com | I29: SPB/SPG Toko | J29: =vlookup(B29,Sheet2!B:D,3,0) -> TOKO JAYA KITCHEN LOMBOK | K29: =vlookup(A29,Sheet2!A:E,5,0) -> MATARAM | L29: =VLOOKUP(B29,Sheet3!B:L,11,0) -> 0562190331 | M29: =vlookup(B29,'data staffinc_3'!B:I,7,0) -> 45920 | N29: 46266 | O29: =vlookup(B29,'data staffinc_3'!B:I,8,0) -> 46265 | P29: =VLOOKUP(A29,Sheet2!A:F,6,0) -> SURABAYA | Q29: PT. Mahakarya Sukses Indonesia | R29: Khusus | T29: 3020000 | W29: 3019015 | X29: 0 | Y29: =W29+X29 -> 3019015
A30: DM20260029 | B30: Eza Adela | C30: =vlookup(B30,Sheet3!B:C,2,0) -> Dusun Danau Kuala Selakau | D30: =vlookup(B30,Sheet3!B:D,3,0) -> 37747 | E30: =vlookup(B30,Sheet3!B:F,5,0) -> Selakau , Kalimantan barat Kabupaten Sambas | F30: =vlookup(B30,Sheet3!B:H,7,0) -> SLTA | G30: =vlookup(B30,Sheet3!B:I,8,0) -> 085656271235 | H30: =vlookup(B30,Sheet3!B:J,9,0) -> adelaeza021@gmail.com | I30: SPB/SPG Toko | J30: =vlookup(B30,Sheet2!B:D,3,0) -> HIBURAN BARU SINGKAWANG | K30: =vlookup(A30,Sheet2!A:E,5,0) -> PONTIANAK | L30: =VLOOKUP(B30,Sheet3!B:L,11,0) -> 8171876893 | M30: 46119 | N30: 46266 | O30: 46265 | P30: =VLOOKUP(A30,Sheet2!A:F,6,0) -> PONTIANAK | Q30: PT. Mahakarya Sukses Indonesia | R30: 70/30 | S30: 3248000 | T30: 2273600 | U30: 974400 | W30: 3247387 | X30: 0 | Y30: =W30+X30 -> 3247387
A31: DM20260030 | B31: Fadhila Rahmatika Haya | C31: =vlookup(B31,Sheet3!B:C,2,0) -> Sangkrah RT 2 RW 11 kelurahan Sangkrah kecamatan pasar Kliwon Surakarta Jawa tengah | D31: =vlookup(B31,Sheet3!B:D,3,0) -> 36788 | E31: =vlookup(B31,Sheet3!B:F,5,0) -> Surakarta | F31: =vlookup(B31,Sheet3!B:H,7,0) -> SLTA | G31: =vlookup(B31,Sheet3!B:I,8,0) -> 085725663034 | H31: =vlookup(B31,Sheet3!B:J,9,0) -> fadhilaarh19@gmail.com | I31: SPB/SPG Toko | J31: =vlookup(B31,Sheet2!B:D,3,0) -> CANDI ELEKTRONIC 310 | K31: =vlookup(A31,Sheet2!A:E,5,0) -> SEMARANG | L31: =VLOOKUP(B31,Sheet3!B:L,11,0) -> 1530616408 | P31: =VLOOKUP(A31,Sheet2!A:F,6,0) -> SEMARANG | Q31: PT. Mahakarya Sukses Indonesia | R31: 70/30 | S31: 3702000 | T31: 2591400 | U31: 1110600
A32: DM20260031 | B32: Fahrur Reza | C32: =vlookup(B32,Sheet3!B:C,2,0) -> Kalibata Selatan no 41, RT 002 RW 009 Kelurahan Kalibata Kecamatan Pancoran Jakarta Selatan 12740 | D32: =vlookup(B32,Sheet3!B:D,3,0) -> 34895 | E32: =vlookup(B32,Sheet3!B:F,5,0) -> Jakarta | F32: =vlookup(B32,Sheet3!B:H,7,0) -> S1 | G32: =vlookup(B32,Sheet3!B:I,8,0) -> 087851843056 | H32: =vlookup(B32,Sheet3!B:J,9,0) -> ezaenii@gmail.com | I32: SPB/SPG Toko | J32: =vlookup(B32,Sheet2!B:D,3,0) -> SPN HOUSEWARE | K32: =vlookup(A32,Sheet2!A:E,5,0) -> JAKARTA | L32: =VLOOKUP(B32,Sheet3!B:L,11,0) -> 1280346540 | M32: 45712 | N32: 46266 | O32: 46265 | P32: =VLOOKUP(A32,Sheet2!A:F,6,0) -> JAKARTA | Q32: PT. Mahakarya Sukses Indonesia | R32: 70/30 | S32: 5730000 | T32: 4011000 | U32: 1719000 | W32: 5729876 | X32: 0 | Y32: =W32+X32 -> 5729876
A33: DM20260032 | B33: Faisol Adha | C33: =vlookup(B33,Sheet3!B:C,2,0) -> DSN. PULE UTARA RT:002/RW:001 PULE, KANDAT | D33: =vlookup(B33,Sheet3!B:D,3,0) -> 34597 | E33: =vlookup(B33,Sheet3!B:F,5,0) -> KEDIRI | F33: =vlookup(B33,Sheet3!B:H,7,0) -> SLTA | G33: =vlookup(B33,Sheet3!B:I,8,0) -> 085748348360 | H33: =vlookup(B33,Sheet3!B:J,9,0) -> faisol.adha03@gmail.com | I33: SPB/SPG Outlet | J33: =vlookup(B33,Sheet2!B:D,3,0) -> TUNJUNGAN PLAZA | K33: =vlookup(A33,Sheet2!A:E,5,0) -> SURABAYA | L33: =VLOOKUP(B33,Sheet3!B:L,11,0) -> 8220741924 | M33: 45147 | N33: 46266 | O33: 46265 | P33: =VLOOKUP(A33,Sheet2!A:F,6,0) -> SURABAYA | Q33: PT. Mahakarya Sukses Indonesia | R33: Khusus | S33: 5289000 | T33: 5289000 | W33: 5288796 | X33: 600000 | Y33: =W33+X33 -> 5888796
A34: DM20260033 | B34: Fatra Laily | C34: =vlookup(B34,Sheet3!B:C,2,0) -> Jln barukang 6 no 2 | D34: =vlookup(B34,Sheet3!B:D,3,0) -> 35910 | E34: =vlookup(B34,Sheet3!B:F,5,0) -> Makassar | F34: =vlookup(B34,Sheet3!B:H,7,0) -> S1 | G34: =vlookup(B34,Sheet3!B:I,8,0) -> 089684056159 | H34: =vlookup(B34,Sheet3!B:J,9,0) -> Fatralaily98@gmail.com | I34: SPB/SPG Toko | J34: =vlookup(B34,Sheet2!B:D,3,0) -> SEMERU SARAPPO | K34: =vlookup(A34,Sheet2!A:E,5,0) -> MAKASSAR | L34: =VLOOKUP(B34,Sheet3!B:L,11,0) -> 7685985489 | M34: 46128 | N34: 46266 | O34: 46265 | P34: =VLOOKUP(A34,Sheet2!A:F,6,0) -> MAKASSAR | Q34: PT. Mahakarya Sukses Indonesia | R34: 70/30 | S34: 4149000 | T34: 2904300 | U34: 1244700 | W34: 4148179 | X34: 0 | Y34: =W34+X34 -> 4148179
A35: DM20260034 | B35: Febry Valentino | C35: =vlookup(B35,Sheet3!B:C,2,0) -> Jl. Berlian, No.i04, Bontang lestari | D35: =vlookup(B35,Sheet3!B:D,3,0) -> 38030 | E35: =vlookup(B35,Sheet3!B:F,5,0) -> Bontang | F35: =vlookup(B35,Sheet3!B:H,7,0) -> SLTA | G35: =vlookup(B35,Sheet3!B:I,8,0) -> 081251882460 | H35: =vlookup(B35,Sheet3!B:J,9,0) -> febrivalentino24@gmail.com | I35: SPB/SPG Toko | J35: =vlookup(B35,Sheet2!B:D,3,0) -> NUANSA ELEKTRONIK BONTANG | K35: =vlookup(A35,Sheet2!A:E,5,0) -> BONTANG | L35: =VLOOKUP(B35,Sheet3!B:L,11,0) -> 6705379401 | M35: 45915 | N35: 46266 | O35: 46265 | P35: =VLOOKUP(A35,Sheet2!A:F,6,0) -> SAMARINDA | Q35: PT. Mahakarya Sukses Indonesia | R35: 70/30 | S35: 3800000 | T35: 2660000 | U35: 1140000 | W35: 3799480 | X35: 0 | Y35: =W35+X35 -> 3799480
A36: DM20260035 | B36: Ferdinand Anthonius Harianja | C36: =vlookup(B36,Sheet3!B:C,2,0) -> Dusun III Perum Johar II Jl. Semangka No.11 | D36: =vlookup(B36,Sheet3!B:D,3,0) -> 36422 | E36: =vlookup(B36,Sheet3!B:F,5,0) -> Payakumbuh | F36: =vlookup(B36,Sheet3!B:H,7,0) -> S1 | G36: =vlookup(B36,Sheet3!B:I,8,0) -> 089512709094 | H36: =vlookup(B36,Sheet3!B:J,9,0) -> ferdinandanthonius1@gmail.com | I36: =vlookup(A36,Sheet2!A:E,3,0) -> GTM | J36: =vlookup(B36,Sheet2!B:D,3,0) -> Kota Medan | K36: =vlookup(A36,Sheet2!A:E,5,0) -> MEDAN | L36: =VLOOKUP(B36,Sheet3!B:L,11,0) -> 2421392678 | M36: =vlookup(B36,'data staffinc_3'!B:I,7,0) -> 46174 | N36: 46266 | O36: =vlookup(B36,'data staffinc_3'!B:I,8,0) -> 46265 | P36: =VLOOKUP(A36,Sheet2!A:F,6,0) -> MEDAN | Q36: PT. Mahakarya Sukses Indonesia | R36: Khusus | T36: 5353000 | W36: 5202238 | X36: 150000 | Y36: =W36+X36 -> 5352238
A37: DM20260036 | B37: Ferdiyan | C37: =vlookup(B37,Sheet3!B:C,2,0) -> JL D.I PANJAITAN NO 08 RT 4 SUMBER REJO | D37: =vlookup(B37,Sheet3!B:D,3,0) -> 37670 | E37: =vlookup(B37,Sheet3!B:F,5,0) -> Balikpapan | F37: =vlookup(B37,Sheet3!B:H,7,0) -> SLTA | G37: =vlookup(B37,Sheet3!B:I,8,0) -> 087773201795 | H37: =vlookup(B37,Sheet3!B:J,9,0) -> Ferdiiiaaann@gmail.com | I37: SPB/SPG Toko | J37: =vlookup(B37,Sheet2!B:D,3,0) -> NUANSA BALIKPAPAN KILO | K37: =vlookup(A37,Sheet2!A:E,5,0) -> BALIKPAPAN | M37: 46202 | N37: 46266 | O37: 46265 | P37: =VLOOKUP(A37,Sheet2!A:F,6,0) -> SAMARINDA | Q37: PT. Mahakarya Sukses Indonesia | R37: 70/30 | S37: 3857000 | T37: 2699900 | U37: 1157100 | W37: 3856694 | X37: 0 | Y37: =W37+X37 -> 3856694
A38: DM20260037 | B38: Fiqri Nur Arfindiyani Putri | C38: =vlookup(B38,Sheet3!B:C,2,0) -> Bendo Rt07/Rw02 , Katur, Gayam Bojonegoro | D38: =vlookup(B38,Sheet3!B:D,3,0) -> 37614 | E38: =vlookup(B38,Sheet3!B:F,5,0) -> Surabaya | F38: =vlookup(B38,Sheet3!B:H,7,0) -> SLTA | G38: =vlookup(B38,Sheet3!B:I,8,0) -> 085604913433 | H38: =vlookup(B38,Sheet3!B:J,9,0) -> findyptr024@gmail.com | I38: SPB/SPG Toko | J38: =vlookup(B38,Sheet2!B:D,3,0) -> OGAN BANDULAN & OGAN BONDOWOSO | K38: =vlookup(A38,Sheet2!A:E,5,0) -> MALANG | M38: 46240 | N38: 46266 | O38: 46265 | P38: =VLOOKUP(A38,Sheet2!A:F,6,0) -> SURABAYA | Q38: PT. Mahakarya Sukses Indonesia | R38: 70/30 | S38: 3803000 | T38: 2662100 | U38: 1140900 | W38: 3736101 | X38: 0 | Y38: =W38+X38 -> 3736101
A39: DM20260038 | B39: Firanda | C39: =vlookup(B39,Sheet3!B:C,2,0) -> DUSUN IV DESA SUNGAI PINANG | D39: =vlookup(B39,Sheet3!B:D,3,0) -> 39056 | E39: =vlookup(B39,Sheet3!B:F,5,0) -> banyuasin | F39: =vlookup(B39,Sheet3!B:H,7,0) -> SLTA | G39: =vlookup(B39,Sheet3!B:I,8,0) -> 083872915839 | H39: =vlookup(B39,Sheet3!B:J,9,0) -> fanda5833@gmail.com | I39: SPB/SPG Toko | J39: =vlookup(B39,Sheet2!B:D,3,0) -> MDP SUPERSTORE | K39: =vlookup(A39,Sheet2!A:E,5,0) -> PALEMBANG | L39: =VLOOKUP(B39,Sheet3!B:L,11,0) -> 8435689139 | M39: 45567 | N39: 46266 | O39: 46265 | P39: =VLOOKUP(A39,Sheet2!A:F,6,0) -> PALEMBANG | Q39: PT. Mahakarya Sukses Indonesia | R39: 70/30 | S39: 4193000 | T39: 2935100 | U39: 1257900 | W39: 4192837 | X39: 0 | Y39: =W39+X39 -> 4192837
A40: DM20260039 | B40: Firda Duri Yatinal Ulya | C40: =vlookup(B40,Sheet3!B:C,2,0) -> JL.PEMUDA 2 GG.PENDAWA BLOK.E NO.86 RT.012 KEL.TEMINDUNG PERMAI KEC.SUNGAI PINANG | D40: =vlookup(B40,Sheet3!B:D,3,0) -> -659022 | E40: =vlookup(B40,Sheet3!B:F,5,0) -> SAMARINDA | F40: =vlookup(B40,Sheet3!B:H,7,0) -> SLTA | G40: =vlookup(B40,Sheet3!B:I,8,0) -> 082128843818 | H40: =vlookup(B40,Sheet3!B:J,9,0) -> firdaduriatinalulya@gmail.com | I40: SPB/SPG Toko | J40: =vlookup(B40,Sheet2!B:D,3,0) -> NUANSA IMAM BONJOL | K40: =vlookup(A40,Sheet2!A:E,5,0) -> SAMARINDA | L40: =VLOOKUP(B40,Sheet3!B:L,11,0) -> 7935297133 | M40: 43777 | N40: 46266 | O40: 46265 | P40: =VLOOKUP(A40,Sheet2!A:F,6,0) -> SAMARINDA | Q40: PT. Mahakarya Sukses Indonesia | R40: 70/30 | S40: 3984000 | T40: 2788800 | U40: 1195200 | V40: Resign per 20/9 | W40: 3983882 | X40: 0 | Y40: =W40+X40 -> 3983882
A41: DM20260040 | B41: Fitri Wulandari | C41: =vlookup(B41,Sheet3!B:C,2,0) -> Jl ampera III ujung rt 038 rw 003 | D41: =vlookup(B41,Sheet3!B:D,3,0) -> 32011 | E41: =vlookup(B41,Sheet3!B:F,5,0) -> Jember | F41: =vlookup(B41,Sheet3!B:H,7,0) -> SLTA | G41: =vlookup(B41,Sheet3!B:I,8,0) -> 085753994944 | H41: =vlookup(B41,Sheet3!B:J,9,0) -> Wulan.rhevian22@gmail.com | I41: SPB/SPG Toko | J41: =vlookup(B41,Sheet2!B:D,3,0) -> PONDOK ELEKTRONIK | K41: =vlookup(A41,Sheet2!A:E,5,0) -> BANJARMASIN | L41: =VLOOKUP(B41,Sheet3!B:L,11,0) -> 8275329891 | M41: 45323 | N41: 46266 | O41: 46265 | P41: =VLOOKUP(A41,Sheet2!A:F,6,0) -> BANJARMASIN | Q41: PT. Mahakarya Sukses Indonesia | R41: 70/30 | S41: 3856000 | T41: 2699200 | U41: 1156800 | W41: 3855894 | X41: 0 | Y41: =W41+X41 -> 3855894
A42: DM20260041 | B42: Fransiskus Xaverius Kuda Koten | C42: =vlookup(B42,Sheet3!B:C,2,0) -> JL. BANTIMURUNG NO 92,RT/RW:042/000, KEL/DESA: GUNUNG BAHAGIA, KEC: BALIKPAPAN SELATAN | D42: =vlookup(B42,Sheet3!B:D,3,0) -> 35212 | E42: =vlookup(B42,Sheet3!B:F,5,0) -> LARANTUKA | F42: =vlookup(B42,Sheet3!B:H,7,0) -> SLTA | G42: =vlookup(B42,Sheet3!B:I,8,0) -> 081239754529 | H42: =vlookup(B42,Sheet3!B:J,9,0) -> fxaverius048@gmail.com | I42: SPB/SPG Toko | J42: =vlookup(B42,Sheet2!B:D,3,0) -> TOKO GYS JAYA | K42: =vlookup(A42,Sheet2!A:E,5,0) -> BALIKPAPAN | L42: =VLOOKUP(B42,Sheet3!B:L,11,0) -> 6965474688 | M42: =vlookup(B42,'data staffinc_3'!B:I,7,0) -> 46247 | N42: 46266 | O42: =vlookup(B42,'data staffinc_3'!B:I,8,0) -> 46265 | P42: =VLOOKUP(A42,Sheet2!A:F,6,0) -> SAMARINDA | Q42: PT. Mahakarya Sukses Indonesia | R42: 70/30 | S42: 3857000 | T42: 2699900 | U42: 1157100 | W42: 3856694 | X42: 0 | Y42: =W42+X42 -> 3856694
A43: DM20260042 | B43: Fuji Restu Nurani | C43: =vlookup(B43,Sheet3!B:C,2,0) -> Jl. Dago Barat No. 06 159/B | D43: =vlookup(B43,Sheet3!B:D,3,0) -> 35383 | E43: =vlookup(B43,Sheet3!B:F,5,0) -> Bandung | F43: =vlookup(B43,Sheet3!B:H,7,0) -> SLTA | G43: =vlookup(B43,Sheet3!B:I,8,0) -> 089507427397 | H43: =vlookup(B43,Sheet3!B:J,9,0) -> fujirestunurani14@gmail.com | I43: SPB/SPG Toko | J43: =vlookup(B43,Sheet2!B:D,3,0) -> MUTIARA SUPER KITCHEN | K43: =vlookup(A43,Sheet2!A:E,5,0) -> BANDUNG | M43: 45996 | N43: 46266 | O43: 46265 | P43: =VLOOKUP(A43,Sheet2!A:F,6,0) -> BANDUNG | Q43: PT. Mahakarya Sukses Indonesia | R43: 70/30 | S43: 4738000 | T43: 3316600 | U43: 1421400 | W43: 4737678 | X43: 0 | Y43: =W43+X43 -> 4737678
A44: DM20260043 | B44: Gabriella Marchelline Blandina Romkeny | C44: =vlookup(B44,Sheet3!B:C,2,0) -> Wisma Lidah Kulon XB-38 | D44: =vlookup(B44,Sheet3!B:D,3,0) -> 36971 | E44: =vlookup(B44,Sheet3!B:F,5,0) -> Surabaya | F44: =vlookup(B44,Sheet3!B:H,7,0) -> SLTA | G44: =vlookup(B44,Sheet3!B:I,8,0) -> 088217641516 | H44: =vlookup(B44,Sheet3!B:J,9,0) -> gabriellaromkeny8@gmail.con | I44: SPB/SPG MT | J44: =vlookup(B44,Sheet2!B:D,3,0) -> HARTONO KERTAJAYA INDAH | K44: =vlookup(A44,Sheet2!A:E,5,0) -> SURABAYA | L44: =VLOOKUP(B44,Sheet3!B:L,11,0) -> 8291068537 | P44: =VLOOKUP(A44,Sheet2!A:F,6,0) -> SURABAYA | Q44: PT. Stein Perkasa Internasional | R44: Khusus | S44: 5289000 | T44: 5289000
A45: DM20260044 | B45: Gusti Rusmiami | C45: =vlookup(B45,Sheet3!B:C,2,0) -> JL KOMPLEK LOYANG INDAH BLOK M4 RT11 RW00 | D45: =vlookup(B45,Sheet3!B:D,3,0) -> 34274 | E45: =vlookup(B45,Sheet3!B:F,5,0) -> KOTABARU | F45: =vlookup(B45,Sheet3!B:H,7,0) -> SLTA | G45: =vlookup(B45,Sheet3!B:I,8,0) -> 082253031413 | H45: =vlookup(B45,Sheet3!B:J,9,0) -> ammygusti@gmail.com | I45: SPB/SPG Toko | J45: =vlookup(B45,Sheet2!B:D,3,0) -> NUANSA ELEKTRONIK TANJUNG | K45: =vlookup(A45,Sheet2!A:E,5,0) -> TABALONG | L45: =VLOOKUP(B45,Sheet3!B:L,11,0) -> 8695108539 | M45: 45627 | N45: 46266 | O45: 46265 | P45: =VLOOKUP(A45,Sheet2!A:F,6,0) -> BANJARMASIN | Q45: PT. Mahakarya Sukses Indonesia | R45: 70/30 | S45: 3828000 | T45: 2679600 | U45: 1148400 | V45: Resign per 25/9 | W45: 3827935 | X45: 0 | Y45: =W45+X45 -> 3827935
A46: DM20260045 | B46: Habib Mustopa | C46: =vlookup(B46,Sheet3!B:C,2,0) -> Jln Cihikeu, Desa Cihikeu Rt 01/ Rw 03 Kecamatan Bungbulang kabupaten Garut | D46: =vlookup(B46,Sheet3!B:D,3,0) -> 37458 | E46: =vlookup(B46,Sheet3!B:F,5,0) -> Garut | F46: =vlookup(B46,Sheet3!B:H,7,0) -> SLTA | G46: =vlookup(B46,Sheet3!B:I,8,0) -> 088985069845 | H46: =vlookup(B46,Sheet3!B:J,9,0) -> habibmustopa25@gmail.com | I46: SPB/SPG Toko | J46: =vlookup(B46,Sheet2!B:D,3,0) -> WIJAYA ELEKTRONIK | K46: =vlookup(A46,Sheet2!A:E,5,0) -> SEMARANG | L46: =VLOOKUP(B46,Sheet3!B:L,11,0) -> 2801851268 | M46: 44911 | N46: 46266 | O46: 46265 | P46: =VLOOKUP(A46,Sheet2!A:F,6,0) -> SEMARANG | Q46: PT. Mahakarya Sukses Indonesia | R46: 70/30 | S46: 3702000 | T46: 2591400 | U46: 1110600 | W46: 4233374 | X46: 0 | Y46: =W46+X46 -> 4233374
A47: DM20260046 | B47: Hagai Hendrik Yonathan | C47: =vlookup(B47,Sheet3!B:C,2,0) -> Dusun Babatan RT 003 RW 018 Sidomekar Semboro Jember | D47: =vlookup(B47,Sheet3!B:D,3,0) -> 31317 | E47: =vlookup(B47,Sheet3!B:F,5,0) -> Lumajang | F47: =vlookup(B47,Sheet3!B:H,7,0) -> SLTA | G47: =vlookup(B47,Sheet3!B:I,8,0) -> 081235652785 | H47: =vlookup(B47,Sheet3!B:J,9,0) -> joetozeta@gmail.com | I47: SPB/SPG Toko | J47: =vlookup(B47,Sheet2!B:D,3,0) -> TOKO RAMAI JAYA JEMBER | K47: =vlookup(A47,Sheet2!A:E,5,0) -> JEMBER | L47: =VLOOKUP(B47,Sheet3!B:L,11,0) -> 1250894160 | M47: 46008 | N47: 46266 | O47: 46265 | P47: =VLOOKUP(A47,Sheet2!A:F,6,0) -> SURABAYA | Q47: PT. Mahakarya Sukses Indonesia | R47: 70/30 | S47: 3013000 | T47: 2109100 | U47: 903900 | W47: 3012197 | X47: 0 | Y47: =W47+X47 -> 3012197
A48: DM20260047 | B48: Helen Budi Yana | C48: =vlookup(B48,Sheet3!B:C,2,0) -> Banjar sari | D48: =vlookup(B48,Sheet3!B:D,3,0) -> 35211 | E48: =vlookup(B48,Sheet3!B:F,5,0) -> Bandar lampung | F48: =vlookup(B48,Sheet3!B:H,7,0) -> SLTA | G48: =vlookup(B48,Sheet3!B:I,8,0) -> 082377054696 | H48: =vlookup(B48,Sheet3!B:J,9,0) -> Hellenby889@gmail.com | I48: SPB/SPG Toko | J48: =vlookup(B48,Sheet2!B:D,3,0) -> CV GEMBIRA HOUSEWARE | K48: =vlookup(A48,Sheet2!A:E,5,0) -> LAMPUNG-METRO | L48: =VLOOKUP(B48,Sheet3!B:L,11,0) -> 0231574629 | M48: 46174 | N48: 46266 | O48: 46265 | P48: =VLOOKUP(A48,Sheet2!A:F,6,0) -> LAMPUNG | Q48: PT. Mahakarya Sukses Indonesia | R48: 70/30 | S48: 3051000 | T48: 2135700 | U48: 915300 | W48: 3050498 | X48: 0 | Y48: =W48+X48 -> 3050498
A49: DM20260048 | B49: Herdy Yansyah | C49: =vlookup(B49,Sheet3!B:C,2,0) -> Ds.UJAN MAS BARU Kec.UJAN MAS Kab.MUARA ENIM | D49: =vlookup(B49,Sheet3!B:D,3,0) -> 37751 | E49: =vlookup(B49,Sheet3!B:F,5,0) -> Ds.TANJUNG RAYA Kab.MUSI BANYUASIN | F49: =vlookup(B49,Sheet3!B:H,7,0) -> SLTA | G49: =vlookup(B49,Sheet3!B:I,8,0) -> 082269859451 | H49: =vlookup(B49,Sheet3!B:J,9,0) -> herdyy275@gmail.com | I49: SPB/SPG Toko | J49: =vlookup(B49,Sheet2!B:D,3,0) -> CV ANEKA JAYA ELEKTRONIK | K49: =vlookup(A49,Sheet2!A:E,5,0) -> MUARA ENIM | L49: =VLOOKUP(B49,Sheet3!B:L,11,0) -> 8120433165 | M49: 45784 | N49: 46266 | O49: 46265 | P49: =VLOOKUP(A49,Sheet2!A:F,6,0) -> PALEMBANG | Q49: PT. Mahakarya Sukses Indonesia | R49: 70/30 | S49: 4193000 | T49: 2935100 | U49: 1257900 | W49: 4192837 | X49: 0 | Y49: =W49+X49 -> 4192837
A50: DM20260049 | B50: Heri Suprihatin | C50: =vlookup(B50,Sheet3!B:C,2,0) -> Semuluh kidul RT/RW 003/015 Ngeposari, Semanu, Gunungkidul | D50: =vlookup(B50,Sheet3!B:D,3,0) -> 33849 | E50: =vlookup(B50,Sheet3!B:F,5,0) -> Gunungkidul | F50: =vlookup(B50,Sheet3!B:H,7,0) -> SLTA | G50: =vlookup(B50,Sheet3!B:I,8,0) -> 083122638000 | H50: =vlookup(B50,Sheet3!B:J,9,0) -> heryfriska97@gmail.com | I50: SPB/SPG Toko | J50: =vlookup(B50,Sheet2!B:D,3,0) -> ATAKRIB BHAYANGKARA | K50: =vlookup(A50,Sheet2!A:E,5,0) -> YOGYAKARTA | L50: =VLOOKUP(B50,Sheet3!B:L,11,0) -> 0375170910 | M50: 46224 | N50: 46266 | O50: 46265 | P50: =VLOOKUP(A50,Sheet2!A:F,6,0) -> SEMARANG | Q50: PT. Mahakarya Sukses Indonesia | R50: 70/30 | S50: 3455000 | T50: 2418500 | U50: 1036500 | W50: 3454827 | X50: 0 | Y50: =W50+X50 -> 3454827
A51: DM20260050 | B51: I Ketut Sugiarta | C51: =vlookup(B51,Sheet3!B:C,2,0) -> Desa : TOLAI BARAT, Kecamatan: TORUE | D51: =vlookup(B51,Sheet3!B:D,3,0) -> 35682 | E51: =vlookup(B51,Sheet3!B:F,5,0) -> TOLAI | F51: =vlookup(B51,Sheet3!B:H,7,0) -> SLTA | G51: =vlookup(B51,Sheet3!B:I,8,0) -> 082193339184 | H51: =vlookup(B51,Sheet3!B:J,9,0) -> sugiartha445566@gmail.com | I51: SPB/SPG Toko | J51: =vlookup(B51,Sheet2!B:D,3,0) -> STAR KITCHEN | K51: =vlookup(A51,Sheet2!A:E,5,0) -> PALU | L51: =VLOOKUP(B51,Sheet3!B:L,11,0) -> 7795175946 | M51: 44753 | N51: 46266 | O51: 46265 | P51: =VLOOKUP(A51,Sheet2!A:F,6,0) -> MAKASSAR | Q51: PT. Mahakarya Sukses Indonesia | R51: 70/30 | S51: 4149000 | T51: 2904300 | U51: 1244700 | W51: 4148179 | X51: 0 | Y51: =W51+X51 -> 4148179
A52: DM20260051 | B52: Ilham Ansyar | C52: =vlookup(B52,Sheet3!B:C,2,0) -> Jl.padat karya komplek purnama permai 3 no 108 RT 060 RW 001 | D52: =vlookup(B52,Sheet3!B:D,3,0) -> 30059 | E52: =vlookup(B52,Sheet3!B:F,5,0) -> BANJARMASIN | F52: =vlookup(B52,Sheet3!B:H,7,0) -> SLTA | G52: =vlookup(B52,Sheet3!B:I,8,0) -> 081253019452 | H52: =vlookup(B52,Sheet3!B:J,9,0) -> ansyarmito2@gmail.com | I52: SPB/SPG Toko | J52: =vlookup(B52,Sheet2!B:D,3,0) -> POS ELEKTRONIK | K52: =vlookup(A52,Sheet2!A:E,5,0) -> BANJARMASIN | L52: =VLOOKUP(B52,Sheet3!B:L,11,0) -> 0511560895 | M52: 42815 | N52: 46266 | O52: 46265 | P52: =VLOOKUP(A52,Sheet2!A:F,6,0) -> BANJARMASIN | Q52: PT. Mahakarya Sukses Indonesia | R52: 70/30 | S52: 3856000 | T52: 2699200 | U52: 1156800 | W52: 3855894 | X52: 0 | Y52: =W52+X52 -> 3855894
A53: DM20260052 | B53: Imelda Febri Christina | C53: =vlookup(B53,Sheet3!B:C,2,0) -> Jl. Kaliombo Raya 93 | D53: =vlookup(B53,Sheet3!B:D,3,0) -> 37308 | E53: =vlookup(B53,Sheet3!B:F,5,0) -> Kediri | F53: =vlookup(B53,Sheet3!B:H,7,0) -> SLTA | G53: =vlookup(B53,Sheet3!B:I,8,0) -> 081217248277 | H53: =vlookup(B53,Sheet3!B:J,9,0) -> imeldamito0612@gmail.com | I53: SPB/SPG Toko | J53: =vlookup(B53,Sheet2!B:D,3,0) -> UFO ELEKTRONIK KEDIRI | K53: =vlookup(A53,Sheet2!A:E,5,0) -> KEDIRI | L53: =VLOOKUP(B53,Sheet3!B:L,11,0) -> 2980820818 | M53: 45692 | N53: 46266 | O53: 46265 | P53: =VLOOKUP(A53,Sheet2!A:F,6,0) -> SURABAYA | Q53: PT. Mahakarya Sukses Indonesia | R53: 70/30 | S53: 2743000 | T53: 1920100 | U53: 822900 | W53: 2742806 | X53: 0 | Y53: =W53+X53 -> 2742806
A54: DM20260053 | B54: Indriyani | C54: =vlookup(B54,Sheet3!B:C,2,0) -> Jl.lapang tanuwijaya situraja sumedang | D54: =vlookup(B54,Sheet3!B:D,3,0) -> 35874 | E54: =vlookup(B54,Sheet3!B:F,5,0) -> Sumedang | F54: =vlookup(B54,Sheet3!B:H,7,0) -> SLTA | G54: =vlookup(B54,Sheet3!B:I,8,0) -> 082218621312 | H54: =vlookup(B54,Sheet3!B:J,9,0) -> Awdodotig@gmail.com | I54: SPB/SPG MT | J54: =vlookup(B54,Sheet2!B:D,3,0) -> HARTONO BANDUNG | K54: =vlookup(A54,Sheet2!A:E,5,0) -> BANDUNG | L54: =VLOOKUP(B54,Sheet3!B:L,11,0) -> 2031154997 | P54: =VLOOKUP(A54,Sheet2!A:F,6,0) -> BANDUNG | Q54: PT. Stein Perkasa Internasional | R54: Khusus | S54: 4738000 | T54: 4738000
A55: DM20260054 | B55: Intan Kristiani Laoli | C55: =vlookup(B55,Sheet3!B:C,2,0) -> ombolata saloo | D55: =vlookup(B55,Sheet3!B:D,3,0) -> 36896 | E55: =vlookup(B55,Sheet3!B:F,5,0) -> nias | F55: =vlookup(B55,Sheet3!B:H,7,0) -> SLTA | G55: =vlookup(B55,Sheet3!B:I,8,0) -> 081274956324 | H55: =vlookup(B55,Sheet3!B:J,9,0) -> intankristiani9@gmail.com | I55: SPB/SPG Toko | J55: =vlookup(B55,Sheet2!B:D,3,0) -> JACKSON'S HOMEWARE MARKET | K55: =vlookup(A55,Sheet2!A:E,5,0) -> BATAM | L55: =VLOOKUP(B55,Sheet3!B:L,11,0) -> 8250436638 | M55: 45924 | N55: 46266 | O55: 46265 | P55: =VLOOKUP(A55,Sheet2!A:F,6,0) -> MEDAN | Q55: PT. Mahakarya Sukses Indonesia | R55: 70/30 | S55: 5358000 | T55: 3750600 | U55: 1607400 | W55: 5357982 | X55: 0 | Y55: =W55+X55 -> 5357982
A56: DM20260055 | B56: Irma Fitriani | C56: =vlookup(B56,Sheet3!B:C,2,0) -> Bukit Hartaco indah blok 1B | D56: =vlookup(B56,Sheet3!B:D,3,0) -> 32993 | E56: =vlookup(B56,Sheet3!B:F,5,0) -> Soppeng | F56: =vlookup(B56,Sheet3!B:H,7,0) -> SLTA | G56: =vlookup(B56,Sheet3!B:I,8,0) -> 085346312661 | H56: =vlookup(B56,Sheet3!B:J,9,0) -> irmafitr3004@gmail.com | I56: SPB/SPG Toko | J56: =vlookup(B56,Sheet2!B:D,3,0) -> MAXI PERINTIS | K56: =vlookup(A56,Sheet2!A:E,5,0) -> MAKASSAR | L56: =VLOOKUP(B56,Sheet3!B:L,11,0) -> 0251311616 | M56: 43440 | N56: 46266 | O56: 46265 | P56: =VLOOKUP(A56,Sheet2!A:F,6,0) -> MAKASSAR | Q56: PT. Mahakarya Sukses Indonesia | R56: 70/30 | S56: 4149000 | T56: 2904300 | U56: 1244700 | W56: 4148179 | X56: 0 | Y56: =W56+X56 -> 4148179
A57: DM20260056 | B57: Isma Kurniawati | C57: =vlookup(B57,Sheet3!B:C,2,0) -> KP BAROS RT 01 RW 02 DS BAROS KEC ARJASARI KAB BANDUNG | D57: =vlookup(B57,Sheet3!B:D,3,0) -> 34161 | E57: =vlookup(B57,Sheet3!B:F,5,0) -> BANDUNG | F57: =vlookup(B57,Sheet3!B:H,7,0) -> SLTA | G57: =vlookup(B57,Sheet3!B:I,8,0) -> 088222510571 | H57: =vlookup(B57,Sheet3!B:J,9,0) -> arrafaizma@gmail.com | I57: SPB/SPG Toko | J57: =vlookup(B57,Sheet2!B:D,3,0) -> TOKO PANTES AGUNG (ONLINE) | K57: =vlookup(A57,Sheet2!A:E,5,0) -> BANDUNG | L57: =VLOOKUP(B57,Sheet3!B:L,11,0) -> 7751764611 | M57: 46055 | N57: 46266 | O57: 46265 | P57: =VLOOKUP(A57,Sheet2!A:F,6,0) -> BANDUNG | Q57: PT. Mahakarya Sukses Indonesia | R57: 70/30 | S57: 4738000 | T57: 3316600 | U57: 1421400 | W57: 4737678 | X57: 0 | Y57: =W57+X57 -> 4737678
A58: DM20260057 | B58: Joko Supriatna | C58: =vlookup(B58,Sheet3!B:C,2,0) -> Kp. Bojong Nangka No 32 Rt 001/008 Jati Rahayu, Pondok Melati, Bekasi | D58: =vlookup(B58,Sheet3!B:D,3,0) -> 33370 | E58: =vlookup(B58,Sheet3!B:F,5,0) -> Lebak Banten | F58: =vlookup(B58,Sheet3!B:H,7,0) -> SLTA | G58: =vlookup(B58,Sheet3!B:I,8,0) -> 08567643486 | H58: =vlookup(B58,Sheet3!B:J,9,0) -> Jksupriatna92@gmail.com | I58: SPB/SPG Outlet | J58: =vlookup(B58,Sheet2!B:D,3,0) -> MALL KELAPA GADING | K58: =vlookup(A58,Sheet2!A:E,5,0) -> JAKARTA | L58: =VLOOKUP(B58,Sheet3!B:L,11,0) -> 6872083061 | M58: 44837 | N58: 46266 | O58: 46265 | P58: =VLOOKUP(A58,Sheet2!A:F,6,0) -> JAKARTA | Q58: PT. Mahakarya Sukses Indonesia | R58: Khusus | S58: 5730000 | T58: 5730000 | W58: 5729876 | X58: 600000 | Y58: =W58+X58 -> 6329876
A59: DM20260058 | B59: Juice Antika Rompis | C59: =vlookup(B59,Sheet3!B:C,2,0) -> DUSUN V KAWANUA | D59: =vlookup(B59,Sheet3!B:D,3,0) -> 37416 | E59: =vlookup(B59,Sheet3!B:F,5,0) -> Palu | F59: =vlookup(B59,Sheet3!B:H,7,0) -> SLTA | G59: =vlookup(B59,Sheet3!B:I,8,0) -> 082192047661 | H59: =vlookup(B59,Sheet3!B:J,9,0) -> juikerompis48@gmail.com | I59: SPB/SPG Toko | J59: =vlookup(B59,Sheet2!B:D,3,0) -> ANUGRAH JAYA PALU | K59: =vlookup(A59,Sheet2!A:E,5,0) -> PALU | L59: =VLOOKUP(B59,Sheet3!B:L,11,0) -> 7795377255 | P59: =VLOOKUP(A59,Sheet2!A:F,6,0) -> MAKASSAR | Q59: PT. Mahakarya Sukses Indonesia | R59: 70/30 | S59: 4149000 | T59: 2904300 | U59: 1244700
A60: DM20260059 | B60: Khoirunnisa Yuliana | C60: =vlookup(B60,Sheet3!B:C,2,0) -> Jl. Danau Rangas VII No. 32 | D60: =vlookup(B60,Sheet3!B:D,3,0) -> 36349 | E60: =vlookup(B60,Sheet3!B:F,5,0) -> Palangkaraya | F60: =vlookup(B60,Sheet3!B:H,7,0) -> SLTA | G60: =vlookup(B60,Sheet3!B:I,8,0) -> 083150001212 | H60: =vlookup(B60,Sheet3!B:J,9,0) -> Khoirunnisayuliana39@gmail.com | I60: SPB/SPG Toko | J60: =vlookup(B60,Sheet2!B:D,3,0) -> CENTRAL PLASTIK PALANGKARAYA | K60: PALANGKARAYA | L60: =VLOOKUP(B60,Sheet3!B:L,11,0) -> 6575189966 | M60: 45835 | N60: 46266 | O60: 46265 | P60: =VLOOKUP(A60,Sheet2!A:F,6,0) -> BANJARMASIN | Q60: PT. Mahakarya Sukses Indonesia | R60: 70/30 | S60: 3725000 | T60: 2607500 | U60: 1117500 | W60: 3686138 | X60: 0 | Y60: =W60+X60 -> 3686138
A61: DM20260060 | B61: Lilis Hidayati | C61: =vlookup(B61,Sheet3!B:C,2,0) -> kp. cisabuk | D61: =vlookup(B61,Sheet3!B:D,3,0) -> 35981 | E61: =vlookup(B61,Sheet3!B:F,5,0) -> garut | F61: =vlookup(B61,Sheet3!B:H,7,0) -> SLTA | G61: =vlookup(B61,Sheet3!B:I,8,0) -> 095172233040 | H61: =vlookup(B61,Sheet3!B:J,9,0) -> lilishidayati8@gmail.com | I61: SPB/SPG Toko | J61: =vlookup(B61,Sheet2!B:D,3,0) -> SINAR GUNTUR GARUT | K61: =vlookup(A61,Sheet2!A:E,5,0) -> GARUT | L61: =VLOOKUP(B61,Sheet3!B:L,11,0) -> 1481886355 | P61: =VLOOKUP(A61,Sheet2!A:F,6,0) -> BANDUNG | Q61: PT. Mahakarya Sukses Indonesia | R61: 70/30 | S61: 3973000 | T61: 2781100 | U61: 1191900
A62: DM20260061 | B62: Liya Nataliya | C62: =vlookup(B62,Sheet3!B:C,2,0) -> PT MII RT/RW 001/005 Kel. Pamesi Kec. Bathin Solapan Kab. Bengkalis Riau | D62: =vlookup(B62,Sheet3!B:D,3,0) -> 37253 | E62: =vlookup(B62,Sheet3!B:F,5,0) -> Pasaman, Sumatera Barat | F62: =vlookup(B62,Sheet3!B:H,7,0) -> SLTA | G62: =vlookup(B62,Sheet3!B:I,8,0) -> 082385625202 | H62: =vlookup(B62,Sheet3!B:J,9,0) -> liyanalita1120@gmail.com | I62: SPB/SPG Toko | J62: =vlookup(B62,Sheet2!B:D,3,0) -> TOKO ATRIA KELAPA GADING | K62: =vlookup(A62,Sheet2!A:E,5,0) -> JAKARTA | L62: =VLOOKUP(B62,Sheet3!B:L,11,0) -> 8520379852 | M62: 45561 | N62: 46266 | O62: 46265 | P62: =VLOOKUP(A62,Sheet2!A:F,6,0) -> JAKARTA | Q62: PT. Mahakarya Sukses Indonesia | R62: 70/30 | S62: 5730000 | T62: 4011000 | U62: 1719000 | W62: 5729876 | X62: 0 | Y62: =W62+X62 -> 5729876
A63: DM20260062 | B63: Mardatillah | C63: =vlookup(B63,Sheet3!B:C,2,0) -> Simpang rt08 rw02 | D63: =vlookup(B63,Sheet3!B:D,3,0) -> 38240 | E63: =vlookup(B63,Sheet3!B:F,5,0) -> Sidoarjo | F63: =vlookup(B63,Sheet3!B:H,7,0) -> SLTA | G63: =vlookup(B63,Sheet3!B:I,8,0) -> 087845284320 | H63: =vlookup(B63,Sheet3!B:J,9,0) -> mamatmarda12@gmail.com | I63: SPB/SPG MT | J63: =vlookup(B63,Sheet2!B:D,3,0) -> HARTONO SIDOARJO | K63: =vlookup(A63,Sheet2!A:E,5,0) -> SIDOARJO | L63: =VLOOKUP(B63,Sheet3!B:L,11,0) -> 0883073760 | M63: 46022 | N63: 46266 | O63: 46265 | P63: =VLOOKUP(A63,Sheet2!A:F,6,0) -> SURABAYA | Q63: PT. Mahakarya Sukses Indonesia | R63: Khusus | T63: 5192000 | W63: 5191541 | X63: 0 | Y63: =W63+X63 -> 5191541
A64: DM20260063 | B64: Marni Dwi widiyaningsih | C64: =vlookup(B64,Sheet3!B:C,2,0) -> Jl kedinding lor gg manggis no 26 | D64: =vlookup(B64,Sheet3!B:D,3,0) -> 35129 | E64: =vlookup(B64,Sheet3!B:F,5,0) -> Tulungagung | F64: =vlookup(B64,Sheet3!B:H,7,0) -> SLTA | G64: =vlookup(B64,Sheet3!B:I,8,0) -> 089502456598 | H64: =vlookup(B64,Sheet3!B:J,9,0) -> marnidwiw@gmail.com | I64: SPB/SPG Toko | J64: =vlookup(B64,Sheet2!B:D,3,0) -> UFO KERTAJAYA | K64: =vlookup(A64,Sheet2!A:E,5,0) -> SURABAYA | L64: =VLOOKUP(B64,Sheet3!B:L,11,0) -> 1011824809 | M64: 46084 | N64: 46266 | O64: 46265 | P64: =VLOOKUP(A64,Sheet2!A:F,6,0) -> SURABAYA | Q64: PT. Mahakarya Sukses Indonesia | R64: 70/30 | S64: 5289000 | T64: 3702300 | U64: 1586700 | W64: 5288796 | X64: 0 | Y64: =W64+X64 -> 5288796
A65: DM20260064 | B65: Martin Agustian | C65: =vlookup(B65,Sheet3!B:C,2,0) -> Jln Satam Dalam RT.009/003 Kel.Semabung Baru Kec. Girimaya Kota Pangkalpinang | D65: =vlookup(B65,Sheet3!B:D,3,0) -> 33667 | E65: =vlookup(B65,Sheet3!B:F,5,0) -> Pangkalpinang | F65: =vlookup(B65,Sheet3!B:H,7,0) -> SLTA | G65: =vlookup(B65,Sheet3!B:I,8,0) -> 081995357575 | H65: =vlookup(B65,Sheet3!B:J,9,0) -> crewnyek@gmail.com | I65: Sales Area | J65: =vlookup(B65,Sheet2!B:D,3,0) -> MITO - SALES B2B | K65: =vlookup(A65,Sheet2!A:E,5,0) -> BANGKA | L65: =VLOOKUP(B65,Sheet3!B:L,11,0) -> 8535125917 | M65: =vlookup(B65,'data staffinc_3'!B:I,7,0) -> 46027 | N65: 46266 | O65: =vlookup(B65,'data staffinc_3'!B:I,8,0) -> 46265 | P65: =VLOOKUP(A65,Sheet2!A:F,6,0) -> PALEMBANG | Q65: PT. Mahakarya Sukses Indonesia | R65: Khusus | T65: =Y65 -> 4485000 | W65: 4035000 | X65: 450000 | Y65: =W65+X65 -> 4485000
A66: DM20260065 | B66: Mawar | C66: =vlookup(B66,Sheet3!B:C,2,0) -> Jln damai gg 4 | D66: =vlookup(B66,Sheet3!B:D,3,0) -> 38831 | E66: =vlookup(B66,Sheet3!B:F,5,0) -> Samarinda | F66: =vlookup(B66,Sheet3!B:H,7,0) -> SLTA | G66: =vlookup(B66,Sheet3!B:I,8,0) -> 085349514526 | H66: =vlookup(B66,Sheet3!B:J,9,0) -> yanihama2415@gmail.com | I66: SPB/SPG Toko | J66: =vlookup(B66,Sheet2!B:D,3,0) -> NUANSA MATOS SAMARINDA | K66: =vlookup(A66,Sheet2!A:E,5,0) -> SAMARINDA | L66: =VLOOKUP(B66,Sheet3!B:L,11,0) -> 6585260766 | M66: 46002 | N66: 46266 | O66: 46265 | P66: =VLOOKUP(A66,Sheet2!A:F,6,0) -> SAMARINDA | Q66: PT. Mahakarya Sukses Indonesia | R66: 70/30 | S66: 3984000 | T66: 2788800 | U66: 1195200 | V66: Resign per 20/9 | W66: 3983882 | X66: 0 | Y66: =W66+X66 -> 3983882
A67: DM20260066 | B67: Merliani Anissa Rachman | C67: =vlookup(B67,Sheet3!B:C,2,0) -> Jln.Milono Gg.Husada | D67: =vlookup(B67,Sheet3!B:D,3,0) -> 39075 | E67: =vlookup(B67,Sheet3!B:F,5,0) -> Berau | F67: =vlookup(B67,Sheet3!B:H,7,0) -> SLTA | G67: =vlookup(B67,Sheet3!B:I,8,0) -> 082353675726 | H67: =vlookup(B67,Sheet3!B:J,9,0) -> merlianianissa1224@gmail.com | I67: SPB/SPG Toko | J67: =vlookup(B67,Sheet2!B:D,3,0) -> NUANSA BERAU | K67: BERAU | L67: =VLOOKUP(B67,Sheet3!B:L,11,0) -> 8605464803 | M67: 45817 | N67: 46266 | O67: 46265 | P67: =VLOOKUP(A67,Sheet2!A:F,6,0) -> SAMARINDA | Q67: PT. Mahakarya Sukses Indonesia | R67: 70/30 | S67: 4392000 | T67: 3074400 | U67: 1317600 | W67: 4391337 | X67: 0 | Y67: =W67+X67 -> 4391337
A68: DM20260067 | B68: Mesrawati Lase | C68: =vlookup(B68,Sheet3!B:C,2,0) -> Jln. Jamin ginting no. 113 | D68: =vlookup(B68,Sheet3!B:D,3,0) -> 35104 | E68: =vlookup(B68,Sheet3!B:F,5,0) -> Nias | F68: =vlookup(B68,Sheet3!B:H,7,0) -> S1 | G68: =vlookup(B68,Sheet3!B:I,8,0) -> 081318812178 | H68: =vlookup(B68,Sheet3!B:J,9,0) -> mesrawatilase01@gmail.com | I68: SPB/SPG Toko | J68: =vlookup(B68,Sheet2!B:D,3,0) -> IRAMA HOUSEWARE | K68: =vlookup(A68,Sheet2!A:E,5,0) -> MEDAN | L68: =VLOOKUP(B68,Sheet3!B:L,11,0) -> 8205655901 | M68: 45541 | N68: 46266 | O68: 46265 | P68: =VLOOKUP(A68,Sheet2!A:F,6,0) -> MEDAN | Q68: PT. Mahakarya Sukses Indonesia | R68: 70/30 | S68: 4336000 | T68: 3035200 | U68: 1300800 | W68: 4335198 | X68: 0 | Y68: =W68+X68 -> 4335198
A69: DM20260068 | B69: Mochamad Abdi Akbar | C69: =vlookup(B69,Sheet3!B:C,2,0) -> Jl.Arismunandar 7a/821 | D69: =vlookup(B69,Sheet3!B:D,3,0) -> 30067 | E69: =vlookup(B69,Sheet3!B:F,5,0) -> MALANG | F69: =vlookup(B69,Sheet3!B:H,7,0) -> SLTA | G69: =vlookup(B69,Sheet3!B:I,8,0) -> 081252153824 | H69: =vlookup(B69,Sheet3!B:J,9,0) -> abdi.akbarr@gmail.com | I69: SPB/SPG Toko | J69: =vlookup(B69,Sheet2!B:D,3,0) -> OGAN BANDULAN & OGAN BONDOWOSO | K69: SURABAYA | L69: =VLOOKUP(B69,Sheet3!B:L,11,0) -> 8161203041 | M69: =vlookup(B69,'data staffinc_3'!B:I,7,0) -> 43374 | N69: 46266 | O69: =vlookup(B69,'data staffinc_3'!B:I,8,0) -> 46265 | P69: =VLOOKUP(A69,Sheet2!A:F,6,0) -> SURABAYA | Q69: PT. Mahakarya Sukses Indonesia | R69: 70/30 | S69: 5289000 | T69: 3702300 | U69: 1586700 | W69: 5288796 | X69: 0 | Y69: =W69+X69 -> 5288796
A70: DM20260069 | B70: Moh Nurdiansah | C70: =vlookup(B70,Sheet3!B:C,2,0) -> Kp curugaru RT/RW : 001/001 Kel, Kadugembong Kec, kaduhejo kab Pandeglang Banten | D70: =vlookup(B70,Sheet3!B:D,3,0) -> 37975 | E70: =vlookup(B70,Sheet3!B:F,5,0) -> Pandeglang | F70: =vlookup(B70,Sheet3!B:H,7,0) -> SLTA | G70: =vlookup(B70,Sheet3!B:I,8,0) -> 085774109821 | H70: =vlookup(B70,Sheet3!B:J,9,0) -> iyann201203@gmail.com | I70: =vlookup(A70,Sheet2!A:E,3,0) -> GTM | J70: =vlookup(B70,Sheet2!B:D,3,0) -> Toko Senyum 5000 BSD Tangerang | K70: =vlookup(A70,Sheet2!A:E,5,0) -> JAKARTA | L70: =VLOOKUP(B70,Sheet3!B:L,11,0) -> 7125610072 | M70: =vlookup(B70,'data staffinc_3'!B:I,7,0) -> 45236 | N70: 46266 | O70: =vlookup(B70,'data staffinc_3'!B:I,8,0) -> 46265 | P70: =VLOOKUP(A70,Sheet2!A:F,6,0) -> JAKARTA | Q70: PT. Mahakarya Sukses Indonesia | R70: Khusus | S70: 5730000 | T70: 5730000 | W70: 5247870 | X70: 330000 | Y70: =W70+X70 -> 5577870
A71: DM20260070 | B71: Mohammad Hidayat | C71: =vlookup(B71,Sheet3!B:C,2,0) -> Kalirejo RT.003/ RW.004 | D71: =vlookup(B71,Sheet3!B:D,3,0) -> 35307 | E71: =vlookup(B71,Sheet3!B:F,5,0) -> Kudus | F71: =vlookup(B71,Sheet3!B:H,7,0) -> SLTA | G71: =vlookup(B71,Sheet3!B:I,8,0) -> 6285736181145 | H71: =vlookup(B71,Sheet3!B:J,9,0) -> mohammadhidayat190@gmail.com | I71: SPB/SPG Toko | J71: =vlookup(B71,Sheet2!B:D,3,0) -> TOKO DEPO MURAH JAYA SENTOSA KUDUS | K71: =vlookup(A71,Sheet2!A:E,5,0) -> KUDUS | M71: 46034 | N71: 46266 | O71: 46265 | P71: =VLOOKUP(A71,Sheet2!A:F,6,0) -> SEMARANG | Q71: PT. Mahakarya Sukses Indonesia | R71: 70/30 | S71: 2819000 | T71: 1973300 | U71: 845700 | W71: 2818585 | X71: 0 | Y71: =W71+X71 -> 2818585
A72: DM20260071 | B72: Mohammad Nur Fadilah | C72: =vlookup(B72,Sheet3!B:C,2,0) -> Jl giri rejo 1 km 15 | D72: =vlookup(B72,Sheet3!B:D,3,0) -> 37775 | E72: =vlookup(B72,Sheet3!B:F,5,0) -> Balikpapan | F72: =vlookup(B72,Sheet3!B:H,7,0) -> SLTA | G72: =vlookup(B72,Sheet3!B:I,8,0) -> 087756414360 | H72: =vlookup(B72,Sheet3!B:J,9,0) -> fnur22037@gmail.com | I72: SPB/SPG Toko | J72: =vlookup(B72,Sheet2!B:D,3,0) -> SURYA JAYA BALIKPAPAN | K72: =vlookup(A72,Sheet2!A:E,5,0) -> BALIKPAPAN | L72: =VLOOKUP(B72,Sheet3!B:L,11,0) -> 6965360526 | M72: =vlookup(B72,'data staffinc_3'!B:I,7,0) -> 45761 | N72: 46266 | O72: =vlookup(B72,'data staffinc_3'!B:I,8,0) -> 46265 | P72: =VLOOKUP(A72,Sheet2!A:F,6,0) -> SAMARINDA | Q72: PT. Mahakarya Sukses Indonesia | R72: 70/30 | S72: 3857000 | T72: 2699900 | U72: 1157100 | W72: 3856694 | X72: 0 | Y72: =W72+X72 -> 3856694
A73: DM20260072 | B73: Moy Yustiwa Rahayu Putri Kartika | C73: =vlookup(B73,Sheet3!B:C,2,0) -> DSN. GROPYOK, DS. TANON, RT/RW : 002/003, KEC. PAPAR, KAB. KEDIRI | D73: =vlookup(B73,Sheet3!B:D,3,0) -> 37492 | E73: =vlookup(B73,Sheet3!B:F,5,0) -> KEDIRI | F73: =vlookup(B73,Sheet3!B:H,7,0) -> S1 | G73: =vlookup(B73,Sheet3!B:I,8,0) -> 081335885943 | H73: =vlookup(B73,Sheet3!B:J,9,0) -> moyyustiwa24@gmail.com | I73: SPB/SPG MT | J73: =vlookup(B73,Sheet2!B:D,3,0) -> HARTONO BG JUNCTION | K73: =vlookup(A73,Sheet2!A:E,5,0) -> SURABAYA | L73: =VLOOKUP(B73,Sheet3!B:L,11,0) -> 6123069515 | M73: =vlookup(B73,'data staffinc_3'!B:I,7,0) -> 46022 | N73: 46266 | O73: =vlookup(B73,'data staffinc_3'!B:I,8,0) -> 46265 | P73: =VLOOKUP(A73,Sheet2!A:F,6,0) -> SURABAYA | Q73: PT. Mahakarya Sukses Indonesia | R73: Khusus | S73: 5289000 | T73: 5289000 | W73: 5288796 | X73: 0 | Y73: =W73+X73 -> 5288796
A74: DM20260073 | B74: Mualling | C74: =vlookup(B74,Sheet3!B:C,2,0) -> Polejiwa | D74: =vlookup(B74,Sheet3!B:D,3,0) -> 37599 | E74: =vlookup(B74,Sheet3!B:F,5,0) -> Barru | F74: =vlookup(B74,Sheet3!B:H,7,0) -> SLTA | G74: =vlookup(B74,Sheet3!B:I,8,0) -> 087890300301 | H74: =vlookup(B74,Sheet3!B:J,9,0) -> Muallinglim@gmail.com | I74: SPB/SPG Toko | J74: =vlookup(B74,Sheet2!B:D,3,0) -> ALASKA | K74: =vlookup(A74,Sheet2!A:E,5,0) -> MAKASSAR | L74: =VLOOKUP(B74,Sheet3!B:L,11,0) -> 8260425260 | M74: 46198 | N74: 46266 | O74: 46265 | P74: =VLOOKUP(A74,Sheet2!A:F,6,0) -> MAKASSAR | Q74: PT. Mahakarya Sukses Indonesia | R74: 70/30 | S74: 4149000 | T74: 2904300 | U74: 1244700 | W74: 4148179 | X74: 0 | Y74: =W74+X74 -> 4148179
A75: DM20260074 | B75: Muhammad Hafrizal | C75: =vlookup(B75,Sheet3!B:C,2,0) -> SIDOTOPO JAYA 2/2 | D75: =vlookup(B75,Sheet3!B:D,3,0) -> 35920 | E75: =vlookup(B75,Sheet3!B:F,5,0) -> SURABAYA | F75: =vlookup(B75,Sheet3!B:H,7,0) -> SLTA | G75: =vlookup(B75,Sheet3!B:I,8,0) -> 081235805598 | H75: =vlookup(B75,Sheet3!B:J,9,0) -> hafrizalmuhammad@gmail.com | I75: SPB/SPG Outlet | J75: =vlookup(B75,Sheet2!B:D,3,0) -> TUNJUNGAN PLAZA | K75: =vlookup(A75,Sheet2!A:E,5,0) -> SURABAYA | L75: =VLOOKUP(B75,Sheet3!B:L,11,0) -> 6170469508 | M75: 45152 | N75: 46266 | O75: 46265 | P75: =VLOOKUP(A75,Sheet2!A:F,6,0) -> SURABAYA | Q75: PT. Mahakarya Sukses Indonesia | R75: Khusus | S75: 5289000 | T75: 5289000 | W75: 5288796 | X75: 600000 | Y75: =W75+X75 -> 5888796
A76: DM20260075 | B76: Muhtar | C76: =vlookup(B76,Sheet3!B:C,2,0) -> Kp. Cikandang Rt 003 Rw 008 desa. Cimareme Kec. Ngamprah | D76: =vlookup(B76,Sheet3!B:D,3,0) -> 34155 | E76: =vlookup(B76,Sheet3!B:F,5,0) -> Bandung | F76: =vlookup(B76,Sheet3!B:H,7,0) -> SLTA | G76: =vlookup(B76,Sheet3!B:I,8,0) -> 08886200919 | H76: =vlookup(B76,Sheet3!B:J,9,0) -> muhtar.banez88@gmail.com | I76: SPB/SPG Toko | J76: =vlookup(B76,Sheet2!B:D,3,0) -> BLIBLI ELEKTRONIK MOCH TOHA | K76: =vlookup(A76,Sheet2!A:E,5,0) -> BANDUNG | L76: =VLOOKUP(B76,Sheet3!B:L,11,0) -> 7940301020 | M76: 46055 | N76: 46266 | O76: 46265 | P76: =VLOOKUP(A76,Sheet2!A:F,6,0) -> BANDUNG | Q76: PT. Mahakarya Sukses Indonesia | R76: 70/30 | S76: 4738000 | T76: 3316600 | U76: 1421400 | W76: 4737678 | X76: 0 | Y76: =W76+X76 -> 4737678
A77: DM20260076 | B77: Munjiyah Agus Cancetta | C77: =vlookup(B77,Sheet3!B:C,2,0) -> JL WALTER CONDRAD GG LOMBOK | D77: =vlookup(B77,Sheet3!B:D,3,0) -> 38092 | E77: =vlookup(B77,Sheet3!B:F,5,0) -> SAMPIT | F77: =vlookup(B77,Sheet3!B:H,7,0) -> SLTA | G77: =vlookup(B77,Sheet3!B:I,8,0) -> 082255195399 | H77: =vlookup(B77,Sheet3!B:J,9,0) -> cancetta4@gmail.com | I77: SPB/SPG Toko | J77: =vlookup(B77,Sheet2!B:D,3,0) -> HOKKY OMEGA SAMPIT | K77: =vlookup(A77,Sheet2!A:E,5,0) -> SAMPIT | L77: =VLOOKUP(B77,Sheet3!B:L,11,0) -> 6695618313 | M77: 45817 | N77: 46266 | O77: 46265 | P77: =VLOOKUP(A77,Sheet2!A:F,6,0) -> BANJARMASIN | Q77: PT. Mahakarya Sukses Indonesia | R77: 70/30 | S77: 3757000 | T77: 2629900 | U77: 1127100 | W77: 3756643 | X77: 0 | Y77: =W77+X77 -> 3756643
A78: DM20260077 | B78: Mustakim | C78: =vlookup(B78,Sheet3!B:C,2,0) -> #N/A | D78: =vlookup(B78,Sheet3!B:D,3,0) -> #N/A | E78: =vlookup(B78,Sheet3!B:F,5,0) -> #N/A | F78: =vlookup(B78,Sheet3!B:H,7,0) -> #N/A | G78: =vlookup(B78,Sheet3!B:I,8,0) -> #N/A | H78: =vlookup(B78,Sheet3!B:J,9,0) -> #N/A | I78: =vlookup(A78,Sheet2!A:E,3,0) -> GTM | J78: =vlookup(B78,Sheet2!B:D,3,0) -> STEIN - SPG/SPB MT | K78: =vlookup(A78,Sheet2!A:E,5,0) -> JAKARTA | L78: =VLOOKUP(B78,Sheet3!B:L,11,0) -> #N/A | P78: =VLOOKUP(A78,Sheet2!A:F,6,0) -> JAKARTA | Q78: PT. Stein Perkasa Internasional | R78: Khusus | T78: 6140000 | W78: 5729876 | X78: 410000 | Y78: =W78+X78 -> 6139876
A79: DM20260078 | B79: Muti'ah Nur Fadilah | C79: =vlookup(B79,Sheet3!B:C,2,0) -> Jln. Ancol Selatan rt05 rw03 no28 Kel.Sunter Agung Kec.Tanjung Priok Jakarta Utara 14350 | D79: =vlookup(B79,Sheet3!B:D,3,0) -> 35378 | E79: =vlookup(B79,Sheet3!B:F,5,0) -> Jakarta | F79: =vlookup(B79,Sheet3!B:H,7,0) -> SLTA | G79: =vlookup(B79,Sheet3!B:I,8,0) -> 0882006362336 | H79: =vlookup(B79,Sheet3!B:J,9,0) -> Mutiahnurf09@gmail.com | I79: =vlookup(A79,Sheet2!A:E,3,0) -> Host Live | J79: =vlookup(B79,Sheet2!B:D,3,0) -> MANGGA DUA SQUARE | K79: =vlookup(A79,Sheet2!A:E,5,0) -> JAKARTA | L79: =VLOOKUP(B79,Sheet3!B:L,11,0) -> 5235189965 | P79: =VLOOKUP(A79,Sheet2!A:F,6,0) -> JAKARTA | Q79: PT. Mahakarya Sukses Indonesia | R79: Khusus | S79: 5730000 | T79: 5730000
A80: DM20260079 | B80: Nada Fadhillah Shobah | C80: =vlookup(B80,Sheet3!B:C,2,0) -> Jl. Srikandi Gg. Swadaya IV No. 4 | D80: =vlookup(B80,Sheet3!B:D,3,0) -> 37039 | E80: =vlookup(B80,Sheet3!B:F,5,0) -> Medan | F80: =vlookup(B80,Sheet3!B:H,7,0) -> SLTA | G80: =vlookup(B80,Sheet3!B:I,8,0) -> 081264583373 | H80: =vlookup(B80,Sheet3!B:J,9,0) -> nadafadhillah28052001@gmail.com | I80: SPB/SPG Toko | J80: =vlookup(B80,Sheet2!B:D,3,0) -> SH MART ELEKTRONIK | K80: =vlookup(A80,Sheet2!A:E,5,0) -> MEDAN | L80: =VLOOKUP(B80,Sheet3!B:L,11,0) -> 1951673540 | M80: 45054 | N80: 46266 | O80: 46265 | P80: =VLOOKUP(A80,Sheet2!A:F,6,0) -> MEDAN | Q80: PT. Mahakarya Sukses Indonesia | R80: 70/30 | S80: 4336000 | T80: 3035200 | U80: 1300800 | W80: 4335198 | X80: 0 | Y80: =W80+X80 -> 4335198
A81: DM20260080 | B81: Nany Maria Panjaitan | C81: =vlookup(B81,Sheet3!B:C,2,0) -> Mrutukalianyar 165 | D81: =vlookup(B81,Sheet3!B:D,3,0) -> 32016 | E81: =vlookup(B81,Sheet3!B:F,5,0) -> SURABAYA | F81: =vlookup(B81,Sheet3!B:H,7,0) -> SLTA | G81: =vlookup(B81,Sheet3!B:I,8,0) -> 08132230318 | H81: =vlookup(B81,Sheet3!B:J,9,0) -> nanymariap@gmail.com | I81: SPB/SPG Toko | J81: =vlookup(B81,Sheet2!B:D,3,0) -> PERDANA MANYAR | K81: =vlookup(A81,Sheet2!A:E,5,0) -> SURABAYA | L81: =VLOOKUP(B81,Sheet3!B:L,11,0) -> 1020482849 | M81: 45505 | N81: 46266 | O81: 46265 | P81: =VLOOKUP(A81,Sheet2!A:F,6,0) -> SURABAYA | Q81: PT. Mahakarya Sukses Indonesia | R81: 70/30 | S81: 5289000 | T81: 3702300 | U81: 1586700 | W81: 5288796 | X81: 0 | Y81: =W81+X81 -> 5288796
A82: DM20260081 | B82: Neni Rahayu | C82: =vlookup(B82,Sheet3!B:C,2,0) -> Jl. Beo GG. Anggrek Kr. Kemong, cakranegara Barat | D82: =vlookup(B82,Sheet3!B:D,3,0) -> 34644 | E82: =vlookup(B82,Sheet3!B:F,5,0) -> Mataram | F82: =vlookup(B82,Sheet3!B:H,7,0) -> SLTA | G82: =vlookup(B82,Sheet3!B:I,8,0) -> 087899215955 | H82: =vlookup(B82,Sheet3!B:J,9,0) -> rahayuneni0611@gmail.com | I82: SPB/SPG Toko | J82: =vlookup(B82,Sheet2!B:D,3,0) -> DAPUR KITA MATARAM | K82: =vlookup(A82,Sheet2!A:E,5,0) -> MATARAM | L82: =VLOOKUP(B82,Sheet3!B:L,11,0) -> 0562729397 | M82: 46034 | N82: 46266 | O82: 46265 | P82: =VLOOKUP(A82,Sheet2!A:F,6,0) -> SURABAYA | Q82: PT. Mahakarya Sukses Indonesia | R82: Khusus | S82: 5730000 | T82: 5730000 | W82: 3019015 | X82: 0 | Y82: =W82+X82 -> 3019015
A83: DM20260082 | B83: Norhidayah.S | C83: =vlookup(B83,Sheet3!B:C,2,0) -> km.14 gg mutiara.gambut | D83: =vlookup(B83,Sheet3!B:D,3,0) -> 32431 | E83: =vlookup(B83,Sheet3!B:F,5,0) -> banjarmasin | F83: =vlookup(B83,Sheet3!B:H,7,0) -> SLTA | G83: =vlookup(B83,Sheet3!B:I,8,0) -> 082154107338 | H83: =vlookup(B83,Sheet3!B:J,9,0) -> udayshar88@gmail.com | I83: SPB/SPG Toko | J83: =vlookup(B83,Sheet2!B:D,3,0) -> PONDOK ELEKTRONIK | K83: =vlookup(A83,Sheet2!A:E,5,0) -> BANJARMASIN | L83: =VLOOKUP(B83,Sheet3!B:L,11,0) -> 8275634804 | M83: =vlookup(B83,'data staffinc_3'!B:I,7,0) -> 45673 | N83: 46266 | O83: =vlookup(B83,'data staffinc_3'!B:I,8,0) -> 46265 | P83: =VLOOKUP(A83,Sheet2!A:F,6,0) -> BANJARMASIN | Q83: PT. Mahakarya Sukses Indonesia | R83: 70/30 | S83: 3856000 | T83: 2699200 | U83: 1156800 | W83: 3855894 | X83: 0 | Y83: =W83+X83 -> 3855894
A84: DM20260083 | B84: Nur Rahmah | C84: =vlookup(B84,Sheet3!B:C,2,0) -> kebon besar rt02 rw 03 kecamatan batu ceper tangerang | D84: =vlookup(B84,Sheet3!B:D,3,0) -> 38171 | E84: =vlookup(B84,Sheet3!B:F,5,0) -> Tangerang | F84: =vlookup(B84,Sheet3!B:H,7,0) -> SLTA | G84: =vlookup(B84,Sheet3!B:I,8,0) -> 087760225284 | H84: =vlookup(B84,Sheet3!B:J,9,0) -> nurrahmahhh11@gmail.com | I84: SPB/SPG Toko | J84: =vlookup(B84,Sheet2!B:D,3,0) -> TOKO EMETAL ASIA JAYA (ONLINE) | K84: =vlookup(A84,Sheet2!A:E,5,0) -> JAKARTA | L84: =VLOOKUP(B84,Sheet3!B:L,11,0) -> 5940898368 | M84: 46164 | N84: 46266 | O84: 46265 | P84: =VLOOKUP(A84,Sheet2!A:F,6,0) -> JAKARTA | Q84: PT. Mahakarya Sukses Indonesia | R84: Khusus | S84: 5730000 | T84: 5730000 | V84: Host Live | W84: 5729876 | X84: 0 | Y84: =W84+X84 -> 5729876
A85: DM20260084 | B85: Nurista Afninda Waqiatul Q | C85: =vlookup(B85,Sheet3!B:C,2,0) -> Jl Ahmad Yani IV/109 Lingk. Tembaan | D85: =vlookup(B85,Sheet3!B:D,3,0) -> 37671 | E85: =vlookup(B85,Sheet3!B:F,5,0) -> Jember | F85: =vlookup(B85,Sheet3!B:H,7,0) -> SLTA | G85: =vlookup(B85,Sheet3!B:I,8,0) -> 089628450401 | H85: =vlookup(B85,Sheet3!B:J,9,0) -> afnindanurista@gmail.com | I85: SPB/SPG Toko | J85: =vlookup(B85,Sheet2!B:D,3,0) -> TOP 100 SWALAYAN | K85: BATAM | L85: =VLOOKUP(B85,Sheet3!B:L,11,0) -> 0123456789 | M85: 45934 | N85: 46266 | O85: 46265 | P85: =VLOOKUP(A85,Sheet2!A:F,6,0) -> SURABAYA | Q85: PT. Mahakarya Sukses Indonesia | R85: 70/30 | S85: 5358000 | T85: 3750600 | U85: 1607400 | W85: 5357982 | X85: 0 | Y85: =W85+X85 -> 5357982
A86: DM20260085 | B86: Nurmalita Widiyanti | C86: =vlookup(B86,Sheet3!B:C,2,0) -> JL. Panglima Sudirman Gang VII No 71B Kepatihan Tulungagung | D86: =vlookup(B86,Sheet3!B:D,3,0) -> 34671 | E86: =vlookup(B86,Sheet3!B:F,5,0) -> Tulungagung | F86: =vlookup(B86,Sheet3!B:H,7,0) -> SLTA | G86: =vlookup(B86,Sheet3!B:I,8,0) -> 081334979494 | H86: =vlookup(B86,Sheet3!B:J,9,0) -> nwidiyanti70@gmail.com | I86: SPB/SPG Toko | J86: =vlookup(B86,Sheet2!B:D,3,0) -> CV OMEGA SEJAHTERA | K86: =vlookup(A86,Sheet2!A:E,5,0) -> TULUNGAGUNG | L86: =VLOOKUP(B86,Sheet3!B:L,11,0) -> 0481650436 | M86: 45446 | N86: 46266 | O86: 46265 | P86: =VLOOKUP(A86,Sheet2!A:F,6,0) -> SURABAYA | Q86: PT. Mahakarya Sukses Indonesia | R86: 70/30 | S86: 2629000 | T86: 1840300 | U86: 788700 | W86: 2628190 | X86: 0 | Y86: =W86+X86 -> 2628190
A87: DM20260086 | B87: Owen Jehezkiel Wijaya | C87: =vlookup(B87,Sheet3!B:C,2,0) -> Kedung Anyar 5/42 | D87: =vlookup(B87,Sheet3!B:D,3,0) -> 39026 | E87: =vlookup(B87,Sheet3!B:F,5,0) -> Surabaya | F87: =vlookup(B87,Sheet3!B:H,7,0) -> SLTA | G87: =vlookup(B87,Sheet3!B:I,8,0) -> 0882009923236 | H87: =vlookup(B87,Sheet3!B:J,9,0) -> Goowen36@gmail.com | I87: SPB/SPG Toko | J87: =vlookup(B87,Sheet2!B:D,3,0) -> SUPER MURAH SURABAYA 2 | K87: =vlookup(A87,Sheet2!A:E,5,0) -> SURABAYA | L87: =VLOOKUP(B87,Sheet3!B:L,11,0) -> 1030769631 | M87: 45579 | N87: 46266 | O87: 46265 | P87: =VLOOKUP(A87,Sheet2!A:F,6,0) -> SURABAYA | Q87: PT. Mahakarya Sukses Indonesia | R87: 70/30 | S87: 5289000 | T87: 3702300 | U87: 1586700 | W87: 5288796 | X87: 0 | Y87: =W87+X87 -> 5288796
A88: DM20260087 | B88: Paramita Restuningtyas | C88: =vlookup(B88,Sheet3!B:C,2,0) -> JL. Watulawang V / 29 | D88: =vlookup(B88,Sheet3!B:D,3,0) -> 33239 | E88: =vlookup(B88,Sheet3!B:F,5,0) -> Semarang | F88: =vlookup(B88,Sheet3!B:H,7,0) -> SLTA | G88: =vlookup(B88,Sheet3!B:I,8,0) -> 085712040947 | H88: =vlookup(B88,Sheet3!B:J,9,0) -> paramitharestu65@gmail.com | I88: SPB/SPG Toko | J88: =vlookup(B88,Sheet2!B:D,3,0) -> PIRANTI HOUSEWARE | K88: =vlookup(A88,Sheet2!A:E,5,0) -> SEMARANG | L88: =VLOOKUP(B88,Sheet3!B:L,11,0) -> 8165474933 | M88: 45061 | N88: 46266 | O88: 46265 | P88: =VLOOKUP(A88,Sheet2!A:F,6,0) -> SEMARANG | Q88: PT. Mahakarya Sukses Indonesia | R88: 70/30 | S88: 3702000 | T88: 2591400 | U88: 1110600 | W88: 3701709 | X88: 0 | Y88: =W88+X88 -> 3701709
A89: DM20260088 | B89: Prakas Armando Yuwono | C89: =vlookup(B89,Sheet3!B:C,2,0) -> JL. LA. Sucipto GG. Stasiun No.16 RT.06 RW.10 Purwodadi Malang | D89: =vlookup(B89,Sheet3!B:D,3,0) -> 36017 | E89: =vlookup(B89,Sheet3!B:F,5,0) -> Malamg | F89: =vlookup(B89,Sheet3!B:H,7,0) -> SLTA | G89: =vlookup(B89,Sheet3!B:I,8,0) -> 089669375797 | H89: =vlookup(B89,Sheet3!B:J,9,0) -> prakasarmando51@gmail.com | I89: SPB/SPG MT | J89: =vlookup(B89,Sheet2!B:D,3,0) -> HARTONO MALANG | K89: =vlookup(A89,Sheet2!A:E,5,0) -> MALANG | L89: =VLOOKUP(B89,Sheet3!B:L,11,0) -> 3310069298 | M89: 46074 | N89: 46266 | O89: 46265 | P89: =VLOOKUP(A89,Sheet2!A:F,6,0) -> SURABAYA | Q89: PT. Mahakarya Sukses Indonesia | R89: Khusus | S89: 3803000 | T89: 3803000 | W89: 3736101 | X89: 0 | Y89: =W89+X89 -> 3736101
A90: DM20260089 | B90: Priya thadgea | C90: =vlookup(B90,Sheet3!B:C,2,0) -> Pedurungan lor | D90: =vlookup(B90,Sheet3!B:D,3,0) -> 36678 | E90: =vlookup(B90,Sheet3!B:F,5,0) -> Cilacap | F90: =vlookup(B90,Sheet3!B:H,7,0) -> SLTA | G90: =vlookup(B90,Sheet3!B:I,8,0) -> 0895381170790 | H90: =vlookup(B90,Sheet3!B:J,9,0) -> Thadhea10@gmail.com | I90: SPB/SPG Toko | J90: =vlookup(B90,Sheet2!B:D,3,0) -> ADA SWALAYAN SETIABUDI | K90: =vlookup(A90,Sheet2!A:E,5,0) -> SEMARANG | L90: =VLOOKUP(B90,Sheet3!B:L,11,0) -> 3440526046 | M90: =vlookup(B90,'data staffinc_3'!B:I,7,0) -> 45938 | N90: 46266 | O90: =vlookup(B90,'data staffinc_3'!B:I,8,0) -> 46265 | P90: =VLOOKUP(A90,Sheet2!A:F,6,0) -> SEMARANG | Q90: PT. Mahakarya Sukses Indonesia | R90: 70/30 | S90: 3702000 | T90: 2591400 | U90: 1110600 | W90: 3701709 | X90: 0 | Y90: =W90+X90 -> 3701709
A91: DM20260090 | B91: Puji Astuti | C91: =vlookup(B91,Sheet3!B:C,2,0) -> Botokenceng Rt. 01, Wirokerten, Banguntapan, Bantul, Yogyakarta | D91: =vlookup(B91,Sheet3!B:D,3,0) -> 29457 | E91: =vlookup(B91,Sheet3!B:F,5,0) -> Klaten | F91: =vlookup(B91,Sheet3!B:H,7,0) -> SLTA | G91: =vlookup(B91,Sheet3!B:I,8,0) -> 08985234603 | H91: =vlookup(B91,Sheet3!B:J,9,0) -> puji27631@gmail.com | I91: SPB/SPG Toko | J91: =vlookup(B91,Sheet2!B:D,3,0) -> FORTUNA | K91: =vlookup(A91,Sheet2!A:E,5,0) -> YOGYAKARTA | L91: =VLOOKUP(B91,Sheet3!B:L,11,0) -> 4451275768 | M91: 45693 | N91: 46266 | O91: 46265 | P91: =VLOOKUP(A91,Sheet2!A:F,6,0) -> SEMARANG | Q91: PT. Mahakarya Sukses Indonesia | R91: 70/30 | S91: 2828000 | T91: 1979600 | U91: 848400 | W91: 2827593 | X91: 0 | Y91: =W91+X91 -> 2827593
A92: DM20260091 | B92: Putri Ananda | C92: =vlookup(B92,Sheet3!B:C,2,0) -> Jl.Pematang pasir gg keluarga, kec tanjung mulia hilir | D92: =vlookup(B92,Sheet3!B:D,3,0) -> 36452 | E92: =vlookup(B92,Sheet3!B:F,5,0) -> Medan | F92: =vlookup(B92,Sheet3!B:H,7,0) -> SLTA | G92: =vlookup(B92,Sheet3!B:I,8,0) -> 082161115775 | H92: =vlookup(B92,Sheet3!B:J,9,0) -> ayyaputri413@gmail.com | I92: SPB/SPG Toko | J92: =vlookup(B92,Sheet2!B:D,3,0) -> WIEGO HOUSEWARE TRITURA | K92: =vlookup(A92,Sheet2!A:E,5,0) -> MEDAN | L92: =VLOOKUP(B92,Sheet3!B:L,11,0) -> 8195203390 | M92: 45352 | N92: 46266 | O92: 46265 | P92: =VLOOKUP(A92,Sheet2!A:F,6,0) -> MEDAN | Q92: PT. Mahakarya Sukses Indonesia | R92: 70/30 | S92: 4336000 | T92: 3035200 | U92: 1300800 | W92: 4335198 | X92: 0 | Y92: =W92+X92 -> 4335198
A93: DM20260092 | B93: Rekha Riakiah | C93: =vlookup(B93,Sheet3!B:C,2,0) -> Jl. cikijang 1 no 2 kec. Koja Kel. koja | D93: =vlookup(B93,Sheet3!B:D,3,0) -> 38138 | E93: =vlookup(B93,Sheet3!B:F,5,0) -> jakarta | F93: =vlookup(B93,Sheet3!B:H,7,0) -> SLTA | G93: =vlookup(B93,Sheet3!B:I,8,0) -> 081385983711 | H93: =vlookup(B93,Sheet3!B:J,9,0) -> raikaece4@gmail.com | I93: SPB/SPG Toko | J93: =vlookup(B93,Sheet2!B:D,3,0) -> TOKO PALAPA | K93: =vlookup(A93,Sheet2!A:E,5,0) -> JAKARTA | L93: =VLOOKUP(B93,Sheet3!B:L,11,0) -> 0930183628 | M93: 46079 | N93: 46266 | O93: 46265 | P93: =VLOOKUP(A93,Sheet2!A:F,6,0) -> JAKARTA | Q93: PT. Mahakarya Sukses Indonesia | R93: Khusus | S93: 5730000 | T93: 5730000 | V93: Host Live | W93: 5729876 | X93: 0 | Y93: =W93+X93 -> 5729876
A94: DM20260093 | B94: Reva Azzahra | C94: =vlookup(B94,Sheet3!B:C,2,0) -> kudu rt01/01 kudu baki sukoharjo | D94: =vlookup(B94,Sheet3!B:D,3,0) -> 38790 | E94: =vlookup(B94,Sheet3!B:F,5,0) -> sukoharjo | F94: =vlookup(B94,Sheet3!B:H,7,0) -> SLTA | G94: =vlookup(B94,Sheet3!B:I,8,0) -> 088227753485 | H94: =vlookup(B94,Sheet3!B:J,9,0) -> revaazzahraaa11@gmail.com | I94: SPB/SPG Toko | J94: =vlookup(B94,Sheet2!B:D,3,0) -> CANDI ELECTRONIC KARTASURA | K94: =vlookup(A94,Sheet2!A:E,5,0) -> SUKOHARJO | L94: =VLOOKUP(B94,Sheet3!B:L,11,0) -> 7851256753 | M94: 45826 | N94: 46266 | O94: 46265 | P94: =VLOOKUP(A94,Sheet2!A:F,6,0) -> SEMARANG | Q94: PT. Mahakarya Sukses Indonesia | R94: 70/30 | S94: 2500000 | T94: 1750000 | U94: 750000 | W94: 2500000 | X94: 0 | Y94: =W94+X94 -> 2500000
A95: DM20260094 | B95: Rindiani Herdialova | C95: =vlookup(B95,Sheet3!B:C,2,0) -> jln ujung pandan no 43B | D95: =vlookup(B95,Sheet3!B:D,3,0) -> 36521 | E95: =vlookup(B95,Sheet3!B:F,5,0) -> Padang | F95: =vlookup(B95,Sheet3!B:H,7,0) -> SLTA | G95: =vlookup(B95,Sheet3!B:I,8,0) -> 082289261153 | H95: =vlookup(B95,Sheet3!B:J,9,0) -> rindianiherdialova27@gmail.com | I95: SPB/SPG Toko | J95: =vlookup(B95,Sheet2!B:D,3,0) -> A FAUZI | K95: =vlookup(A95,Sheet2!A:E,5,0) -> PADANG | L95: =VLOOKUP(B95,Sheet3!B:L,11,0) -> 1630588509 | M95: 45474 | N95: 46266 | O95: 46265 | P95: =VLOOKUP(A95,Sheet2!A:F,6,0) -> PALEMBANG | Q95: PT. Mahakarya Sukses Indonesia | R95: 70/30 | S95: 3183000 | T95: 2228100 | U95: 954900 | W95: 3182955 | X95: 0 | Y95: =W95+X95 -> 3182955
A96: DM20260095 | B96: Riris Mustika Sari | C96: =vlookup(B96,Sheet3!B:C,2,0) -> Ngaglik RT01/RW 03,Manjung,Ngawen,klaten | D96: =vlookup(B96,Sheet3!B:D,3,0) -> 34287 | E96: =vlookup(B96,Sheet3!B:F,5,0) -> Klaten | F96: =vlookup(B96,Sheet3!B:H,7,0) -> SLTA | G96: =vlookup(B96,Sheet3!B:I,8,0) -> 085725777296 | H96: =vlookup(B96,Sheet3!B:J,9,0) -> Rirismustika575@gamil.com | I96: SPB/SPG Toko | J96: =vlookup(B96,Sheet2!B:D,3,0) -> LARIS KLATEN | K96: =vlookup(A96,Sheet2!A:E,5,0) -> KLATEN | L96: =VLOOKUP(B96,Sheet3!B:L,11,0) -> 0301481984 | M96: 45636 | N96: 46266 | O96: 46265 | P96: =VLOOKUP(A96,Sheet2!A:F,6,0) -> SEMARANG | Q96: PT. Mahakarya Sukses Indonesia | R96: 70/30 | S96: 2539000 | T96: 1777300 | U96: 761700 | W96: 2538691 | X96: 0 | Y96: =W96+X96 -> 2538691
A97: DM20260096 | B97: Rista bellawati basuki | C97: =vlookup(B97,Sheet3!B:C,2,0) -> Jalan Ploso 1 no 16 a | D97: =vlookup(B97,Sheet3!B:D,3,0) -> 35238 | E97: =vlookup(B97,Sheet3!B:F,5,0) -> Surabaya | F97: =vlookup(B97,Sheet3!B:H,7,0) -> SLTA | G97: =vlookup(B97,Sheet3!B:I,8,0) -> 089678564827 | H97: =vlookup(B97,Sheet3!B:J,9,0) -> ristabella274@gmail.com | I97: SPB/SPG MT | J97: =vlookup(B97,Sheet2!B:D,3,0) -> HARTONO KERTAJAYA INDAH | K97: =vlookup(A97,Sheet2!A:E,5,0) -> SURABAYA | L97: =VLOOKUP(B97,Sheet3!B:L,11,0) -> 5190184422 | M97: 46043 | N97: 46266 | O97: 46265 | P97: =VLOOKUP(A97,Sheet2!A:F,6,0) -> SURABAYA | Q97: PT. Mahakarya Sukses Indonesia | R97: Khusus | S97: 5289000 | T97: 5289000 | W97: 5288796 | X97: 0 | Y97: =W97+X97 -> 5288796
A98: DM20260097 | B98: Rizky Nanda Karunia | C98: =vlookup(B98,Sheet3!B:C,2,0) -> Dsn Ngadimulyo RT/RW 002/002, Ds Bulurejo, Kec Purwoharjo, Kab Banyuwangi | D98: =vlookup(B98,Sheet3!B:D,3,0) -> 37232 | E98: =vlookup(B98,Sheet3!B:F,5,0) -> Banyuwangi | F98: =vlookup(B98,Sheet3!B:H,7,0) -> S1 | G98: =vlookup(B98,Sheet3!B:I,8,0) -> 085231231536 | H98: =vlookup(B98,Sheet3!B:J,9,0) -> rizkynandakarunia712@gmail.com | I98: SPB/SPG Toko | J98: =vlookup(B98,Sheet2!B:D,3,0) -> MEDIA ELEKTRONIK DENPASAR | K98: DENPASAR | L98: =VLOOKUP(B98,Sheet3!B:L,11,0) -> 3510460391 | M98: 46084 | N98: 46266 | O98: 46265 | P98: =VLOOKUP(A98,Sheet2!A:F,6,0) -> SURABAYA | Q98: PT. Mahakarya Sukses Indonesia | R98: 70/30 | S98: 3500000 | T98: 2450000 | U98: 1050000 | W98: 3499878 | X98: 0 | Y98: =W98+X98 -> 3499878
A99: DM20260098 | B99: Roby Sugiarti | C99: =vlookup(B99,Sheet3!B:C,2,0) -> Jl.Plumbon RT06 RW03 WONOSARI NGALIYAN SEMARANG | D99: =vlookup(B99,Sheet3!B:D,3,0) -> 34541 | E99: =vlookup(B99,Sheet3!B:F,5,0) -> Semarang | F99: =vlookup(B99,Sheet3!B:H,7,0) -> S1 | G99: =vlookup(B99,Sheet3!B:I,8,0) -> 0895359984060 | H99: =vlookup(B99,Sheet3!B:J,9,0) -> robysugiarti21@gmail.com | I99: SPB/SPG Toko | J99: =vlookup(B99,Sheet2!B:D,3,0) -> PASIFIK PEKOJAN | K99: =vlookup(A99,Sheet2!A:E,5,0) -> SEMARANG | L99: =VLOOKUP(B99,Sheet3!B:L,11,0) -> 0092461121 | P99: =VLOOKUP(A99,Sheet2!A:F,6,0) -> SEMARANG | Q99: PT. Mahakarya Sukses Indonesia | R99: 70/30 | S99: 3702000 | T99: 2591400 | U99: 1110600
A100: DM20260099 | B100: Sabila Fadillah | C100: =vlookup(B100,Sheet3!B:C,2,0) -> JL CILENGKRNG II PALASARI V RT 001/007 PALASARI, CIBIRU | D100: =vlookup(B100,Sheet3!B:D,3,0) -> 36747 | E100: =vlookup(B100,Sheet3!B:F,5,0) -> BANDUNG | F100: =vlookup(B100,Sheet3!B:H,7,0) -> SLTA | G100: =vlookup(B100,Sheet3!B:I,8,0) -> 085624685906 | H100: =vlookup(B100,Sheet3!B:J,9,0) -> sblfdllh@gmail.com | I100: SPB/SPG Toko | J100: =vlookup(B100,Sheet2!B:D,3,0) -> MUTIARA SUPER KITCHEN UJUNG BERUNG | K100: =vlookup(A100,Sheet2!A:E,5,0) -> BANDUNG | L100: =VLOOKUP(B100,Sheet3!B:L,11,0) -> 2831985111 | M100: 46161 | N100: 46266 | O100: 46265 | P100: =VLOOKUP(A100,Sheet2!A:F,6,0) -> BANDUNG | Q100: PT. Mahakarya Sukses Indonesia | R100: 70/30 | S100: 4738000 | T100: 3316600 | U100: 1421400 | W100: 4737678 | X100: 0 | Y100: =W100+X100 -> 4737678
...

Sheet data staffinc_3
A1: No | B1: Mitra Sampingan's Name | C1: Position | D1: Area | E1: Branch Name | F1: Period | G1: Status | H1: Join Date | I1: Last Day (if inactive) | J1: Actual Working Days | K1: Effective Working Days | L1: Overtime Hours | M1: Basic Salary | N1: Tunjangan Outlet / Sales | O1: Upah Lembur/jam | P1: EWA | Q1: Adjustment (-) | R1: THP | S1: Notes Basic Salary | T1: Notes Overtime | U1: Notes Adjustment | V1: Note from Staffinc to MITO
A2: 1 | B2: Anggiza Gana Pawestri | C2: SPG/SPB Toko | D2: JABO | E2: JABO - HARAPAN BARU | F2: 25 Jul 2026 - 24 Aug 2026 | G2: inactive | H2: 43409 | I2: 46265 | J2: 28 | K2: 26 | M2: 5729876 | N2: 0 | O2: 15000 | P2: 660000 | R2: #VALUE! | S2: Hari Kerja: 28 / 26 x 5729876 | T2: Total jam lembur yang disetujui =
A3: 2 | B3: Annisa | C3: SPG/SPB Toko | D3: BANJARMASIN | E3: BANJARMASIN - POS ELEKTRONIK | F3: 25 Jul 2026 - 24 Aug 2026 | G3: inactive | H3: 42826 | I3: 46265 | J3: 30 | K3: 26 | M3: 3855894 | N3: 0 | O3: 15000 | R3: #VALUE! | S3: Hari Kerja: 30 / 26 x 3855894
A4: 3 | B4: Ilham Ansyar | C4: SPG/SPB Toko | D4: BANJARMASIN | E4: BANJARMASIN - POS ELEKTRONIK | F4: 25 Jul 2026 - 24 Aug 2026 | G4: inactive | H4: 42815 | I4: 46265 | J4: 30 | K4: 26 | M4: 3855894 | N4: 0 | O4: 15000 | P4: 1905000 | R4: 2579108 | S4: Hari Kerja: 30 / 26 x 3855894
A5: 4 | B5: Irma Fitriani | C5: SPG/SPB Toko | D5: MAKASSAR | E5: MAKASSAR - MAXI PERINTIS | F5: 25 Jul 2026 - 24 Aug 2026 | G5: inactive | H5: 43440 | I5: 46265 | J5: 27 | K5: 26 | M5: 4148179 | N5: 0 | O5: 15000 | R5: #VALUE! | S5: Hari Kerja: 27 / 26 x 4148179
A6: 5 | B6: Retno Dwi Ningrum | C6: SPG/SPB Toko | D6: PALEMBANG | E6: PALEMBANG - DAPOER MUTIARA (CV PELITA MAS) | F6: 25 Jul 2026 - 24 Aug 2026 | G6: inactive | H6: 42962 | I6: 46258 | J6: 27 | K6: 26 | M6: 4192837 | N6: 0 | O6: 15000 | R6: #VALUE! | S6: Hari Kerja: 27 / 26 x 4192837
A7: 6 | B7: Firda Duri Yatinal Ulya | C7: SPG/SPB Toko | D7: SAMARINDA | E7: SAMARINDA - NUANSA IMAM BONJOL | F7: 25 Jul 2026 - 24 Aug 2026 | G7: inactive | H7: 43777 | I7: 46265 | J7: 28 | K7: 26 | M7: 3983882 | N7: 0 | O7: 15000 | R7: #VALUE! | S7: Hari Kerja: 28 / 26 x 3983882
A8: 7 | B8: Mochamad Abdi Akbar | C8: SPG/SPB Toko | D8: SURABAYA | E8: SURABAYA - OGAN BANDULAN & OGAN BONDOWOSO | F8: 25 Jul 2026 - 24 Aug 2026 | G8: inactive | H8: 43374 | I8: 46265 | J8: 27 | K8: 26 | M8: 5288796 | N8: 0 | O8: 15000 | P8: 584097 | R8: 4943114 | S8: Hari Kerja: 27 / 26 x 5288796
A9: 8 | B9: Elisa Putra Afdiono | C9: SPG/SPB Toko | D9: SURABAYA | E9: SURABAYA - TOENG MARKET JAKSA AGUNG SUPRAPTO | F9: 25 Jul 2026 - 24 Aug 2026 | G9: inactive | H9: 44077 | I9: 46265 | J9: 27 | K9: 26 | M9: 5288796 | N9: 0 | O9: 15000 | P9: 1834500 | R9: 3692711 | S9: Hari Kerja: 27 / 26 x 5288796
A10: 9 | B10: I Ketut Sugiarta | C10: SPG/SPB Toko | D10: MAKASSAR | E10: MAKASSAR - STAR KITCHEN | F10: 25 Jul 2026 - 24 Aug 2026 | G10: inactive | H10: 44753 | I10: 46265 | J10: 26 | K10: 26 | M10: 4148179 | N10: 0 | O10: 15000 | R10: #VALUE! | S10: Hari Kerja: 26 / 26 x 4148179
A11: 10 | B11: Sri Astuti | C11: SPG/SPB Toko | D11: PEKANBARU | E11: PEKANBARU - GOLDEN DRAGON ELEKTRONIK | F11: 25 Jul 2026 - 24 Aug 2026 | G11: inactive | H11: 44816 | I11: 46265 | J11: 27 | K11: 26 | M11: 3998179 | N11: 0 | O11: 15000 | P11: 1943000 | R11: 2243955 | S11: Hari Kerja: 27 / 26 x 3998179
A12: 11 | B12: Adelina Astuti | C12: SPG/SPB Outlet | D12: OUTLET | E12: OUTLET - JABODETABEK - MALL KELAPA GADING | F12: 25 Jul 2026 - 24 Aug 2026 | G12: inactive | H12: 44852 | I12: 46265 | J12: 29 | K12: 26 | M12: 5729876 | N12: 600000 | O12: 15000 | R12: #VALUE! | S12: Hari Kerja: 29 / 26 x 5729876
A13: 12 | B13: Ari Kusumawati | C13: SPG/SPB Outlet | D13: OUTLET | E13: OUTLET - JABODETABEK - MALL KELAPA GADING | F13: 25 Jul 2026 - 24 Aug 2026 | G13: inactive | H13: 44844 | I13: 46265 | J13: 30 | K13: 26 | M13: 5729876 | N13: 600000 | O13: 15000 | R13: #VALUE! | S13: Hari Kerja: 30 / 26 x 5729876
A14: 13 | B14: Joko Supriatna | C14: SPG/SPB Outlet | D14: OUTLET | E14: OUTLET - JABODETABEK - MALL KELAPA GADING | F14: 25 Jul 2026 - 24 Aug 2026 | G14: inactive | H14: 44837 | I14: 46265 | J14: 28 | K14: 26 | M14: 5729876 | N14: 600000 | O14: 15000 | R14: #VALUE! | S14: Hari Kerja: 28 / 26 x 5729876
A15: 14 | B15: Firda Nur Agustin Cahyani | C15: SPG/SPB Toko | D15: BANDUNG | E15: BANDUNG - TOKO SINAR GUNTUR | F15: 25 Jul 2026 - 24 Aug 2026 | G15: inactive | H15: 44858 | I15: 46265 | J15: 28 | K15: 26 | M15: 2472227 | N15: 0 | O15: 15000 | R15: #VALUE! | S15: Hari Kerja: 28 / 26 x 2472227
A16: 15 | B16: Habib Mustopa | C16: SPG/SPB Toko | D16: SEMARANG | E16: SEMARANG - WIJAYA ELEKTRONIK | F16: 25 Jul 2026 - 24 Aug 2026 | G16: inactive | H16: 44911 | I16: 46265 | J16: 27 | K16: 26 | M16: 4233374 | N16: 0 | O16: 15000 | P16: 811500 | R16: 3619696 | S16: Hari Kerja: 27 / 26 x 4233374
A17: 16 | B17: Suci Ramadhani | C17: SPG/SPB Toko | D17: PEKANBARU | E17: PEKANBARU - BERKAT ELEKTRONIK | F17: 25 Jul 2026 - 24 Aug 2026 | G17: inactive | H17: 44963 | I17: 46265 | J17: 27 | K17: 26 | M17: 3898210 | N17: 0 | O17: 15000 | R17: #VALUE! | S17: Hari Kerja: 27 / 26 x 3898210
A18: 17 | B18: Nada Fadhillah Shobah | C18: SPG/SPB Toko | D18: MEDAN | E18: MEDAN - SH MART ELEKTRONIK | F18: 25 Jul 2026 - 24 Aug 2026 | G18: inactive | H18: 45054 | I18: 46265 | J18: 25 | K18: 26 | M18: 4335198 | N18: 0 | O18: 15000 | R18: #VALUE! | S18: Hari Kerja: 25 / 26 x 4335198
A19: 18 | B19: Paramita Restuningtyas | C19: SPG/SPB Toko | D19: SEMARANG | E19: SEMARANG - PIRANTI HOUSEWARE | F19: 25 Jul 2026 - 24 Aug 2026 | G19: inactive | H19: 45061 | I19: 46265 | J19: 27 | K19: 26 | M19: 3701709 | N19: 0 | O19: 15000 | R19: #VALUE! | S19: Hari Kerja: 27 / 26 x 3701709
A20: 19 | B20: Yuliana Siswanti | C20: SPG/SPB Outlet | D20: OUTLET | E20: OUTLET - SURABAYA - TUNJUNGAN PLAZA | F20: 25 Jul 2026 - 24 Aug 2026 | G20: inactive | H20: 45147 | I20: 46265 | J20: 26 | K20: 26 | M20: 5288796 | N20: 600000 | O20: 15000 | R20: #VALUE! | S20: Hari Kerja: 26 / 26 x 5288796
A21: 20 | B21: Faisol Adha | C21: SPG/SPB Outlet | D21: OUTLET | E21: OUTLET - SURABAYA - TUNJUNGAN PLAZA | F21: 25 Jul 2026 - 24 Aug 2026 | G21: inactive | H21: 45147 | I21: 46265 | J21: 27 | K21: 26 | M21: 5288796 | N21: 600000 | O21: 15000 | R21: #VALUE! | S21: Hari Kerja: 27 / 26 x 5288796
A22: 21 | B22: Muhammad Hafrizal | C22: SPG/SPB Outlet | D22: OUTLET | E22: OUTLET - SURABAYA - TUNJUNGAN PLAZA | F22: 25 Jul 2026 - 24 Aug 2026 | G22: inactive | H22: 45152 | I22: 46265 | J22: 27 | K22: 26 | M22: 5288796 | N22: 600000 | O22: 15000 | R22: #VALUE! | S22: Hari Kerja: 27 / 26 x 5288796
A23: 22 | B23: Fitri Wulandari | C23: SPG/SPB Toko | D23: BANJARMASIN | E23: BANJARMASIN - PONDOK ELEKTRONIK | F23: 25 Jul 2026 - 24 Aug 2026 | G23: inactive | H23: 45323 | I23: 46265 | J23: 25 | K23: 26 | M23: 3855894 | N23: 0 | O23: 15000 | R23: #VALUE! | S23: Hari Kerja: 25 / 26 x 3855894
A24: 23 | B24: Hendrika Buwa | C24: SPG/SPB Toko | D24: SAMARINDA | E24: SAMARINDA - MAMASUKA | F24: 25 Jul 2026 - 24 Aug 2026 | G24: inactive | H24: 45327 | I24: 46259 | J24: 26 | K24: 26 | M24: 3983882 | N24: 0 | O24: 15000 | P24: 750000 | R24: 3268882 | S24: Hari Kerja: 26 / 26 x 3983882
A25: 24 | B25: Sulaiman | C25: SPG/SPB Toko | D25: MAKASSAR | E25: MAKASSAR - SEMERU PERINTIS | F25: 25 Jul 2026 - 24 Aug 2026 | G25: inactive | H25: 45356 | I25: 46265 | J25: 28 | K25: 26 | M25: 4148179 | N25: 0 | O25: 15000 | R25: #VALUE! | S25: Hari Kerja: 28 / 26 x 4148179
A26: 25 | B26: Putri Ananda | C26: SPG/SPB Toko | D26: MEDAN | E26: MEDAN - WIEGO HOUSEWARE TRITURA | F26: 25 Jul 2026 - 24 Aug 2026 | G26: inactive | H26: 45352 | I26: 46265 | J26: 22 | K26: 26 | M26: 4335198 | N26: 0 | O26: 15000 | R26: #VALUE! | S26: Hari Kerja: 22 / 26 x 4335198
A27: 26 | B27: Nurmalita Widiyanti | C27: SPG/SPB Toko | D27: SURABAYA | E27: SURABAYA - CV OMEGA SEJAHTERA | F27: 25 Jul 2026 - 24 Aug 2026 | G27: inactive | H27: 45446 | I27: 46265 | J27: 27 | K27: 26 | M27: 2628190 | N27: 0 | O27: 15000 | R27: #VALUE! | S27: Hari Kerja: 27 / 26 x 2628190
A28: 27 | B28: Rindiani Herdialova | C28: SPG/SPB Toko | D28: PADANG | E28: PADANG - A FAUZI | F28: 25 Jul 2026 - 24 Aug 2026 | G28: inactive | H28: 45474 | I28: 46265 | J28: 25 | K28: 26 | M28: 3182955 | N28: 0 | O28: 15000 | R28: #VALUE! | S28: Hari Kerja: 25 / 26 x 3182955
A29: 28 | B29: Nany Maria Panjaitan | C29: SPG/SPB Toko | D29: SURABAYA | E29: SURABAYA - PERDANA MANYAR | F29: 25 Jul 2026 - 24 Aug 2026 | G29: inactive | H29: 45505 | I29: 46265 | J29: 29 | K29: 26 | L29: 2 | M29: 5288796 | N29: 0 | O29: 15000 | P29: 750000 | R29: 5214042 | S29: Hari Kerja: 29 / 26 x 5288796 | T29: Total jam lembur yang disetujui = 2
A30: 29 | B30: Yeni Angraini | C30: SPG/SPB Toko | D30: MAKASSAR | E30: MAKASSAR - HOKKY HOUSE WARE | F30: 25 Jul 2026 - 24 Aug 2026 | G30: inactive | H30: 45855 | I30: 46265 | J30: 24 | K30: 26 | M30: 4148179 | N30: 0 | O30: 15000 | P30: 440000 | R30: 3424088 | S30: Hari Kerja: 24 / 26 x 4148179
A31: 30 | B31: AgusTia ningRum | C31: SPG/SPB Toko | D31: BANJARMASIN | E31: BANJARMASIN - NUANSA PANGKALANBUN | F31: 25 Jul 2026 - 24 Aug 2026 | G31: inactive | H31: 45546 | I31: 46265 | J31: 27 | K31: 26 | M31: 3909005 | N31: 0 | O31: 15000 | R31: #VALUE! | S31: Hari Kerja: 27 / 26 x 3909005
A32: 31 | B32: Mesrawati Lase | C32: SPG/SPB Toko | D32: MEDAN | E32: MEDAN - IRAMA HOUSEWARE | F32: 25 Jul 2026 - 24 Aug 2026 | G32: inactive | H32: 45541 | I32: 46265 | J32: 25 | K32: 26 | M32: 4335198 | N32: 0 | O32: 15000 | R32: #VALUE! | S32: Hari Kerja: 25 / 26 x 4335198
A33: 32 | B33: Jesty Ananda | C33: SPG/SPB Toko | D33: SAMARINDA | E33: SAMARINDA - NUANSA TENGGARONG | F33: 25 Jul 2026 - 24 Aug 2026 | G33: inactive | H33: 45553 | I33: 46265 | J33: 28 | K33: 26 | M33: 3991797 | N33: 0 | O33: 15000 | R33: #VALUE! | S33: Hari Kerja: 28 / 26 x 3991797
A34: 33 | B34: Firanda | C34: SPG/SPB Toko | D34: PALEMBANG | E34: PALEMBANG - MDP SUPERSTORE | F34: 25 Jul 2026 - 24 Aug 2026 | G34: inactive | H34: 45567 | I34: 46265 | J34: 27 | K34: 26 | M34: 4192837 | N34: 0 | O34: 15000 | P34: 750000 | R34: 3639100 | S34: Hari Kerja: 27 / 26 x 4192837
A35: 34 | B35: Yustika Kaimuddin | C35: SPG/SPB Toko | D35: MAKASSAR | E35: MAKASSAR - MAXI ALAUDDIN | F35: 25 Jul 2026 - 24 Aug 2026 | G35: inactive | H35: 45566 | I35: 46265 | J35: 27 | K35: 26 | M35: 4148179 | N35: 0 | O35: 15000 | R35: #VALUE! | S35: Hari Kerja: 27 / 26 x 4148179
A36: 35 | B36: Dinda Sri Rahayu | C36: SPG/SPB Toko | D36: BANDUNG | E36: BANDUNG - LOGIN MEGASTORE (ABC) | F36: 25 Jul 2026 - 24 Aug 2026 | G36: inactive | H36: 45576 | I36: 46265 | J36: 28 | K36: 26 | M36: 4737678 | N36: 0 | O36: 15000 | P36: 750000 | R36: 4387115 | S36: Hari Kerja: 28 / 26 x 4737678
A37: 36 | B37: Owen Jehezkiel Wijaya | C37: SPG/SPB Toko | D37: SURABAYA | E37: SURABAYA - SUPER MURAH SURABAYA 2 | F37: 25 Jul 2026 - 24 Aug 2026 | G37: inactive | H37: 45579 | I37: 46265 | J37: 29 | K37: 26 | M37: 5288796 | N37: 0 | O37: 15000 | R37: #VALUE! | S37: Hari Kerja: 29 / 26 x 5288796
A38: 37 | B38: Selviana | C38: SPG/SPB Toko | D38: SAMARINDA | E38: SAMARINDA - TOKO SURYA JAYA | F38: 25 Jul 2026 - 24 Aug 2026 | G38: inactive | H38: 45628 | I38: 46265 | J38: 27 | K38: 26 | M38: 3991797 | N38: 0 | O38: 15000 | R38: #VALUE! | S38: Hari Kerja: 27 / 26 x 3991797
A39: 38 | B39: Christiana Dwi Jayanti | C39: SPG/SPB Toko | D39: SEMARANG | E39: SEMARANG - A TAKRIB LIFE STYLE | F39: 25 Jul 2026 - 24 Aug 2026 | G39: inactive | H39: 45627 | I39: 46265 | J39: 27 | K39: 26 | M39: 2827593 | N39: 0 | O39: 15000 | R39: #VALUE! | S39: Hari Kerja: 27 / 26 x 2827593
A40: 39 | B40: Gusti Rusmiami | C40: SPG/SPB Toko | D40: BANJARMASIN | E40: BANJARMASIN - NUANSA ELEKTRONIK TANJUNG | F40: 25 Jul 2026 - 24 Aug 2026 | G40: inactive | H40: 45627 | I40: 46265 | J40: 27 | K40: 26 | M40: 3827935 | N40: 0 | O40: 15000 | R40: #VALUE! | S40: Hari Kerja: 27 / 26 x 3827935
A41: 40 | B41: Riris Mustika Sari | C41: SPG/SPB Toko | D41: SEMARANG | E41: SEMARANG - LARIS KLATEN | F41: 25 Jul 2026 - 24 Aug 2026 | G41: inactive | H41: 45636 | I41: 46265 | J41: 27 | K41: 26 | M41: 2538691 | N41: 0 | O41: 15000 | R41: #VALUE! | S41: Hari Kerja: 27 / 26 x 2538691
A42: 41 | B42: Ela Siska Ariatun | C42: SPG/SPB Toko | D42: SAMARINDA | E42: SAMARINDA - NUANSA ELEKTRONIC TANAH GROGOT | F42: 25 Jul 2026 - 24 Aug 2026 | G42: inactive | H42: 45647 | I42: 46265 | J42: 30 | K42: 26 | M42: 3776998 | N42: 0 | O42: 15000 | P42: 750000 | R42: 3643075 | S42: Hari Kerja: 30 / 26 x 3776998
A43: 42 | B43: Vera Winarti | C43: SPG/SPB Toko | D43: SEMARANG | E43: SEMARANG - PROGO JOGJA | F43: 25 Jul 2026 - 24 Aug 2026 | G43: inactive | H43: 45673 | I43: 46265 | J43: 27 | K43: 26 | M43: 2827593 | N43: 0 | O43: 15000 | R43: #VALUE! | S43: Hari Kerja: 27 / 26 x 2827593
A44: 43 | B44: Norhidayah.S | C44: SPG/SPB Toko | D44: BANJARMASIN | E44: BANJARMASIN - PONDOK ELEKTRONIK | F44: 25 Jul 2026 - 24 Aug 2026 | G44: inactive | H44: 45673 | I44: 46265 | J44: 28 | K44: 26 | M44: 3855894 | N44: 0 | O44: 15000 | R44: #VALUE! | S44: Hari Kerja: 28 / 26 x 3855894
A45: 44 | B45: Ainun Jariah | C45: SPG/SPB Toko | D45: BANJARMASIN | E45: BANJARMASIN - GOLDEN 10 | F45: 25 Jul 2026 - 24 Aug 2026 | G45: inactive | H45: 45685 | I45: 46265 | J45: 28 | K45: 26 | M45: 3855894 | N45: 0 | O45: 15000 | R45: #VALUE! | S45: Hari Kerja: 28 / 26 x 3855894
A46: 45 | B46: Imelda Febri Christina | C46: SPG/SPB Toko | D46: SURABAYA | E46: SURABAYA - UFO ELEKTRONIK KEDIRI | F46: 25 Jul 2026 - 24 Aug 2026 | G46: inactive | H46: 45692 | I46: 46265 | J46: 27 | K46: 26 | M46: 2742806 | N46: 0 | O46: 15000 | P46: 700000 | R46: 2183299 | S46: Hari Kerja: 27 / 26 x 2742806
A47: 46 | B47: Fhadila Rahmatika Haya | C47: SPG/SPB Toko | D47: SEMARANG | E47: SEMARANG - CANDI ELEKTRONIC 310 | F47: 25 Jul 2026 - 24 Aug 2026 | G47: inactive | H47: 45685 | I47: 46265 | J47: 28 | K47: 26 | M47: 2570000 | N47: 0 | O47: 15000 | R47: #VALUE! | S47: Hari Kerja: 28 / 26 x 2570000
A48: 47 | B48: Apriliyani | C48: SPG/SPB Toko | D48: SEMARANG | E48: SEMARANG - ATLANTA MATARAM | F48: 25 Jul 2026 - 24 Aug 2026 | G48: inactive | H48: 45691 | I48: 46265 | J48: 27 | K48: 26 | M48: 3701709 | N48: 0 | O48: 15000 | R48: #VALUE! | S48: Hari Kerja: 27 / 26 x 3701709
A49: 48 | B49: Puji Astuti | C49: SPG/SPB Toko | D49: SEMARANG | E49: SEMARANG - FORTUNA | F49: 25 Jul 2026 - 24 Aug 2026 | G49: inactive | H49: 45693 | I49: 46265 | J49: 20 | K49: 26 | M49: 2827593 | N49: 0 | O49: 15000 | R49: #VALUE! | S49: Hari Kerja: 20 / 26 x 2827593
A50: 49 | B50: Fahrur Reza | C50: SPG/SPB Toko | D50: JABO | E50: JABO - SPN HOUSEWARE | F50: 25 Jul 2026 - 24 Aug 2026 | G50: inactive | H50: 45712 | I50: 46265 | J50: 27 | K50: 26 | M50: 5729876 | N50: 0 | O50: 15000 | R50: #VALUE! | S50: Hari Kerja: 27 / 26 x 5729876
A51: 50 | B51: Yahya | C51: SPG/SPB Toko | D51: JABO | E51: JABO - JAWA ELEKTRONIK | F51: 25 Jul 2026 - 24 Aug 2026 | G51: inactive | H51: 45712 | I51: 46265 | J51: 27 | K51: 26 | M51: 5729876 | N51: 0 | O51: 15000 | R51: #VALUE! | S51: Hari Kerja: 27 / 26 x 5729876
A52: 51 | B52: Diah Catur Apriani | C52: SPG/SPB Toko | D52: SEMARANG | E52: SEMARANG - DEPO PELITA | F52: 25 Jul 2026 - 24 Aug 2026 | G52: inactive | H52: 45714 | I52: 46265 | J52: 27 | K52: 26 | M52: 2474598 | N52: 0 | O52: 15000 | R52: #VALUE! | S52: Hari Kerja: 27 / 26 x 2474598
A53: 52 | B53: Juike Antika Rompis | C53: SPG/SPB Toko | D53: MAKASSAR | E53: MAKASSAR - ANUGRAH JAYA PALU | F53: 25 Jul 2026 - 24 Aug 2026 | G53: inactive | H53: 45719 | I53: 46265 | J53: 23 | K53: 26 | M53: 4148179 | N53: 0 | O53: 15000 | P53: 439000 | R53: 3265543 | S53: Hari Kerja: 23 / 26 x 4148179
A54: 53 | B54: Widya Kusuma | C54: SPG/SPB Toko | D54: MEDAN | E54: MEDAN - BALIKADO MENTENG | F54: 25 Jul 2026 - 24 Aug 2026 | G54: inactive | H54: 45741 | I54: 46265 | J54: 25 | K54: 26 | M54: 4335198 | N54: 0 | O54: 15000 | R54: #VALUE! | S54: Hari Kerja: 25 / 26 x 4335198
A55: 54 | B55: Mohammad Nur Fadilah | C55: SPG/SPB Toko | D55: SAMARINDA | E55: SAMARINDA - SURYA JAYA BALIKPAPAN | F55: 25 Jul 2026 - 24 Aug 2026 | G55: inactive | H55: 45761 | I55: 46265 | J55: 25 | K55: 26 | M55: 3856694 | N55: 0 | O55: 15000 | P55: 1840500 | R55: 1902860 | S55: Hari Kerja: 25 / 26 x 3856694
A56: 55 | B56: Widana | C56: SPG/SPB Toko | D56: PALEMBANG | E56: PALEMBANG - ANUGERAH SUKSES | F56: 25 Jul 2026 - 24 Aug 2026 | G56: inactive | H56: 45769 | I56: 46265 | J56: 31 | K56: 26 | M56: 3942963 | N56: 0 | O56: 15000 | R56: #VALUE! | S56: Hari Kerja: 31 / 26 x 3942963
A57: 56 | B57: Siti Maryam | C57: SPG/SPB Toko | D57: JABO | E57: JABO - CAHAYA BARU | F57: 25 Jul 2026 - 24 Aug 2026 | G57: inactive | H57: 45796 | I57: 46265 | J57: 26 | K57: 26 | M57: 5437203 | N57: 0 | O57: 15000 | R57: #VALUE! | S57: Hari Kerja: 26 / 26 x 5437203
A58: 57 | B58: Herdy Yansyah | C58: SPG/SPB Toko | D58: PALEMBANG | E58: PALEMBANG - CV ANEKA JAYA ELEKTRONIK | F58: 25 Jul 2026 - 24 Aug 2026 | G58: inactive | H58: 45784 | I58: 46265 | J58: 24 | K58: 26 | M58: 4192837 | N58: 0 | O58: 15000 | R58: #VALUE! | S58: Hari Kerja: 24 / 26 x 4192837
A59: 58 | B59: Winda Mardiana | C59: SPG/SPB Toko | D59: BATAM | E59: BATAM - UNIVERSAL PASIR PUTIH | F59: 25 Jul 2026 - 24 Aug 2026 | G59: inactive | H59: 45796 | I59: 46265 | J59: 27 | K59: 26 | M59: 5357982 | N59: 0 | O59: 15000 | R59: #VALUE! | S59: Hari Kerja: 27 / 26 x 5357982
A60: 59 | B60: Darussalam | C60: SPG/SPB Toko | D60: MAKASSAR | E60: MAKASSAR - GRAND TOSERBA PENGAYOMAN | F60: 25 Jul 2026 - 24 Aug 2026 | G60: inactive | H60: 45803 | I60: 46265 | J60: 26 | K60: 26 | M60: 4148179 | N60: 0 | O60: 15000 | R60: #VALUE! | S60: Hari Kerja: 26 / 26 x 4148179
A61: 60 | B61: Elga Pratangkas | C61: SPG/SPB Toko | D61: SURABAYA | E61: SURABAYA - BARES | F61: 25 Jul 2026 - 24 Aug 2026 | G61: inactive | H61: 45810 | I61: 46265 | J61: 26 | K61: 26 | M61: 2989145 | N61: 0 | O61: 15000 | R61: #VALUE! | S61: Hari Kerja: 26 / 26 x 2989145
A62: 61 | B62: Ahmad Gumilar | C62: SPG/SPB Toko | D62: SEMARANG | E62: SEMARANG - PASIFIK PEKOJAN | F62: 25 Jul 2026 - 24 Aug 2026 | G62: inactive | H62: 45812 | I62: 46265 | J62: 24 | K62: 26 | M62: 3701709 | N62: 0 | O62: 15000 | P62: 750000 | R62: 2701962 | S62: Hari Kerja: 24 / 26 x 3701709
A63: 62 | B63: Munjiyah Agus Cancetta | C63: SPG/SPB Toko | D63: BANJARMASIN | E63: BANJARMASIN - HOKKY OMEGA SAMPIT | F63: 25 Jul 2026 - 24 Aug 2026 | G63: inactive | H63: 45817 | I63: 46265 | J63: 28 | K63: 26 | M63: 3756643 | N63: 0 | O63: 15000 | P63: 474000 | R63: 3606616 | S63: Hari Kerja: 28 / 26 x 3756643
A64: 63 | B64: Merliani Anissa Rachman | C64: SPG/SPB Toko | D64: SAMARINDA | E64: SAMARINDA - NUANSA BERAU | F64: 25 Jul 2026 - 24 Aug 2026 | G64: inactive | H64: 45817 | I64: 46265 | J64: 29 | K64: 26 | M64: 4391337 | N64: 0 | O64: 15000 | P64: 750000 | R64: 4183030 | S64: Hari Kerja: 29 / 26 x 4391337
A65: 64 | B65: Agustina Galuh Prihaningtyas | C65: SPG/SPB Toko | D65: SEMARANG | E65: SEMARANG - UFO YOGYAKARTA JOKTENG | F65: 25 Jul 2026 - 24 Aug 2026 | G65: inactive | H65: 45819 | I65: 46265 | J65: 28 | K65: 26 | M65: 2827593 | N65: 0 | O65: 15000 | R65: #VALUE! | S65: Hari Kerja: 28 / 26 x 2827593
A66: 65 | B66: Devi Isvaradilla Agrully | C66: SPG/SPB Toko | D66: SAMARINDA | E66: SAMARINDA - NUANSA BALIKPAPAN | F66: 25 Jul 2026 - 24 Aug 2026 | G66: inactive | H66: 45824 | I66: 46265 | J66: 26 | K66: 26 | M66: 3856694 | N66: 0 | O66: 15000 | P66: 750000 | R66: 3141694 | S66: Hari Kerja: 26 / 26 x 3856694
A67: 66 | B67: Reva Azzahra | C67: SPG/SPB Toko | D67: SEMARANG | E67: SEMARANG - CANDI ELECTRONIC KARTASURA | F67: 25 Jul 2026 - 24 Aug 2026 | G67: inactive | H67: 45826 | I67: 46265 | J67: 27 | K67: 26 | M67: 2500000 | N67: 0 | O67: 15000 | R67: #VALUE! | S67: Hari Kerja: 27 / 26 x 2500000
A68: 67 | B68: Khoirunnisa Yuliana | C68: SPG/SPB Toko | D68: BANJARMASIN | E68: BANJARMASIN - CENTRAL PLASTIK PALANGKARAYA | F68: 25 Jul 2026 - 24 Aug 2026 | G68: inactive | H68: 45835 | I68: 46265 | J68: 24 | K68: 26 | M68: 3686138 | N68: 0 | O68: 15000 | R68: #VALUE! | S68: Hari Kerja: 24 / 26 x 3686138
A69: 68 | B69: Siti Arimah | C69: SPG/SPB Toko | D69: JABO | E69: JABO - TOKO AMAC | F69: 25 Jul 2026 - 24 Aug 2026 | G69: inactive | H69: 45838 | I69: 46265 | J69: 27 | K69: 26 | M69: 5399405 | N69: 0 | O69: 15000 | R69: #VALUE! | S69: Hari Kerja: 27 / 26 x 5399405
A70: 69 | B70: Siti Maslikah | C70: SPG/SPB Toko | D70: SEMARANG | E70: SEMARANG - ATLANTA MAJAPAHIT | F70: 25 Jul 2026 - 24 Aug 2026 | G70: inactive | H70: 45839 | I70: 46265 | J70: 29 | K70: 26 | M70: 3701709 | N70: 0 | O70: 15000 | R70: #VALUE! | S70: Hari Kerja: 29 / 26 x 3701709
A71: 70 | B71: Charles Setiawan | C71: SPG/SPB Toko | D71: PONTIANAK | E71: PONTIANAK - TOKO PUTRA ELEKTRONIK | F71: 25 Jul 2026 - 24 Aug 2026 | G71: inactive | H71: 45845 | I71: 46265 | J71: 30 | K71: 26 | M71: 3205220 | N71: 0 | O71: 15000 | P71: 1588500 | R71: 2144831 | S71: Hari Kerja: 30 / 26 x 3205220
A72: 71 | B72: Febry Valentino | C72: SPG/SPB Toko | D72: SAMARINDA | E72: SAMARINDA - NUANSA ELEKTRONIK BONTANG | F72: 25 Jul 2026 - 24 Aug 2026 | G72: inactive | H72: 45915 | I72: 46265 | J72: 27 | K72: 26 | M72: 3799480 | N72: 0 | O72: 15000 | P72: 1683500 | R72: 2297114 | S72: Hari Kerja: 27 / 26 x 3799480
A73: 72 | B73: Elisabeth NoviYanti Ayu N | C73: SPG/SPB Toko | D73: SURABAYA | E73: SURABAYA - TOKO JAYA KITCHEN LOMBOK | F73: 25 Jul 2026 - 24 Aug 2026 | G73: inactive | H73: 45920 | I73: 46265 | J73: 23 | K73: 26 | M73: 3019015 | N73: 0 | O73: 15000 | R73: #VALUE! | S73: Hari Kerja: 23 / 26 x 3019015
A74: 73 | B74: Intan Kristiani Laoli | C74: SPG/SPB Toko | D74: BATAM | E74: BATAM - JACKSON'S HOMEWARE MARKET | F74: 25 Jul 2026 - 24 Aug 2026 | G74: inactive | H74: 45924 | I74: 46265 | J74: 26 | K74: 26 | M74: 5357982 | N74: 0 | O74: 15000 | P74: 750000 | R74: 4642982 | S74: Hari Kerja: 26 / 26 x 5357982
A75: 74 | B75: Nurista Afninda Waqiatul Q | C75: SPG/SPB Toko | D75: BATAM | E75: BATAM - TOP 100 SWALAYAN | F75: 25 Jul 2026 - 24 Aug 2026 | G75: inactive | H75: 45934 | I75: 46265 | J75: 28 | K75: 26 | M75: 5357982 | N75: 0 | O75: 15000 | P75: 700000 | R75: 5105134 | S75: Hari Kerja: 28 / 26 x 5357982
A76: 75 | B76: Priya thadgea | C76: SPG/SPB Toko | D76: SEMARANG | E76: SEMARANG - ADA SWALAYAN SETIABUDI | F76: 25 Jul 2026 - 24 Aug 2026 | G76: inactive | H76: 45938 | I76: 46265 | J76: 27 | K76: 26 | M76: 3701709 | N76: 0 | O76: 15000 | P76: 807500 | R76: 3071582 | S76: Hari Kerja: 27 / 26 x 3701709
A77: 76 | B77: Umayah mirani | C77: SPG/SPB Toko | D77: SEMARANG | E77: SEMARANG - HERO HOUSEWARE | F77: 25 Jul 2026 - 24 Aug 2026 | G77: inactive | H77: 45940 | I77: 46265 | J77: 27 | K77: 26 | M77: 2474598 | N77: 0 | O77: 15000 | R77: #VALUE! | S77: Hari Kerja: 27 / 26 x 2474598
A78: 77 | B78: Anisa Nurajijah | C78: SPG/SPB Toko | D78: PONTIANAK | E78: PONTIANAK - OSCAR GEMILANG | F78: 25 Jul 2026 - 24 Aug 2026 | G78: inactive | H78: 45957 | I78: 46265 | J78: 29 | K78: 26 | M78: 3561801 | N78: 0 | O78: 15000 | P78: 750000 | R78: 3257778 | S78: Hari Kerja: 29 / 26 x 3561801
A79: 78 | B79: Wahyu Hidayat | C79: SPG/SPB Toko | D79: BANDUNG | E79: BANDUNG - YOGYA RIAU JUNCTION | F79: 25 Jul 2026 - 24 Aug 2026 | G79: inactive | H79: 45996 | I79: 46265 | J79: 26 | K79: 26 | M79: 4737678 | N79: 0 | O79: 15000 | P79: 1939000 | R79: 2833678 | S79: Hari Kerja: 26 / 26 x 4737678
A80: 79 | B80: Fuji Restu Nurani | C80: SPG/SPB Toko | D80: BANDUNG | E80: BANDUNG - MUTIARA SUPER KITCHEN | F80: 25 Jul 2026 - 24 Aug 2026 | G80: inactive | H80: 45996 | I80: 46265 | J80: 26 | K80: 26 | M80: 4737678 | N80: 0 | O80: 15000 | P80: 1857000 | R80: 2915678 | S80: Hari Kerja: 26 / 26 x 4737678
A81: 80 | B81: Syfa Dwi Ayu Cahyani | C81: SPG/SPB Toko | D81: SURABAYA | E81: SURABAYA - BARES ROGOJAMPI | F81: 25 Jul 2026 - 24 Aug 2026 | G81: inactive | H81: 46000 | I81: 46265 | J81: 27 | K81: 26 | M81: 2989145 | N81: 0 | O81: 15000 | R81: #VALUE! | S81: Hari Kerja: 27 / 26 x 2989145
A82: 81 | B82: Mawar | C82: SPG/SPB Toko | D82: SAMARINDA | E82: SAMARINDA - NUANSA MATOS SAMARINDA | F82: 25 Jul 2026 - 24 Aug 2026 | G82: inactive | H82: 46002 | I82: 46265 | J82: 29 | K82: 26 | M82: 3983882 | N82: 0 | O82: 15000 | R82: #VALUE! | S82: Hari Kerja: 29 / 26 x 3983882
A83: 82 | B83: Devi Eriyanti | C83: SPG/SPB Toko | D83: BANJARMASIN | E83: BANJARMASIN - PONDOK ELEKTRONIK BANJARBARU | F83: 25 Jul 2026 - 24 Aug 2026 | G83: inactive | H83: 46008 | I83: 46265 | J83: 27 | K83: 26 | M83: 3843037 | N83: 0 | O83: 15000 | P83: 964000 | R83: 3061846 | S83: Hari Kerja: 27 / 26 x 3843037
A84: 83 | B84: Hagai Hendrik Yonathan | C84: SPG/SPB Toko | D84: SURABAYA | E84: SURABAYA - TOKO RAMAI JAYA JEMBER | F84: 25 Jul 2026 - 24 Aug 2026 | G84: inactive | H84: 46008 | I84: 46265 | J84: 27 | K84: 26 | M84: 3012197 | N84: 0 | O84: 15000 | R84: #VALUE! | S84: Hari Kerja: 27 / 26 x 3012197
A85: 84 | B85: Ayu Novitaningsih | C85: SPG/SPB Toko | D85: SURABAYA | E85: SURABAYA - CV SAMI JAYA | F85: 25 Jul 2026 - 24 Aug 2026 | G85: inactive | H85: 46015 | I85: 46265 | J85: 29 | K85: 26 | M85: 2549876 | N85: 0 | O85: 15000 | R85: #VALUE! | S85: Hari Kerja: 29 / 26 x 2549876
A86: 85 | B86: Sitti Aisyah Syafitri.H | C86: SPG/SPB Toko | D86: MAKASSAR | E86: MAKASSAR - ALASKA | F86: 25 Jul 2026 - 24 Aug 2026 | G86: inactive | H86: 46024 | I86: 46265 | J86: 25 | K86: 26 | M86: 4148179 | N86: 0 | O86: 15000 | P86: 944000 | R86: 3079634 | S86: Hari Kerja: 25 / 26 x 4148179
A87: 86 | B87: Wartini | C87: SPG/SPB Toko | D87: SEMARANG | E87: SEMARANG - SINAR JAYA | F87: 25 Jul 2026 - 24 Aug 2026 | G87: inactive | H87: 46027 | I87: 46265 | J87: 27 | K87: 26 | M87: 2880798 | N87: 0 | O87: 15000 | R87: #VALUE! | S87: Hari Kerja: 27 / 26 x 2880798
A88: 87 | B88: Moy Yustiwa Rahayu Putri Kartika | C88: SPG/SPB Toko | D88: SURABAYA | E88: SURABAYA - HARTONO BG JUNCTION | F88: 25 Jul 2026 - 24 Aug 2026 | G88: inactive | H88: 46022 | I88: 46265 | J88: 26 | K88: 26 | M88: 5288796 | N88: 0 | O88: 15000 | R88: #VALUE! | S88: Hari Kerja: 26 / 26 x 5288796
A89: 88 | B89: Mardatillah | C89: SPG/SPB Toko | D89: SURABAYA | E89: SURABAYA - HARTONO SIDOARJO | F89: 25 Jul 2026 - 24 Aug 2026 | G89: inactive | H89: 46022 | I89: 46265 | J89: 25 | K89: 26 | M89: 5191541 | N89: 0 | O89: 15000 | R89: #VALUE! | S89: Hari Kerja: 25 / 26 x 5191541
A90: 89 | B90: Mohammad Hidayat | C90: SPG/SPB Toko | D90: SEMARANG | E90: SEMARANG - TOKO DEPO MURAH JAYA SENTOSA KUDUS | F90: 25 Jul 2026 - 24 Aug 2026 | G90: inactive | H90: 46034 | I90: 46265 | J90: 27 | K90: 26 | M90: 2818585 | N90: 0 | O90: 15000 | R90: #VALUE! | S90: Hari Kerja: 27 / 26 x 2818585
A91: 90 | B91: Neni Rahayu | C91: SPG/SPB Toko | D91: SURABAYA | E91: SURABAYA - DAPUR KITA MATARAM | F91: 25 Jul 2026 - 24 Aug 2026 | G91: inactive | H91: 46034 | I91: 46265 | J91: 27 | K91: 26 | M91: 3019015 | N91: 0 | O91: 15000 | R91: #VALUE! | S91: Hari Kerja: 27 / 26 x 3019015
A92: 91 | B92: Deni Lindiansah | C92: SPG/SPB Toko | D92: BANDUNG | E92: BANDUNG - HARTONO | F92: 25 Jul 2026 - 24 Aug 2026 | G92: inactive | H92: 46036 | I92: 46265 | J92: 27 | K92: 26 | M92: 4737678 | N92: 0 | O92: 15000 | R92: #VALUE! | S92: Hari Kerja: 27 / 26 x 4737678
A93: 92 | B93: Rista bellawati basuki | C93: SPG/SPB Toko | D93: SURABAYA | E93: SURABAYA - HARTONO KERTAJAYA INDAH | F93: 25 Jul 2026 - 24 Aug 2026 | G93: inactive | H93: 46043 | I93: 46265 | J93: 27 | K93: 26 | M93: 5288796 | N93: 0 | O93: 15000 | P93: 672000 | R93: 4855211 | S93: Hari Kerja: 27 / 26 x 5288796
A94: 93 | B94: Bagus Dwi Ardiansyah | C94: SPG/SPB Toko | D94: SURABAYA | E94: SURABAYA - HARTONO BUKIT DARMO | F94: 25 Jul 2026 - 24 Aug 2026 | G94: inactive | H94: 46047 | I94: 46265 | J94: 27 | K94: 26 | M94: 5288796 | N94: 0 | O94: 15000 | R94: #VALUE! | S94: Hari Kerja: 27 / 26 x 5288796
A95: 94 | B95: Muhtar | C95: SPG/SPB Toko | D95: BANDUNG | E95: BANDUNG - BLIBLI ELEKTRONIK MOCH TOHA | F95: 25 Jul 2026 - 24 Aug 2026 | G95: inactive | H95: 46055 | I95: 46265 | J95: 28 | K95: 26 | M95: 4737678 | N95: 0 | O95: 15000 | P95: 860500 | R95: 4276615 | S95: Hari Kerja: 28 / 26 x 4737678
A96: 95 | B96: Liya Nataliya | C96: SPG/SPB Toko | D96: JABO | E96: JABO - TOKO ATRIA KELAPA GADING | F96: 25 Jul 2026 - 24 Aug 2026 | G96: inactive | H96: 45561 | I96: 46265 | J96: 27 | K96: 26 | L96: 2 | M96: 5729876 | N96: 0 | O96: 15000 | P96: 750000 | R96: 5265256 | S96: Hari Kerja: 27 / 26 x 5729876 | T96: Total jam lembur yang disetujui = 2
A97: 96 | B97: Isma Kurniawati | C97: SPG/SPB Toko | D97: BANDUNG | E97: BANDUNG - TOKO PANTES AGUNG (ONLINE) | F97: 25 Jul 2026 - 24 Aug 2026 | G97: inactive | H97: 46055 | I97: 46265 | J97: 29 | K97: 26 | M97: 4737678 | N97: 0 | O97: 15000 | P97: 1640000 | R97: 3679333 | S97: Hari Kerja: 29 / 26 x 4737678
A98: 97 | B98: Prakas Armando Yuwono | C98: SPG/SPB Toko | D98: SURABAYA | E98: SURABAYA - HARTONO MALANG | F98: 25 Jul 2026 - 24 Aug 2026 | G98: inactive | H98: 46074 | I98: 46265 | J98: 24 | K98: 26 | M98: 3736101 | N98: 0 | O98: 15000 | P98: 1255500 | R98: 2228209 | S98: Hari Kerja: 24 / 26 x 3736101
A99: 98 | B99: Rekha Riakiah | C99: Promotor Live | D99: JABO | E99: JABO - TOKO PALAPA | F99: 25 Jul 2026 - 24 Aug 2026 | G99: inactive | H99: 46079 | I99: 46265 | J99: 22 | K99: 26 | M99: 5729876 | N99: 0 | O99: 15000 | R99: #VALUE! | S99: Hari Kerja: 22 / 26 x 5729876
A100: 99 | B100: Utami Septi Cahyani | C100: SPG/SPB Toko | D100: BANJARMASIN | E100: BANJARMASIN - GLOBALMART BATULICIN | F100: 25 Jul 2026 - 24 Aug 2026 | G100: inactive | H100: 46083 | I100: 46265 | J100: 31 | K100: 26 | M100: 3736000 | N100: 0 | O100: 15000 | R100: #VALUE! | S100: Hari Kerja: 31 / 26 x 3736000
...

Sheet data StaffInc
A1: Employee ID* | B1: Name* | C1: Phone Number* | D1: Email | E1: Position | F1: Gender | G1: KTP Number | H1: Date of Birth | I1: Birth Place Code | J1: Religion | K1: Blood Type | L1: Marital Status | M1: Domicile Province Code | N1: Domicile City Code | O1: Domicile District Code | P1: Domicile Address | Q1: Status* | R1: Join Date | S1: Deactivation Type | T1: Receive Resignation Request At | U1: Last Day | V1: Inactive Reason | W1: Inactive Notes | X1: External Employee ID | Y1: Entity | Z1: Deployment Province Code | AA1: Deployment City Code | AB1: Deployment District Code | AC1: Deployment Group | AD1: Employement type | AE1: Contract type | AF1: Digital Signature ID | AG1: Active Contract start date | AH1: Active Contract end date | AI1: Project | AJ1: Branch ID | AK1: Payroll Group ID | AL1: Leave Policy | AM1: BPJS TK Number | AN1: BPJS Kesehatan Number | AO1: NPWP | AP1: BPJS Kesehatan Eligibility | AQ1: BPJS TK Eligibility | AR1: BPJS TK Membership | AS1: BPJS TK Program | AT1: PTKP Status | AU1: Payment Channel Type | AV1: Payment Channel Code | AW1: Payment Account Name | AX1: Payment Account Number | AY1: Emergency Contact’s Full Name | AZ1: Emergency Contact’s Phone Number | BA1: Emergency Contact’s Address | BB1: Emergency Contact's Relation to Employee
A2: 187078 | B2: Anggiza Gana Pawestri | C2: 87887345099 | D2: anggi_zhie@yahoo.com | E2: SPG/SPB Toko | F2: Female | G2: 3175104409860007 | H2: 31659 | I2: 694 | J2: Islam | K2: O | L2: Kawin | M2: 11 | N2: 694 | O2: 2006 | P2: Jl. Buni Malaka, Rt. 006, Rw. 008, Kel. Munjul, Kec. Cipayung | Q2: Inactive | R2: 43409 | S2: Now | U2: 46265 | W2: selesai project | X2: 20181101 | Y2: PT Kita Mitra Indonesia | Z2: 12 | AA2: 721 | AD2: Full-Time | AE2: Kemitraan | AG2: 46167 | AH2: 46265 | AJ2: 11073 | AM2: 21033169232 | AN2: 1737584458 | AO2: 589400142009000 | AP2: Inactive | AQ2: Active | AR2: BPU | AS2: JKM;JKK | AT2: TK/1 | AU2: Bank | AV2: BCA | AW2: ANGGIZA GANA PAWESTRI | AX2: 8691115984 | AY2: Rangga | AZ2: 85772005148 | BA2: Jl.buni malaka GG mushola 1 Rt06/08 no 15 | BB2: Suami
A3: 187079 | B3: Annisa | C3: 85754771101 | D3: annisaauliani11@gmail.com | E3: SPG/SPB Toko | F3: Female | G3: 6.3710251e+15 | H3: 33553 | I3: 891 | J3: Islam | K3: O | L3: Kawin | M3: 22 | N3: 891 | O3: 5055 | P3: Keramat Raya Gg Satu Dua Rt.10 No.37D Kecamatan Banjarmasin Timur Kelurahan Sungai Bilu Banjarmasin 70236 | Q3: Inactive | R3: 42826 | S3: Now | U3: 46265 | W3: selesai project | X3: 20170401 | Y3: PT Kita Mitra Indonesia | Z3: 22 | AA3: 891 | AD3: Full-Time | AE3: Kemitraan | AG3: 46167 | AH3: 46265 | AJ3: 11060 | AM3: 23048929410 | AN3: 2044139477 | AO3: 755898756731000 | AP3: Inactive | AQ3: Active | AR3: BPU | AS3: JKM;JKK | AT3: K/3 | AU3: Bank | AV3: BCA | AW3: ANNISA | AX3: 511915910 | AY3: rini yulianti | AZ3: 82150088297 | BA3: jl keramat gg satu dua rt.10 no.37d | BB3: Ibu
A4: 187085 | B4: Firda Duri Yatinal Ulya | C4: 82128843818 | D4: firdaduriatinalulya@gmail.com | E4: SPG/SPB Toko | F4: Female | G4: 6472056708950005 | H4: 34938 | I4: 901 | J4: Islam | L4: Belum Kawin | M4: 23 | N4: 901 | O4: 1418 | P4: Jl. Pemuda 2 Gg. Pendawa Blok. E. No. 86, Rt. 012, Rw.000, Kel. Temindung Permai, Kec. Sungai Pinang | Q4: Inactive | R4: 43777 | S4: Now | U4: 46265 | W4: selesai project | X4: 20191101 | Y4: PT Kita Mitra Indonesia | Z4: 23 | AA4: 901 | AD4: Full-Time | AE4: Kemitraan | AG4: 46167 | AH4: 46265 | AJ4: 11113 | AM4: 23048929329 | AN4: 2265201641 | AO4: 940212715722000 | AP4: Inactive | AQ4: Active | AR4: BPU | AS4: JKM;JKK | AT4: TK/0 | AU4: Bank | AV4: BCA | AW4: FIRDA DURI YATINAL ULYA | AX4: 7935297133 | AY4: Ani | AZ4: 85845230207 | BA4: jl.gelatik blok.c | BB4: Saudara Kandung
A5: 187089 | B5: Elisa Putra Afdiono | C5: 89686949505 | D5: zolla041123@gmail.com | E5: SPG/SPB Toko | F5: Female | G5: 3578024803960005 | H5: 35132 | I5: 801 | J5: Islam | K5: O | L5: Kawin | M5: 15 | N5: 801 | O5: 3921 | P5: Margorejo 2-G/32, Rt. 004, Rw. 003, Kel. Margorejo, Kec. Wonocolo | Q5: Inactive | R5: 44077 | S5: Now | U5: 46265 | W5: selesai project | X5: 20200902 | Y5: PT Kita Mitra Indonesia | Z5: 15 | AA5: 801 | AD5: Full-Time | AE5: Kemitraan | AG5: 46167 | AH5: 46265 | AJ5: 11202 | AM5: 23048929493 | AN5: 786612418 | AO5: 726397177609000 | AP5: Inactive | AQ5: Active | AR5: BPU | AS5: JKM;JKK | AT5: TK/0 | AU5: Bank | AV5: BCA | AW5: ELISA PUTRA AFDIONO | AX5: 5600289308 | AY5: andre | AZ5: 8990008817 | BA5: margorejo 2g no 32 | BB5: Suami
A6: 187090 | B6: I Ketut Sugiarta | C6: 82193339184 | D6: sugiartha9977@gmail.com | E6: SPG/SPB Toko | F6: Male | G6: 7208090909970002 | H6: 35682 | I6: 930 | J6: Hindu | K6: O | L6: Belum Kawin | M6: 26 | N6: 930 | O6: 5503 | P6: Dusun Iv , Rt. 000 , Rw. 000 , Kel. Tolai Barat , Kec. Torue - Sulawesi Tengah | Q6: Inactive | R6: 44753 | S6: Now | U6: 46265 | W6: selesai project | X6: 20220703 | Y6: PT Kita Mitra Indonesia | Z6: 27 | AA6: 957 | AD6: Full-Time | AE6: Kemitraan | AG6: 46198 | AH6: 46265 | AJ6: 11091 | AM6: 23048929451 | AN6: 2392202924 | AO6: 437589070831000 | AP6: Inactive | AQ6: Active | AR6: BPU | AS6: JKM;JKK | AT6: TK/0 | AU6: Bank | AV6: BCA | AW6: I KETUT SUGIARTA | AX6: 7795175946
A7: 187092 | B7: Adelina Astuti | C7: 85849233099 | D7: adelinemeidian@gmail.com | E7: SPG/SPB Outlet | F7: Female | G7: 3207195305920001 | H7: 33737 | I7: 704 | J7: Islam | K7: AB | L7: Belum Kawin | M7: 12 | N7: 704 | O7: 2256 | P7: Dusun Tamansari , Rt. 012 , Rw. 004 , Kel. Kertahayu , Kec. Pamarican - Jawa Barat | Q7: Inactive | R7: 44852 | S7: Now | U7: 46265 | V7: Finished - End of Contract | W7: selesai project | X7: 20221006 | Y7: PT Kita Mitra Indonesia | Z7: 11 | AA7: 697 | AD7: Full-Time | AE7: Kemitraan | AG7: 46167 | AH7: 46265 | AJ7: 11354 | AN7: 437862701 | AO7: 614250264442000 | AP7: Inactive | AQ7: Active | AR7: BPU | AS7: JKM;JKK | AT7: TK/0 | AU7: Bank | AV7: BCA | AW7: ADELINA ASTUTI | AX7: 5910185235
A8: 187093 | B8: Ari Kusumawati | C8: 85780008440 | D8: nayarengganis25@gmail.com | E8: SPG/SPB Outlet | F8: Female | G8: 3171026709890003 | H8: 32778 | I8: 695 | J8: Islam | K8: O | L8: Belum Kawin | M8: 11 | N8: 695 | O8: 1966 | P8: Jl. Gn Sahari Ix , Rt. 005 , Rw. 004 , Kel. Gunung Sahari Utara , Kec. Sawah Besar - Jakarta Pusat | Q8: Inactive | R8: 44844 | S8: Now | U8: 46265 | W8: selesai project | X8: 20221004 | Y8: PT Kita Mitra Indonesia | Z8: 11 | AA8: 697 | AD8: Full-Time | AE8: Kemitraan | AG8: 46167 | AH8: 46265 | AJ8: 11354 | AM8: 17000717391 | AN8: 373457902 | AO8: 984389981026000 | AP8: Inactive | AQ8: Active | AR8: BPU | AS8: JKM;JKK | AT8: TK/0 | AU8: Bank | AV8: BCA | AW8: ARI KUSUMAWATI | AX8: 6840428964
A9: 187095 | B9: Firda Nur Agustin Cahyani | C9: 87842322685 | D9: firdanac1608@gmail.com | E9: SPG/SPB Toko | F9: Female | G9: 3205055608020002 | H9: 37484 | I9: 702 | J9: Islam | K9: A | L9: Belum Kawin | M9: 12 | N9: 702 | O9: 2161 | P9: Kp. Leuwi Daun , Rt. 003 , Rw. 008 , Kel. Haurpanggung , Kec. Tarogong Kidul - Jawa Barat | Q9: Inactive | R9: 44858 | S9: Now | U9: 46265 | W9: selesai project | X9: 20221008 | Y9: PT Kita Mitra Indonesia | Z9: 12 | AA9: 702 | AD9: Full-Time | AE9: Kemitraan | AG9: 46167 | AH9: 46265 | AJ9: 11049 | AM9: 23048929402 | AN9: 3045761223 | AO9: 637892589443000 | AP9: Inactive | AQ9: Active | AR9: BPU | AS9: JKM;JKK | AT9: TK/0 | AU9: Bank | AV9: BCA | AW9: FIRDA NUR AGUSTIN CAHYAN | AX9: 4460703641
A10: 187096 | B10: Habib Mustopa | C10: 88985069845 | D10: habibmustopa25@gmail.com | E10: SPG/SPB Toko | F10: Male | G10: 3205312107020002 | H10: 37458 | I10: 702 | J10: Islam | K10: A | L10: Belum Kawin | M10: 12 | N10: 702 | O10: 2187 | P10: Kp Cihikeu , Rt. 001 , Rw. 003 , Kel. Cihikeu , Kec. Bungbulang - Jawa Barat | Q10: Inactive | R10: 44911 | S10: Now | U10: 46265 | W10: selesai project | X10: 20221201 | Y10: PT Kita Mitra Indonesia | Z10: 13 | AA10: 757 | AD10: Full-Time | AE10: Kemitraan | AG10: 46198 | AH10: 46265 | AJ10: 11126 | AM10: 23048929386 | AN10: 1198164565 | AO10: 623212982423000 | AP10: Inactive | AQ10: Active | AR10: BPU | AS10: JKM;JKK | AT10: TK/0 | AU10: Bank | AV10: BCA | AW10: HABIB MUSTOPA | AX10: 2801851268 | AY10: imas masliah | AZ10: 85759557515 | BA10: Jln Cihikeu Desa Cihikeu Kec Bungbulang garut | BB10: Ibu
A11: 187104 | B11: Faisol Adha | C11: 85748348360 | D11: Faisol.adha03@gmail.com | E11: SPG/SPB Outlet | F11: Male | G11: 3506052009940003 | H11: 34597 | I11: 794 | J11: Islam | K11: A | L11: Belum Kawin | M11: 15 | N11: 770 | O11: 3380 | P11: Dsn. Pule Utara, Rt. 002, Rw. 001, Kel. Pule. Kec. Kandat | Q11: Inactive | R11: 45147 | S11: Now | U11: 46265 | W11: selesai project | X11: 20230804 | Y11: PT Kita Mitra Indonesia | Z11: 15 | AA11: 801 | AD11: Full-Time | AE11: Kemitraan | AG11: 46167 | AH11: 46265 | AJ11: 11194 | AM11: 21073634251 | AN11: 1642981026 | AO11: 669091779655000 | AP11: Inactive | AQ11: Active | AR11: BPU | AS11: JKM;JKK | AT11: TK/0 | AU11: Bank | AV11: BCA | AW11: FAISOL ADHA | AX11: 8220741924
A12: 187108 | B12: Fitri Wulandari | C12: 85753994944 | D12: wulan.rhevian22@gmail.com | E12: SPG/SPB Toko | F12: Female | G12: 6303036208870004 | H12: 32011 | I12: 773 | J12: Islam | K12: O | L12: Belum Kawin | M12: 22 | N12: 891 | O12: 5056 | P12: Jl. Ampera III Ujung, Rt. 038, Rw. 003, Kel. Basirih, Kec. Banjarmasin Barat | Q12: Inactive | R12: 45323 | S12: Now | U12: 46265 | W12: selesai project | X12: 20240204 | Y12: PT Kita Mitra Indonesia | Z12: 22 | AA12: 891 | AD12: Full-Time | AE12: Kemitraan | AG12: 46228 | AH12: 46265 | AJ12: 11065 | AM12: 24087351821 | AN12: 3107840848 | AO12: 609448345731000 | AP12: Inactive | AQ12: Active | AR12: BPU | AS12: JKM;JKK | AT12: TK/0 | AU12: Bank | AV12: BCA | AW12: FITRI WULANDARI | AX12: 8275329891
A13: 187109 | B13: Hendrika Buwa | C13: 85246946597 | D13: buwaqhendrika@gmail.com | E13: SPG/SPB Toko | F13: Female | G13: 6472064110950005 | H13: 34973 | I13: 899 | J13: Islam | K13: B | L13: Kawin | M13: 23 | N13: 901 | O13: 5164 | P13: Jl. Kh Agus Salim Gg. Tanjung/49, Rt. 036, Rw. 000, Kel. Sungai Pinang Luar, Samarinda Kota | Q13: Inactive | R13: 45327 | S13: Scheduled | T13: 46244 | U13: 46259 | V13: Resign - Get New Job | X13: 20240206 | Y13: PT Kita Mitra Indonesia | Z13: 23 | AA13: 901 | AD13: Full-Time | AE13: Kemitraan | AG13: 46167 | AH13: 46258 | AJ13: 11114 | AM13: 22033920558 | AN13: 1282675533 | AO13: 844473009722000 | AP13: Inactive | AQ13: Active | AR13: BPU | AS13: JKM;JKK | AT13: K/2 | AU13: Bank | AV13: BCA | AW13: HENDRIKA BUWA | AX13: 7935355427
A14: 187120 | B14: Agus Tianing Rum | C14: 811522178 | D14: ningrumtia03@gmail.com | E14: SPG/SPB Toko | F14: Female | G14: 3320136308000005 | H14: 36395 | I14: 744 | J14: Islam | K14: O | L14: Cerai hidup | M14: 21 | N14: 866 | O14: 4773 | P14: Jl. Kasan Rejo Rt/Rw.018/000, Kel. Sidorejo, Kec.Arut Selatan Kota.Waringin Barat, Kalimantan Tengah | Q14: Inactive | R14: 45546 | S14: Now | U14: 46265 | V14: Finished - End of Contract | W14: selesai project | X14: 20240909 | Y14: PT Kita Mitra Indonesia | Z14: 22 | AA14: 891 | AD14: Full-Time | AE14: Kemitraan | AG14: 46198 | AH14: 46265 | AJ14: 11063 | AM14: 24160946190 | AN14: 2434254276 | AO14: 500765599713000 | AP14: Inactive | AQ14: Active | AR14: BPU | AS14: JKM;JKK | AT14: TK/1 | AU14: Bank | AV14: BCA | AW14: AGUS TIANING RUM | AX14: 8585226544
A15: 187122 | B15: Jesty Ananda | C15: 895338933809 | D15: jestyananda903@gmail.com | E15: SPG/SPB Toko | F15: Female | G15: 6402064701040005 | H15: 37993 | I15: 895 | J15: Protestan | K15: B | L15: Belum Kawin | M15: 23 | N15: 895 | O15: 5079 | P15: Jl. Gunung Pegat No.13 Rt/Rw.035/000, Kel. Melayu, Kec. Tenggarong, Kab. Kutai Kartanegara, Kalimantan Timur | Q15: Inactive | R15: 45553 | S15: Now | U15: 46265 | V15: Finished - End of Contract | X15: 20240912 | Y15: PT Kita Mitra Indonesia | Z15: 23 | AA15: 901 | AD15: Full-Time | AE15: Kemitraan | AG15: 46167 | AH15: 46265 | AJ15: 11115 | AM15: 24160946208 | AO15: 200081255728000 | AP15: Inactive | AQ15: Active | AR15: BPU | AS15: JKM;JKK | AT15: TK/0 | AU15: Bank | AV15: BCA | AW15: JESTY ANANDA | AX15: 8145371186 | AY15: Iin paramitha utami | AZ15: 85350032333 | BA15: jln gn pegat,gg 01C,rumah kontrakan | BB15: Saudara Kandung
A16: 187123 | B16: Firanda | C16: 83872915839 | D16: fanda5833@gmail.com | E16: SPG/SPB Toko | F16: Female | G16: 1607064512060003 | H16: 39056 | J16: Islam | L16: Belum Kawin | M16: 6 | N16: 642 | O16: 730 | P16: Dusun Iv Desa Sungai Pinang Rt/Rw.024/000 Kel. Sungaipinang, Kec. Rambutan, Kab. Banyuasin, Sumatera Selatan. | Q16: Inactive | R16: 45567 | S16: Now | U16: 46265 | W16: selesai project | X16: 20241005 | Y16: PT Kita Mitra Indonesia | Z16: 6 | AA16: 649 | AD16: Full-Time | AE16: Kemitraan | AG16: 46167 | AH16: 46265 | AJ16: 11107 | AM16: 24160946232 | AP16: Inactive | AQ16: Active | AR16: BPU | AS16: JKM;JKK | AT16: TK/0 | AU16: Bank | AV16: BCA | AW16: FIRANDA | AX16: 8435689139
A17: 187126 | B17: Dinda Sri Rahayu | C17: 89659753361 | D17: dindasrirahayu9@gmail.com | E17: SPG/SPB Toko | F17: Female | G17: 3204355911990003 | H17: 36483 | I17: 701 | J17: Islam | K17: O | L17: Belum Kawin | M17: 12 | N17: 701 | O17: 2149 | P17: Kp. Pangsor Rt 008, Rw 010. Kel.Sukamantri. Kec.Paseh, Kab. Bandung, Jawa Barat. | Q17: Inactive | R17: 45576 | S17: Now | U17: 46265 | W17: selesai project | X17: 20241011 | Y17: PT Kita Mitra Indonesia | Z17: 12 | AA17: 718 | AD17: Full-Time | AE17: Kemitraan | AG17: 46167 | AH17: 46265 | AJ17: 11055 | AM17: 24134943919 | AO17: 937047769444000 | AP17: Inactive | AQ17: Active | AR17: BPU | AS17: JKM;JKK | AT17: TK/0 | AU17: Bank | AV17: BCA | AW17: DINDA SRI RAHAYU | AX17: 3760618135 | AY17: nunung | AZ17: 89514887715 | BA17: kp. pangsor Rt.08/10 | BB17: Ibu
A18: 187132 | B18: Gusti Rusmiami | C18: 82253031413 | D18: ammygusti@gmail.com | E18: SPG/SPB Toko | F18: Female | G18: 6302064111930005 | H18: 34274 | J18: Islam | K18: A | L18: Kawin | M18: 22 | N18: 888 | O18: 3169 | P18: Komplek Loyang Indah Rt/Rw.011/00 Kel. Jangkung, Kec. Tanjung, Kab. Tabalong, Kalimantan Selatan. | Q18: Inactive | R18: 45627 | S18: Now | U18: 46265 | W18: selesai project | X18: 20241202 | Y18: PT Kita Mitra Indonesia | Z18: 22 | AA18: 891 | AD18: Full-Time | AE18: Kemitraan | AG18: 46167 | AH18: 46265 | AJ18: 11064 | AM18: 24217518620 | AO18: 147219026735000 | AP18: Inactive | AQ18: Active | AR18: BPU | AS18: JKM;JKK | AT18: TK/0 | AU18: Bank | AV18: BCA | AW18: GUSTI RUSMIAMI | AX18: 8695108539 | AY18: Rija Husaini | AZ18: 8125450053 | BA18: Jl Komp Loyan Indah Rt 11 | BB18: Suami
A19: 187135 | B19: Ela Siska Ariatun | C19: 82358812078 | D19: elasiska01@gmail.com | E19: SPG/SPB Toko | F19: Female | G19: 6401044908020005 | H19: 37477 | I19: 799 | J19: Islam | K19: B | L19: Kawin | M19: 23 | N19: 893 | O19: 5067 | P19: Jl. Modang Gg Rukun Rt/Rw.005/002 Kel. Tanah Grogot, Kec. Tanah Grogot, Kab. Paser, Kalimantan Timur. | Q19: Inactive | R19: 45647 | S19: Now | U19: 46265 | W19: selesai project | X19: 20241218 | Y19: PT Kita Mitra Indonesia | Z19: 23 | AA19: 901 | AD19: Full-Time | AE19: Kemitraan | AG19: 46198 | AH19: 46265 | AJ19: 11117 | AM19: 24217518612 | AN19: 2288253497 | AO19: 618137277726000 | AP19: Inactive | AQ19: Active | AR19: BPU | AS19: JKM;JKK | AT19: TK/0 | AU19: Bank | AV19: BCA | AW19: ELA SISKA ARIATUN | AX19: 7815831241
A20: 187138 | B20: Ainun Jariyah | C20: 895608199789 | D20: Program.ainun@gmail.com | E20: SPG/SPB Toko | F20: Female | G20: 6371014305950008 | H20: 34822 | I20: 891 | J20: Islam | K20: AB | L20: Belum Kawin | M20: 22 | N20: 891 | O20: 5054 | P20: Jl. Kelayan A Gg. Sidodadi. Rt/Rw. 011/001. Kel. Murung Raya. Kec. Banjarmasin Selatan | Q20: Inactive | R20: 45685 | S20: Now | U20: 46265 | V20: Finished - End of Contract | W20: selesai project | X20: 20250120 | Y20: PT Kita Mitra Indonesia | Z20: 22 | AA20: 891 | AD20: Full-Time | AE20: Kemitraan | AG20: 45901 | AH20: 46265 | AJ20: 11066 | AO20: 910303221736000 | AP20: Inactive | AQ20: Active | AR20: BPU | AS20: JKM;JKK | AT20: TK/0 | AU20: Bank | AV20: BCA | AW20: AINUN JARIAH | AX20: 7820819785 | AY20: sam | AZ20: 81348153855 | BA20: Kelayan A gang sidodadi | BB20: Ayah
A21: 187144 | B21: Fhadila Rahmatika Haya | C21: 85725663034 | D21: fadhilaarh19@gmail.com | E21: SPG/SPB Toko | F21: Female | G21: 3372035909000002 | H21: 36788 | I21: 755 | J21: Islam | K21: B | L21: Belum Kawin | M21: 13 | N21: 755 | O21: 3179 | P21: Sangkrah Rt/02 Rw/11. Kel. Sangkrah Kec. Pasar Kliwon | Q21: Inactive | R21: 45685 | S21: Now | U21: 46265 | W21: selesai project | X21: 20250121 | Y21: PT Kita Mitra Indonesia | Z21: 13 | AA21: 757 | AD21: Full-Time | AE21: Kemitraan | AG21: 46198 | AH21: 46265 | AJ21: 11145 | AN21: 1692987175 | AO21: 508108073526000 | AP21: Inactive | AQ21: Active | AR21: BPU | AS21: JKM;JKK | AT21: TK/0 | AU21: Bank | AV21: BCA | AW21: FHADILA RAHMATIKA HAYA | AX21: 1530616408
A22: 187145 | B22: Apriliyani | C22: 85727351515 | D22: aprilprily53@gmail.com | E22: SPG/SPB Toko | F22: Female | G22: 3322086004920002 | H22: 33714 | I22: 757 | J22: Islam | L22: Cerai hidup | M22: 13 | N22: 746 | O22: 3039 | P22: Dsn Lendoh. Ds. Bedono Rt/01 Rw/02 Kel. Jambu. Kab. Semarang | Q22: Inactive | R22: 45691 | S22: Now | U22: 46265 | W22: selesai project | X22: 20250203 | Y22: PT Kita Mitra Indonesia | Z22: 13 | AA22: 757 | AD22: Full-Time | AE22: Kemitraan | AG22: 46167 | AH22: 46265 | AJ22: 11128 | AM22: 16004816571 | AN22: 603512278 | AO22: 818964009505000 | AP22: Inactive | AQ22: Active | AR22: BPU | AS22: JKM;JKK | AT22: TK/0 | AU22: Bank | AV22: BCA | AW22: APRILIYANI | AX22: 3201041480
A23: 187150 | B23: Fahrur Reza | C23: 87851843056 | D23: ezaenii@gmail.com | E23: SPG/SPB Toko | F23: Male | G23: 3174081507951002 | H23: 34895 | I23: 693 | J23: Islam | K23: O | L23: Belum Kawin | M23: 11 | N23: 693 | O23: 1994 | P23: Jl. Warung Jati Timur. Gg. Ainul Yaqin No.41 Rt/Rw. 002/009. Kel Kalibata. Kec. Pancoran | Q23: Inactive | R23: 45712 | S23: Now | U23: 46265 | W23: selesai project | X23: 20250223 | Y23: PT Kita Mitra Indonesia | Z23: 11 | AA23: 697 | AD23: Full-Time | AE23: Kemitraan | AG23: 46167 | AH23: 46265 | AJ23: 11075 | AO23: 986551182061000 | AP23: Inactive | AQ23: Active | AR23: BPU | AS23: JKM;JKK | AT23: TK/0 | AU23: Bank | AV23: BCA | AW23: FAHRUR REZA | AX23: 1280346540 | AY23: Aryo Yuwono | AZ23: 895359849162 | BA23: Jl Guru Muhyin Blok Kancil 1 No 20 (Griya Bombay) Rt14 Rw02, Lenteng Agung Jagakarsa | BB23: Kerabat Dekat Lainnya
A24: 187151 | B24: Yahya | C24: 85179986982 | D24: yahyaharita2017@gmail.com | E24: SPG/SPB Toko | F24: Male | G24: 3603110306910001 | H24: 33392 | I24: 694 | J24: Islam | L24: Kawin | M24: 11 | N24: 694 | O24: 2002 | P24: Bojong Rangkong. Rt/Rw. 014/03. Kel. Pulo Gebang. Kec. Cakung | Q24: Inactive | R24: 45712 | S24: Now | U24: 46265 | X24: 20250225 | Y24: PT Kita Mitra Indonesia | Z24: 11 | AA24: 694 | AD24: Full-Time | AE24: Kemitraan | AG24: 46167 | AH24: 46265 | AJ24: 11076 | AN24: 808841305 | AO24: 224588533502000 | AP24: Inactive | AQ24: Active | AR24: BPU | AS24: JKM;JKK | AT24: K/1 | AU24: Bank | AV24: BCA | AW24: ELY SUPRIANI | AX24: 4080026311
A25: 187157 | B25: Widya Kusuma | C25: 81276880772 | D25: wkesuma809@gmail.com | E25: SPG/SPB Toko | F25: Female | G25: 1207256005990001 | H25: 36223 | I25: 590 | J25: Islam | K25: A | L25: Belum Kawin | M25: 2 | N25: 572 | O25: 407 | P25: Jl. Masjid Gg Teratai 23 Pasar X Tembung. Kel. Bandar Khalipah. Kec. Percut Sei Tuan | Q25: Inactive | R25: 45741 | S25: Now | U25: 46265 | X25: 20250317 | Y25: PT Kita Mitra Indonesia | Z25: 2 | AA25: 590 | AD25: Full-Time | AE25: Kemitraan | AG25: 46167 | AH25: 46265 | AJ25: 11223 | AO25: 631625779125000 | AP25: Inactive | AQ25: Active | AR25: BPU | AS25: JKM;JKK | AT25: TK/0 | AU25: Bank | AV25: BCA | AW25: WIDYA KUSUMA | AX25: 5585001675 | AY25: Linar Aifa | AZ25: 81276880772 | BA25: Jl Masjid Gg. Teratai 23 Pasar 11 Tembung | BB25: Ibu
A26: 187160 | B26: Widana | C26: 895603182217 | D26: wwid956@gmail.com | E26: SPG/SPB Toko | F26: Female | G26: 1673015709950001 | H26: 34959 | I26: 652 | J26: Islam | K26: A | L26: Kawin | M26: 6 | N26: 652 | O26: 1468 | P26: Jl. Sejahtera. Rt.01. Kel. Watervang. Kec. Lubuklinggau Timur 1 | Q26: Inactive | R26: 45769 | S26: Now | U26: 46265 | X26: 20250415 | Y26: PT Kita Mitra Indonesia | Z26: 6 | AA26: 649 | AD26: Full-Time | AE26: Kemitraan | AG26: 46167 | AH26: 46265 | AJ26: 11108 | AO26: 167301570995000 | AP26: Inactive | AQ26: Active | AR26: BPU | AS26: JKM;JKK | AT26: TK/0 | AU26: Bank | AV26: BCA | AW26: WIDANA | AX26: 6245038783
A27: 187163 | B27: Siti Maryam | C27: 85211110630 | D27: sitimaryam140586@gmail.com | E27: SPG/SPB Toko | F27: Female | G27: 3207035405860001 | H27: 31546 | I27: 704 | J27: Islam | K27: O | L27: Kawin | M27: 12 | N27: 698 | O27: 1542 | P27: Bumi Pesanggrahan Indah Blok C6 No 6 Rt/Rw. 05/10 Kel. Cilebut Barat. Kec. Sukaraja | Q27: Inactive | R27: 45796 | S27: Now | U27: 46265 | X27: 20250511 | Y27: PT Kita Mitra Indonesia | Z27: 12 | AA27: 716 | AD27: Full-Time | AE27: Kemitraan | AG27: 46167 | AH27: 46265 | AJ27: 11078 | AN27: 1648683257 | AO27: 589736826442000 | AP27: Inactive | AQ27: Active | AR27: BPU | AS27: JKM;JKK | AT27: TK/0 | AU27: Bank | AV27: BCA | AW27: SITI MARYAM | AX27: 4210353190 | AY27: R Abdul Fattah | AZ27: 8119690778 | BA27: Bumi pesanggrahan indah blok c6 no.6 cilebut barat sukaraja bogor | BB27: Suami
A28: 187164 | B28: Herdy Yansyah | C28: 82269859451 | D28: herdyy275@gmail.com | E28: SPG/SPB Toko | F28: Male | G28: 1606051005040004 | H28: 37751 | I28: 641 | J28: Islam | K28: A | L28: Belum Kawin | M28: 6 | N28: 638 | O28: 1281 | P28: Dusun 3 Talang Jawa, Desa. Ujan Mas Baru. Kel. Ujan Mas Baru. Kec. Ujan Mas | Q28: Inactive | R28: 45784 | S28: Now | U28: 46265 | W28: selesai project | X28: 20250506 | Y28: PT Kita Mitra Indonesia | Z28: 6 | AA28: 649 | AD28: Full-Time | AE28: Kemitraan | AG28: 46167 | AH28: 46265 | AJ28: 11110 | AP28: Inactive | AQ28: Active | AR28: BPU | AS28: JKM;JKK | AT28: TK/0 | AU28: Bank | AV28: BCA | AW28: HERDY YANSYAH | AX28: 8120433165 | AZ28: 82269859451
A29: 187165 | B29: Winda Mardiana | C29: 89615384948 | D29: windamardiana816@gmail.com | E29: SPG/SPB Toko | F29: Female | G29: 1871086101020001 | H29: 37277 | I29: 676 | J29: Islam | K29: A | L29: Belum Kawin | M29: 10 | N29: 690 | O29: 1949 | P29: Perum Masyeba Permai Thp 1 Blok F No. 4. Rt/Rw. 001/000 Kel. Patam Lestari. Kec. Sekupang | Q29: Inactive | R29: 45796 | S29: Now | U29: 46265 | X29: 20250514 | Y29: PT Kita Mitra Indonesia | Z29: 10 | AA29: 690 | AD29: Full-Time | AE29: Kemitraan | AG29: 46167 | AH29: 46265 | AJ29: 12311 | AO29: 960090611324000 | AP29: Inactive | AQ29: Active | AR29: BPU | AS29: JKM;JKK | AT29: TK/0 | AU29: Bank | AV29: BCA | AW29: WINDA MARDIANA | AX29: 4300673746 | AY29: Hasan | AZ29: 85384341755 | BA29: Jln. Banten Teluk Betung Barat Bandar Lampung | BB29: Ayah
A30: 187166 | B30: Darussalam | C30: 89501607968 | D30: salamdarulmito26@gmail.com | E30: SPG/SPB Toko | F30: Male | G30: 7322112001940002 | H30: 34354 | I30: 941 | J30: Islam | K30: O | L30: Belum Kawin | M30: 11 | N30: 694 | O30: 2002 | P30: Jl. Poros Tarobok Baebunta. Rt/Rw. 01/01 Kel. Tarobok Kec. Tamalenrea | Q30: Inactive | R30: 45803 | S30: Now | U30: 46265 | W30: selesai project | X30: 20250515 | Y30: PT Kita Mitra Indonesia | Z30: 27 | AA30: 957 | AD30: Full-Time | AE30: Kemitraan | AG30: 46167 | AH30: 46265 | AJ30: 11098 | AM30: 1555690847 | AN30: 24109628875 | AO30: 758816284803000 | AP30: Inactive | AQ30: Active | AR30: BPU | AS30: JKM;JKK | AT30: TK/0 | AU30: Bank | AV30: BCA | AW30: DARUSSALAM | AX30: 7990187805
A31: 187167 | B31: Elga Pratangkas | C31: 85895246860 | D31: elpratangkas@gmail.com | E31: SPG/SPB Toko | F31: Male | G31: 3510076712060002 | H31: 39078 | I31: 774 | J31: Islam | K31: O | L31: Belum Kawin | M31: 15 | N31: 774 | O31: 3493 | P31: Dusun Sidomukti, Desa Yosomulyo Kec. Gambiran | Q31: Inactive | R31: 45810 | S31: Now | U31: 46265 | W31: selesai project | X31: 20250606 | Y31: PT Kita Mitra Indonesia | Z31: 15 | AA31: 801 | AD31: Full-Time | AE31: Kemitraan | AG31: 46198 | AH31: 46265 | AJ31: 11160 | AP31: Inactive | AQ31: Active | AR31: BPU | AS31: JKM;JKK | AT31: TK/0 | AU31: Bank | AV31: BCA | AW31: ELGA PRATANGKAS | AX31: 8980810837 | AY31: Elga Pratangkas | AZ31: 85895246860 | BA31: Desa Yosomulyo, Kec Gambiran, Banyuwangi Jawa Timur | BB31: Kerabat Dekat Lainnya
A32: 187168 | B32: Ahmad Gumilar | C32: 895377409105 | D32: gumilarahmad54@gmail.com | E32: SPG/SPB Toko | F32: Male | G32: 3205172707940004 | H32: 34877 | I32: 702 | J32: Islam | K32: AB | L32: Belum Kawin | M32: 13 | N32: 757 | O32: 3200 | P32: Jln Raya Ngaliyan Semarang. Kel. Purwoyoso Kec. Ngaliyan | Q32: Inactive | R32: 45812 | S32: Now | U32: 46265 | V32: Finished - End of Contract | W32: selesai project | X32: 20250610 | Y32: PT Kita Mitra Indonesia | Z32: 13 | AA32: 757 | AD32: Full-Time | AE32: Kemitraan | AG32: 46198 | AH32: 46265 | AJ32: 11129 | AO32: 934954777443000 | AP32: Inactive | AQ32: Active | AR32: BPU | AS32: JKM;JKK | AT32: TK/0 | AU32: Bank | AV32: BCA | AW32: AHMAD GUMILAR | AX32: 8715805096 | AY32: Fitriyani | AZ32: 895377409105 | BA32: Samarang , Garut | BB32: Saudara Kandung
A33: 187173 | B33: Agustina Galuh Prihaningtyas | C33: 87814045446 | D33: galuh8893@gmail.com | E33: SPG/SPB Toko | F33: Female | G33: 3471075010860001 | H33: 31695 | I33: 764 | J33: Katolik | K33: O | L33: Kawin | M33: 14 | N33: 764 | O33: 3284 | P33: Jl Jagalan No 65. Rt/Rw. 01/02 Kel. Purwokinanti, Kec. Pakualaman | Q33: Inactive | R33: 45819 | S33: Now | U33: 46265 | V33: Finished - End of Contract | W33: selesai project | X33: 20250614 | Y33: PT Kita Mitra Indonesia | Z33: 13 | AA33: 757 | AD33: Full-Time | AE33: Kemitraan | AG33: 46198 | AH33: 46265 | AJ33: 11141 | AN33: 2047564866 | AP33: Inactive | AQ33: Active | AR33: BPU | AS33: JKM;JKK | AT33: TK/0 | AU33: Bank | AV33: BCA | AW33: AGUSTINA GALUH PRIHANING | AX33: 1690194631
A34: 187177 | B34: Devi Isvaradilla Agrully | C34: 85656950939 | D34: deviisvaradilla16@gmail.com | E34: SPG/SPB Toko | F34: Female | G34: 6471035608010001 | H34: 37119 | I34: 900 | J34: Islam | K34: O | L34: Belum Kawin | M34: 23 | N34: 900 | O34: 5152 | P34: Jl. Minangkabau No. 101, Rt. 004, Rw. 000, Kel. Batu Ampar, Kec. Balikpapan Utara | Q34: Inactive | R34: 45824 | S34: Now | U34: 46265 | W34: selesai project | X34: 20200610 | Y34: PT Kita Mitra Indonesia | Z34: 23 | AA34: 900 | AD34: Full-Time | AE34: Kemitraan | AG34: 46198 | AH34: 46265 | AJ34: 11122 | AM34: 23048929394 | AN34: 2092289534 | AO34: 931148159721000 | AP34: Inactive | AQ34: Active | AR34: BPU | AS34: JKM;JKK | AT34: TK/0 | AU34: Bank | AV34: BCA | AW34: DEVI ISVARADILLA AGRULLY | AX34: 7810287131 | AY34: Rusmini Sri rejeki | AZ34: 82151938133 | BA34: jl aw syahrani rt 31 gg argosari | BB34: Ibu
A35: 187178 | B35: Reva Azzahra | C35: 88227753485 | D35: revaazzahraaa11@gmail.com | E35: SPG/SPB Toko | F35: Female | G35: 3311105403060002 | H35: 38790 | I35: 735 | J35: Islam | L35: Belum Kawin | M35: 13 | N35: 735 | O35: 2858 | P35: Dk Kudu Rt001 Rw 001,Kudu,Baki | Q35: Inactive | R35: 45826 | S35: Now | U35: 46265 | X35: 20250623 | Y35: PT Kita Mitra Indonesia | Z35: 13 | AA35: 757 | AD35: Full-Time | AE35: Kemitraan | AG35: 46198 | AH35: 46265 | AJ35: 11148 | AN35: 2346783592 | AO35: 197497290532000 | AP35: Inactive | AQ35: Active | AR35: BPU | AS35: JKM;JKK | AT35: TK/0 | AU35: Bank | AV35: BCA | AW35: REVA AZZAHRA | AX35: 7851256753
A36: 187180 | B36: Khoirunnisa Yuliana | C36: 83150001212 | D36: khoirunnisayuliana39@gmail.com | E36: SPG/SPB Toko | F36: Female | G36: 6271034807990001 | H36: 36349 | I36: 879 | J36: Islam | K36: O | L36: Kawin | M36: 21 | N36: 879 | O36: 4905 | P36: Jl. Danau Rangas Vii No. 32. Rt/Rw 02/07. Kel. Bukit Tunggal . Kec Jekan Raya | Q36: Inactive | R36: 45835 | S36: Now | U36: 46265 | X36: 20250632 | Y36: PT Kita Mitra Indonesia | Z36: 22 | AA36: 891 | AD36: Full-Time | AE36: Kemitraan | AG36: 46198 | AH36: 46265 | AJ36: 11071 | AO36: 902699883711000 | AP36: Inactive | AQ36: Active | AR36: BPU | AS36: JKM;JKK | AT36: TK/0 | AU36: Bank | AV36: BCA | AW36: KHOIRUNNISA YULIANA | AX36: 6575189966 | AY36: Ridwan | AZ36: 81251544938 | BA36: Jl. Danau Rangas VII No. 32 | BB36: Suami
A37: 187183 | B37: Siti Arimah | C37: 85691568762 | D37: arimaaaa31@gmail.com | E37: SPG/SPB Toko | F37: Female | G37: 3601244107050066 | H37: 37652 | I37: 803 | J37: Islam | L37: Belum Kawin | M37: 16 | N37: 803 | O37: 3974 | P37: Kp. Kelapa. Rt/Rw 12/02, Rahayu Patia, Kab Pandeglang Banten | Q37: Inactive | R37: 45838 | S37: Now | U37: 46265 | X37: 20250630 | Y37: PT Kita Mitra Indonesia | Z37: 16 | AA37: 807 | AD37: Full-Time | AE37: Kemitraan | AG37: 46198 | AH37: 46265 | AJ37: 11080 | AO37: 608924783419000 | AP37: Inactive | AQ37: Active | AR37: BPU | AS37: JKM;JKK | AT37: TK/0 | AU37: Bank | AV37: BCA | AW37: SITI ARIMAH | AX37: 4900427021
A38: 187184 | B38: Siti Maslikah | C38: 81215716464 | D38: alikaayu41@gmail.com | E38: SPG/SPB Toko | F38: Female | G38: 3318026106930002 | H38: 34141 | I38: 742 | J38: Islam | K38: O | L38: Kawin | M38: 13 | N38: 757 | O38: 3195 | P38: Perum Graha Pratama Blok A4. Rt/Rw. 06/05. Kel. Rowosari. Kec. Tembalang | Q38: Inactive | R38: 45839 | S38: Now | U38: 46265 | X38: 20250633 | Y38: PT Kita Mitra Indonesia | Z38: 13 | AA38: 757 | AD38: Full-Time | AE38: Kemitraan | AG38: 46198 | AH38: 46265 | AJ38: 11131 | AN38: 586177705 | AO38: 535270334518000 | AP38: Inactive | AQ38: Active | AR38: BPU | AS38: JKM;JKK | AT38: TK/0 | AU38: Bank | AV38: BCA | AW38: SITI MASLIKAH | AX38: 980363422 | AY38: raafi harlanwi sanday purnama | AZ38: 85602992719 | BA38: perumahan Graha pratama asri blok A.4 RT.06 RW.05 rowosari tembalang | BB38: Suami
A39: 187185 | B39: Charles Setiawan | C39: 85651034052 | D39: cs5657394@gmail.com | E39: SPG/SPB Toko | F39: Male | G39: 6104170504950007 | H39: 34794 | I39: 857 | J39: Protestan | K39: O | L39: Belum Kawin | M39: 20 | N39: 864 | O39: 4765 | P39: Toko Putra Elektronik, Jl. Tanjung Putra no 5-7( Depan Bank KalBar) | Q39: Inactive | R39: 45845 | S39: Now | U39: 46265 | W39: selesai project | X39: 20250704 | Y39: PT Kita Mitra Indonesia | Z39: 20 | AA39: 864 | AD39: Full-Time | AE39: Kemitraan | AG39: 46167 | AH39: 46265 | AJ39: 11176 | AM39: 24207959552 | AN39: 1728855112 | AO39: 610417050495000 | AP39: Inactive | AQ39: Active | AR39: BPU | AS39: JKM;JKK | AT39: TK/0 | AU39: Bank | AV39: BCA | AW39: CHARLES SETIAWAN | AX39: 1711654599
A40: 187187 | B40: Moh Nurdiansyah | C40: 85693556180 | D40: iyann201203@gmail.com | E40: GTM | F40: Male | G40: 3601192012030004 | H40: 37975 | I40: 803 | J40: Islam | K40: Tidak Tahu | L40: Belum Kawin | M40: 16 | N40: 807 | O40: 4075 | P40: Jl. Kiasnawi No.31, RT.003/RW.003, Sukarasa, Kec. Tangerang, Kota Tangerang, Banten 15111 | Q40: Inactive | R40: 45236 | S40: Now | U40: 46265 | X40: 20231101 | Y40: PT Kita Mitra Indonesia | Z40: 11 | AA40: 697 | AB40: 1973 | AD40: Full-Time | AE40: Kemitraan | AG40: 46146 | AH40: 46265 | AJ40: 11187 | AL40: 1792;1793;1794;1709;1947 | AM40: 25008123942 | AN40: 796521407 | AO40: 537949547419000 | AP40: Inactive | AQ40: Active | AR40: BPU | AS40: JKM;JKK | AT40: TK/0 | AU40: Bank | AV40: BCA | AW40: MOH NURDIANSAH | AX40: 7125610072 | AY40: Riyan | AZ40: 83895259493 | BA40: jl pepaya raya no 79 Cibodas Tangerang | BB40: Kerabat Dekat Lainnya
A41: 187193 | B41: Afrizal Adinata | C41: 81271892394 | D41: afrizal.adinata@gmail.com | E41: GTM | F41: Male | G41: 1671112304820001 | H41: 30064 | I41: 649 | J41: Islam | L41: Kawin | M41: 6 | N41: 649 | O41: 1455 | P41: Jl. Radial Lr. Dahlia No.12/5 Rt/Rw.020/005, Kel. Dua Puluh Empat Ilir, Kec. Bukitkecil, Kota. Palembang, Sumatera Selatan. | Q41: Inactive | R41: 45600 | S41: Now | U41: 46265 | V41: Finished - End of Contract | W41: selesai project | X41: 20241101 | Y41: PT Kita Mitra Indonesia | Z41: 27 | AA41: 957 | AB41: 5856 | AD41: Full-Time | AE41: Kemitraan | AG41: 46167 | AH41: 46265 | AJ41: 11183 | AL41: 1792;1793;1794;1709;1947 | AM41: 25003790893 | AO41: 167293265307000 | AP41: Inactive | AQ41: Active | AR41: BPU | AS41: JKM;JKK | AT41: K/3 | AU41: Bank | AV41: BCA | AW41: AFRIZAL ADINATA | AX41: 214271334
A42: 189602 | B42: Febry Valentino | C42: 895329958077 | D42: febrivalentino24@gmail.com | E42: SPG/SPB Toko | F42: Male | G42: 6474011302040001 | H42: 38030 | I42: 902 | J42: Protestan | K42: O | L42: Belum Kawin | M42: 23 | N42: 902 | O42: 5167 | P42: Jl. Berlian no. I04 | Q42: Inactive | R42: 45915 | S42: Now | U42: 46265 | W42: selesai project | Y42: PT Kita Mitra Indonesia | Z42: 23 | AA42: 902 | AB42: 5166 | AD42: Full-Time | AE42: Kemitraan | AG42: 46198 | AH42: 46265 | AJ42: 11112 | AP42: Inactive | AQ42: Inactive | AR42: Waiting for Registration | AT42: TK/0 | AU42: Bank | AV42: BRI | AW42: Febry Valentino | AX42: 33301018582534 | AY42: andi | AZ42: 89689482457 | BA42: jl berlian no i04 | BB42: Saudara Kandung
A43: 190224 | B43: Elisabeth Novi Yanti Ayu N | C43: 87865850309 | D43: elisabethayu1997@gmail.com | E43: SPG/SPB Toko | F43: Female | G43: 5204215711970002 | H43: 35751 | I43: 823 | J43: Katolik | K43: O | L43: Belum Kawin | M43: 18 | N43: 823 | O43: 4224 | P43: Dusun Meno | Q43: Inactive | R43: 45920 | S43: Now | U43: 46265 | W43: selesai project | Y43: PT Kita Mitra Indonesia | Z43: 15 | AA43: 801 | AD43: Full-Time | AE43: Kemitraan | AG43: 46198 | AH43: 46265 | AJ43: 11418 | AO43: 430697235914000 | AP43: Inactive | AQ43: Inactive | AT43: TK/0 | AU43: Bank | AV43: BCA | AW43: ELISABETH NOVI YANTI AYU N | AX43: 562190331 | AY43: Erika | AZ43: 82359598134 | BA43: Jakarta | BB43: Saudara Kandung
A44: 194232 | B44: Nurista Afninda Waqiatul Q | C44: 89628450401 | D44: afnindanurista@gmail.com | E44: SPG/SPB Toko | F44: Female | G44: 3509195902030004 | H44: 37671 | I44: 773 | J44: Islam | K44: AB | L44: Belum Kawin | M44: 10 | N44: 690 | O44: 1955 | P44: Jl Bengkong Pertiwi F5 No.1 Kel. Tanjung Buntung, Kec. Bengkong, Batam | Q44: Inactive | R44: 45934 | S44: Now | U44: 46265 | Y44: PT Kita Mitra Indonesia | Z44: 10 | AA44: 690 | AD44: Full-Time | AE44: Kemitraan | AG44: 46228 | AH44: 46265 | AJ44: 11676 | AO44: 991185851626000 | AP44: Inactive | AQ44: Inactive | AT44: TK/0 | AU44: Bank | AV44: MANDIRI | AW44: NURISTA AFNINDA WAQIATUL Q | AX44: 1430021384092 | AY44: NURISTA LAILI RAFIKA ADINDA | AZ44: 8999888696 | BA44: jember, jawa timur | BB44: Saudara Kandung
A45: 195008 | B45: Priya Thadhea | C45: 895381170790 | D45: thadhea10@gmail.com | E45: SPG/SPB Toko | F45: Female | G45: 3301214106000005 | H45: 36678 | I45: 725 | J45: Islam | K45: B | L45: Kawin | M45: 13 | N45: 757 | O45: 3191 | P45: jl pedurungan lor rt05/05 | Q45: Inactive | R45: 45938 | S45: Now | U45: 46265 | Y45: PT Kita Mitra Indonesia | Z45: 13 | AA45: 746 | AD45: Full-Time | AE45: Kemitraan | AG45: 46228 | AH45: 46265 | AJ45: 11130 | AP45: Inactive | AQ45: Inactive | AT45: TK/0 | AU45: Bank | AV45: BCA | AW45: priya thadhea | AX45: 3440526046
A46: 195315 | B46: Umayah mirani | C46: 85726532701 | D46: umayahmirani85@gmail.com | E46: SPG/SPB Toko | F46: Female | G46: 3302196003970005 | H46: 35754 | I46: 726 | J46: Islam | K46: B | L46: Kawin | M46: 13 | N46: 726 | O46: 2676 | P46: Sokaraja Kulon | Q46: Inactive | R46: 45940 | S46: Now | U46: 46265 | Y46: PT Kita Mitra Indonesia | Z46: 13 | AA46: 726 | AD46: Full-Time | AE46: Kemitraan | AG46: 46228 | AH46: 46265 | AJ46: 11143 | AP46: Inactive | AQ46: Inactive | AT46: TK/0 | AU46: Bank | AV46: BCA | AW46: Umayah mirani | AX46: 1801135019
A47: 196051 | B47: Dila Puspita | C47: 85814632383 | D47: puspitasaridila193@gmail.com | E47: National Admin | F47: Female | G47: 3175076001010003 | H47: 36911 | I47: 694 | J47: Islam | L47: Belum Kawin | M47: 11 | N47: 694 | O47: 2003 | P47: Jl. Betung V no.171 | Q47: Inactive | R47: 45925 | S47: Now | U47: 46265 | W47: selesai project | Y47: PT Kita Mitra Indonesia | Z47: 11 | AA47: 693 | AB47: 1992 | AD47: Full-Time | AE47: PKWT | AF47: LODPSI2383 | AG47: 46198 | AH47: 46265 | AJ47: 11451 | AL47: 1792;1793;1794;1709;1947 | AM47: 25060601504 | AN47: 2307130334 | AP47: Inactive | AQ47: Inactive | AU47: Bank | AV47: BCA | AW47: Dila Puspita Sari | AX47: 2740698730
A48: 198542 | B48: Anisa Nurajijah | C48: 89524367514 | D48: uchanel1983@gmail.com | E48: SPG/SPB Toko | F48: Female | G48: 3213306811040001 | H48: 38319 | I48: 710 | J48: Islam | K48: B | L48: Belum Kawin | M48: 20 | N48: 864 | P48: ketapang | Q48: Inactive | R48: 45957 | S48: Now | U48: 46265 | W48: selesai project | Z48: 20 | AA48: 857 | AB48: 4656 | AD48: Full-Time | AE48: Kemitraan | AG48: 46228 | AH48: 46265 | AJ48: 12512 | AO48: 397576190016000 | AP48: Inactive | AQ48: Inactive | AT48: TK/0 | AU48: Bank | AV48: BNI | AW48: ANNISA NURAJIJAH | AX48: 1821399402
A49: 204244 | B49: Wahyu Hidayat | C49: 83111617926 | D49: wahyuhidayat62320@gmail.com | E49: SPG/SPB Toko | F49: Male | G49: 3204320604990004 | H49: 36256 | I49: 718 | J49: Islam | K49: A | L49: Belum Kawin | M49: 12 | N49: 701 | O49: 2146 | P49: KP Pasir Pogor No 193 RT004/003 Desa Malakasari | Q49: Inactive | R49: 45996 | S49: Now | U49: 46265 | Y49: PT. Kita Mitra Indonesia | Z49: 12 | AA49: 718 | AB49: 2567 | AD49: Full-Time | AE49: Kemitraan | AG49: 46198 | AH49: 46265 | AJ49: 12789 | AM49: 25175864583 | AN49: 25175864583 | AO49: 941879272145000 | AP49: Inactive | AQ49: Inactive | AT49: TK/0 | AU49: Bank | AV49: BCA | AW49: Wahyu Hidayat | AX49: 8101192474 | AY49: Wini Kuswahyuni | AZ49: 89656168279 | BA49: kp pasir pogor no 193 RT004/003 Desa Malakasari Baleendah | BB49: Saudara Kandung
A50: 204422 | B50: Fuji Restu Nurani | C50: 89507427397 | D50: fujirestunurani14@gmail.com | E50: SPG/SPB Toko | F50: Female | G50: 3273025411960001 | H50: 35383 | I50: 718 | J50: Islam | K50: AB | L50: Belum Kawin | M50: 12 | N50: 718 | O50: 2560 | P50: Jl. Dago Barat no. 06 159/B RT.08 RW.05 Kel. Dago Kec. Coblong | Q50: Inactive | R50: 45996 | S50: Now | U50: 46265 | W50: selesai project | Y50: PT. Kita Mitra Indonesia | Z50: 12 | AA50: 718 | AB50: 2574 | AD50: Full-Time | AE50: Kemitraan | AG50: 46198 | AH50: 46265 | AJ50: 11058 | AN50: 506670592 | AO50: 938428240423000 | AP50: Inactive | AQ50: Inactive | AT50: TK/0 | AU50: Bank | AV50: MANDIRI | AW50: Fuji Restu Nurani | AX50: 1310020987097 | AY50: Iin Ina Marsina | AZ50: 85524793334 | BA50: Jl. Dago Barat No.06 159/B RT. 08 RW. 05 Kel. Dago Kec. Coblong Kota Bandung, Jawa Barat 40135 | BB50: Ibu
A51: 205574 | B51: Syfa Ayu Dwi Cahyani | C51: 87731284107 | D51: syfadwiayu06@gmail.com | E51: SPG/SPB Toko | F51: Female | G51: 3510234610060003 | H51: 38996 | I51: 774 | J51: Islam | K51: B | L51: Belum Kawin | M51: 15 | N51: 774 | O51: 3509 | P51: Dsn Krajan 1 RT 08 RW 03 Desa Tegalsari | Q51: Inactive | R51: 46000 | S51: Now | U51: 46265 | Y51: PT. Kita Mitra Indonesia | Z51: 15 | AA51: 774 | AB51: 3499 | AD51: Full-Time | AE51: Kemitraan | AG51: 46198 | AH51: 46265 | AJ51: 12827 | AN51: 3340836573 | AO51: 3510234610060003 | AP51: Inactive | AQ51: Inactive | AT51: TK/0 | AU51: Bank | AV51: BCA | AW51: SYFA DWI AYU CAHYANI | AX51: 2631238621 | AY51: Ardimas Ahsan Yusuf | AZ51: 85933151574 | BA51: Dsn Krajan 1 RT 08 RW 03 Desa Tegalsari Kecamatan Tegalsari Kab. Banyuwangi | BB51: Saudara Kandung
A52: 206205 | B52: Mawar | C52: 85349514526 | D52: yanihama2415@gmail.com | E52: SPG/SPB Toko | F52: Female | G52: 6472046404060002 | H52: 38831 | I52: 901 | J52: Islam | K52: Tidak Tahu | L52: Belum Kawin | M52: 23 | N52: 901 | O52: 5159 | P52: Jl. Damai GG 4 | Q52: Inactive | R52: 46002 | S52: Now | U52: 46265 | Y52: PT. Kita Mitra Indonesia | Z52: 23 | AA52: 901 | AB52: 5158 | AD52: Full-Time | AE52: Kemitraan | AG52: 46198 | AH52: 46265 | AJ52: 11119 | AP52: Inactive | AQ52: Inactive | AU52: Bank | AV52: BCA | AW52: mawar | AX52: 6585260766 | AY52: yani | AZ52: 85355958903 | BA52: jl damai GG syariah | BB52: Ibu
A53: 208420 | B53: Devi Eriyanti | C53: 88804268618 | D53: Vira08359@gmail.com | E53: SPG/SPB Toko | F53: Female | G53: 6407096709950001 | H53: 34969 | I53: 902 | J53: Islam | K53: A | L53: Belum Kawin | M53: 22 | N53: 892 | O53: 5062 | P53: Kompleks hunian idaman asri banjar Blok A No 3 Rt 49 RW 1 sungai besar Banjar baru selatan | Q53: Inactive | R53: 46008 | S53: Now | U53: 46265 | W53: selesai project | Y53: PT. Kita Mitra Indonesia | Z53: 22 | AA53: 892 | AB53: 5062 | AD53: Full-Time | AE53: Kemitraan | AG53: 46198 | AH53: 46265 | AJ53: 11061 | AP53: Inactive | AQ53: Inactive | AU53: Bank | AV53: BCA | AW53: Devi Eriyanti | AX53: 1912978251 | AY53: Anggarini Norma Agustin | AZ53: 85249465257 | BA53: Komplek hunian idaman asri Blok A no 3 Rt 49 Rw 1 sungai besar | BB53: Saudara Kandung
A54: 208471 | B54: Hagai Hendrik Yonathan | C54: 81235652785 | D54: joetozeta@gmail.com | E54: SPG/SPB Toko | F54: Male | G54: 3508072709850002 | H54: 31317 | I54: 772 | J54: Protestan | K54: O | L54: Kawin | M54: 15 | N54: 773 | O54: 3462 | P54: Dusun Babatan RT 003 RW 018 Sidomekar Semboro JEMBER | Q54: Inactive | R54: 46008 | S54: Now | U54: 46265 | W54: selesai project | Y54: PT. Kita Mitra Indonesia | Z54: 15 | AA54: 773 | AB54: 3468 | AD54: Full-Time | AE54: Kemitraan | AG54: 46198 | AH54: 46265 | AJ54: 12887 | AO54: 3508072709850002 | AP54: Inactive | AQ54: Inactive | AU54: Bank | AV54: BCA | AW54: Hagai Hendrik Yonathan | AX54: 1250894160 | AY54: Hana | AZ54: 81332159592 | BA54: Dusun Babatan RT 03 RW 18 Sidomekar Semboro Jember | BB54: Istri
A55: 211179 | B55: Ayu Novitaningsih | C55: 82141638390 | D55: ayu_mamay@ymail.com | E55: SPG/SPB Toko | F55: Female | G55: 3502144911950001 | H55: 35012 | I55: 766 | J55: Islam | K55: AB | L55: Cerai hidup | M55: 15 | N55: 766 | O55: 3313 | P55: DUKUH BRINGIN RT02/RW01 DESA KARANGWALUH SAMPUNG PONOROGO | Q55: Inactive | R55: 46015 | S55: Now | U55: 46265 | W55: selesai project | Y55: PT. Kita Mitra Indonesia | Z55: 15 | AA55: 766 | AB55: 3316 | AD55: Full-Time | AE55: Kemitraan | AG55: 46198 | AH55: 46265 | AJ55: 11157 | AO55: 816293948647000 | AP55: Inactive | AQ55: Inactive | AU55: Bank | AV55: BCA | AW55: AYU NOVITANINGSIH | AX55: 2891046822 | AY55: SURYATI | AZ55: 82131693684 | BA55: DUKUH KARANGWALUH RT02/RW01 DESA KARANGWALUH SAMPUNG PONOROGO | BB55: Ibu
A56: 211189 | B56: Martin Agustian | C56: 81995357575 | D56: crewnyek@gmail.com | E56: Sales B2B - MITO | F56: Male | G56: 1971010403920001 | H56: 33667 | I56: 678 | J56: Protestan | K56: O | L56: Kawin | M56: 9 | N56: 684 | O56: 1886 | P56: Jln Satam Dalam RT.09/03 Kel. Semabung Baru | Q56: Inactive | R56: 46027 | S56: Now | U56: 46265 | Y56: PT. Kita Mitra Indonesia | Z56: 9 | AA56: 684 | AD56: Full-Time | AE56: Kemitraan | AG56: 46228 | AH56: 46265 | AJ56: 13021 | AM56: 23097824561 | AN56: 2140533821 | AO56: 763755394304000 | AP56: Inactive | AQ56: Inactive | AT56: K/2 | AU56: Bank | AV56: BCA | AW56: Martin Agustian | AX56: 8535125917 | AY56: Julfiana | AZ56: 82180052775 | BA56: Jln Satam Dalam RT.09/03 Kel. Semabung Baru Kec. Girimaya Kota Pangkalpinang | BB56: Istri
A57: 212658 | B57: Sitti Aisyah Syafitri | C57: 85398646723 | D57: vhyrawati055@gmail.com | E57: SPG/SPB Toko | F57: Female | G57: 7371064512020001 | H57: 37595 | I57: 957 | J57: Islam | K57: Tidak Tahu | L57: Kawin | M57: 27 | N57: 957 | O57: 5858 | P57: jl kandea 3 kip 7 no 28B | Q57: Inactive | R57: 46024 | S57: Now | U57: 46265 | Y57: PT. Kita Mitra Indonesia | Z57: 27 | AA57: 957 | AB57: 5861 | AD57: Full-Time | AE57: Kemitraan | AG57: 46228 | AH57: 46265 | AJ57: 11092 | AP57: Inactive | AQ57: Inactive | AU57: Bank | AV57: BRI | AW57: Sitti aisyah syafitri H | AX57: 341101038748539
A58: 212901 | B58: Wartini | C58: 81915461459 | D58: tinialidrisiyyah@gmail.com | E58: SPG/SPB Toko | F58: Female | G58: 3209195707020009 | H58: 37304 | I58: 706 | J58: Islam | K58: Tidak Tahu | L58: Belum Kawin | M58: 12 | N58: 706 | O58: 2315 | P58: desa megu ciliki, blok galgadung, kecamatan weru, kabupaten Cirebon | Q58: Inactive | R58: 46027 | S58: Now | U58: 46265 | Y58: PT. Kita Mitra Indonesia | Z58: 12 | AA58: 706 | AB58: 2316 | AD58: Full-Time | AE58: Kemitraan | AG58: 46228 | AH58: 46265 | AJ58: 13013 | AN58: 453454896 | AP58: Inactive | AQ58: Inactive | AU58: Bank | AV58: BCA | AW58: wartini | AX58: 7746551729 | AY58: siti Mariyam | AZ58: 882002148473 | BA58: desa megu ciliki, blok galgadung, kecamatan weru, kabupaten Cirebon | BB58: Saudara Kandung
A59: 213212 | B59: Moy Yustiwa | C59: 81335885943 | D59: moyyustiwa24@gmail.com | E59: SPG/SPB Toko | F59: Female | G59: 3506146408020002 | H59: 37492 | I59: 770 | J59: Islam | K59: Tidak Tahu | L59: Belum Kawin | M59: 15 | N59: 801 | O59: 3920 | P59: Jl. Kedurus Dukuh Gg. III No.62, Kedurus, Kec. Karangpilang, Surabaya, Jawa Timur 60223 | Q59: Inactive | R59: 46022 | S59: Now | U59: 46265 | Y59: PT. Kita Mitra Indonesia | Z59: 15 | AA59: 801 | AB59: 3940 | AD59: Full-Time | AE59: Kemitraan | AG59: 46198 | AH59: 46265 | AJ59: 13207 | AN59: 2284919741 | AO59: 3506146408020002 | AP59: Inactive | AQ59: Inactive | AT59: TK/2 | AU59: Bank | AV59: BCA | AW59: MOY YUSTIWA RAHAYU PUTRI KARTIKA | AX59: 6123069515 | AY59: Klodya Emdhe | AZ59: 8888049889 | BA59: Jl. Kedurus Dukuh Gg. III No.62, Kedurus, Kec. Karangpilang, Surabaya, Jawa Timur 60223
A60: 213215 | B60: Mardatillah | C60: 87845284320 | D60: mamatmarda12@gmail.com | E60: SPG/SPB Toko | F60: Female | G60: 3515025009040002 | H60: 38240 | I60: 779 | J60: Islam | K60: A | L60: Kawin | M60: 15 | N60: 779 | O60: 3608 | P60: karangploso rt5 rw4 gelang tulangan | Q60: Inactive | R60: 46022 | S60: Now | U60: 46265 | Y60: PT. Kita Mitra Indonesia | Z60: 15 | AA60: 779 | AB60: 3607 | AD60: Full-Time | AE60: Kemitraan | AG60: 46198 | AH60: 46265 | AJ60: 13025 | AN60: 1115591973 | AP60: Inactive | AQ60: Inactive | AU60: Bank | AV60: BCA | AW60: Mardatillah | AX60: 883073760 | AY60: Abdullah | AZ60: 85601855346 | BA60: bungurasih timur waru | BB60: Ayah
A61: 214229 | B61: Mohammad Hidayat | C61: 85602723475 | D61: mohammadhidayat190@gmail.com | E61: SPG/SPB Toko | F61: Male | G61: 3319043008960005 | H61: 35307 | I61: 743 | J61: Islam | L61: Belum Kawin | M61: 13 | N61: 743 | O61: 2996 | P61: kalirejo | Q61: Inactive | R61: 46034 | S61: Now | U61: 46265 | Z61: 13 | AA61: 743 | AB61: 2994 | AD61: Full-Time | AE61: Kemitraan | AG61: 46228 | AH61: 46265 | AJ61: 13131 | AN61: 591222701 | AO61: 292787132506000 | AP61: Inactive | AQ61: Inactive | AU61: Bank | AV61: MANDIRI | AW61: Mohammad Hidayat | AX61: 1840003423991 | AY61: Nor Rohman | AZ61: 85701265868 | BA61: kalirejo | BB61: Saudara Kandung
A62: 214532 | B62: Neni Rahayu | C62: 87899215955 | D62: rahayuneni0611@gmail.com | E62: SPG/SPB Toko | F62: Female | G62: 5271034611940002 | H62: 34644 | I62: 828 | J62: Islam | K62: A | L62: Kawin | M62: 18 | N62: 828 | O62: 4274 | P62: jl beo, gang Anggrek, karang kemong | Q62: Inactive | R62: 46034 | S62: Now | U62: 46265 | Y62: PT. Kita Mitra Indonesia | Z62: 18 | AA62: 828 | AB62: 4273 | AD62: Full-Time | AE62: Kemitraan | AG62: 46228 | AH62: 46265 | AJ62: 13064 | AN62: 1579243364 | AO62: 5271034611940002 | AP62: Inactive | AQ62: Inactive | AT62: TK/0 | AU62: E-wallet | AV62: DANA | AW62: DANATOPUP NENX RAHXXX | AX62: =+6287899215955 -> 6287899215955 | AY62: Heri setiawan | AZ62: 87765933522 | BA62: jln. Beo Gg. Anggrek Kr. kemong | BB62: Suami
A63: 215205 | B63: Deni Lindiansah | C63: 89670444004 | D63: denilnndsh@gmail.com | E63: SPG/SPB Toko | F63: Male | G63: 3273250212000005 | H63: 36862 | I63: 718 | J63: Islam | K63: AB | L63: Kawin | M63: 12 | N63: 701 | O63: 2127 | P63: Jln Panyandaan Rt 03 Rw 07 | Q63: Inactive | R63: 46036 | S63: Now | U63: 46265 | W63: selesai project | Y63: PT. Kita Mitra Indonesia | Z63: 12 | AA63: 718 | AB63: 2567 | AD63: Full-Time | AE63: Kemitraan | AG63: 46228 | AH63: 46265 | AJ63: 13138 | AM63: 25091774841 | AN63: 1779175427 | AO63: 962696589429000 | AP63: Inactive | AQ63: Inactive | AT63: K/1 | AU63: Bank | AV63: BCA | AW63: Deni Lindiansah | AX63: 2832076288 | AY63: Wina Widacitra | AZ63: 87827555269 | BA63: Jln Panyandaan Rt 03 Rw 07 Cimenyan kab Bandung | BB63: Istri
A64: 215867 | B64: Rista bellawati basuki | C64: 89678564827 | D64: ristabella274@gmail.com | E64: SPG/SPB Toko | F64: Female | G64: 3578106206960001 | H64: 35238 | I64: 801 | J64: Islam | K64: Tidak Tahu | L64: Kawin | M64: 15 | N64: 801 | O64: 3937 | P64: jalan Lakarsantri RT 1 RW 1 | Q64: Inactive | R64: 46043 | S64: Now | U64: 46265 | Y64: PT. Kita Mitra Indonesia | Z64: 15 | AA64: 801 | AB64: 3928 | AD64: Full-Time | AE64: Kemitraan | AG64: 46228 | AH64: 46265 | AJ64: 13172 | AM64: 21062921164 | AN64: 1421222589 | AO64: 954647699619000 | AP64: Inactive | AQ64: Inactive | AT64: K/2 | AU64: Bank | AV64: BCA | AW64: Rista bellawati basuki | AX64: 5190184422 | AY64: angki pranata | AZ64: 85853407472 | BA64: jalan Lakarsantri RT 1 RW 1 | BB64: Suami
A65: 216720 | B65: Bagus Dwi Ardiansyah | C65: 81283148912 | D65: bagusdwiar@gmail.com | E65: SPG/SPB Toko | F65: Male | G65: 3578302108970001 | H65: 35663 | I65: 801 | J65: Islam | K65: O | L65: Belum Kawin | M65: 15 | N65: 801 | O65: 3949 | P65: Pondok Benowo Indah BO 14 Surabaya | Q65: Inactive | R65: 46047 | S65: Now | U65: 46265 | W65: selesai project | Y65: PT. Kita Mitra Indonesia | Z65: 15 | AA65: 801 | AB65: 3932 | AD65: Full-Time | AE65: Kemitraan | AG65: 46228 | AH65: 46265 | AJ65: 13024 | AO65: 3578302108970001 | AP65: Inactive | AQ65: Inactive | AT65: TK/0 | AU65: Bank | AV65: MANDIRI | AW65: BAGUS DWI ARDIANSYAH | AX65: 1410025187097 | AY65: M Amin Edy Saputra | AZ65: 81331165665 | BA65: Pondok Benowo Indah BO 14 Surabaya | BB65: Ayah
A66: 217847 | B66: Muhtar | C66: 8886200919 | D66: muhtar.banez88@gmail.com | E66: SPG/SPB Toko | F66: Male | G66: 3217060506930015 | H66: 34155 | I66: 718 | J66: Islam | K66: A | L66: Kawin | M66: 12 | N66: 722 | O66: 2619 | P66: jl. cipageran no 120 | Q66: Inactive | R66: 46055 | S66: Now | U66: 46265 | Y66: PT. Kita Mitra Indonesia | Z66: 12 | AA66: 718 | AB66: 2568 | AD66: Full-Time | AE66: Kemitraan | AG66: 46167 | AH66: 46265 | AJ66: 13271 | AO66: 718774425421000 | AP66: Inactive | AQ66: Inactive | AU66: Bank | AV66: BCA | AW66: MUHTAR | AX66: 7940301020 | AY66: Diana Ayu Prawitasari | AZ66: 8883673003 | BA66: jl. cipageran no. 120 | BB66: Istri
A67: 218212 | B67: Liya Nataliya | C67: 82385625202 | D67: liyanalita1120@gmail.com | E67: SPG/SPB Toko | F67: Female | G67: 1403096812010002 | H67: 37253 | I67: 602 | J67: Islam | L67: Belum Kawin | M67: 11 | N67: 697 | O67: 1978 | P67: Jln Kelapa Cengkir Timur V Blok EF 2 No.5 | Q67: Inactive | R67: 45561 | S67: Now | U67: 46265 | Y67: PT. Kita Mitra Indonesia | Z67: 11 | AA67: 697 | AB67: 1978 | AD67: Full-Time | AE67: Kemitraan | AG67: 46198 | AH67: 46265 | AJ67: 13288 | AN67: 1397689121 | AO67: 962718144225000 | AP67: Inactive | AQ67: Inactive | AT67: TK/0 | AU67: Bank | AV67: BCA | AW67: Liya NataLiya | AX67: 8520379852 | AY67: Novi | AZ67: 87773897300 | BA67: Kelapa Gading Jakarta Utara | BB67: Kerabat Dekat Lainnya
A68: 218463 | B68: Isma Kurniawati | C68: 88222510571 | D68: arrafaizma@gmail.com | E68: SPG/SPB Toko | F68: Female | G68: 3604055107930006 | H68: 34161 | I68: 701 | J68: Islam | K68: B | L68: Kawin | M68: 12 | N68: 701 | O68: 2137 | P68: kp baros rt 01 rw 02 ds baros kec arjasari | Q68: Inactive | R68: 46055 | S68: Now | U68: 46265 | Y68: PT. Kita Mitra Indonesia | Z68: 12 | AA68: 718 | AB68: 2570 | AD68: Full-Time | AE68: Kemitraan | AG68: 46167 | AH68: 46265 | AJ68: 13284 | AP68: Inactive | AQ68: Inactive | AU68: Bank | AV68: SEABANK | AW68: Isma Kurniawati | AX68: 901129801442 | AY68: o juariah | AZ68: 83117024800 | BA68: kp baros rt 01 rw 02 ds baros kec arjasari kab bandung | BB68: Kerabat Dekat Lainnya
A69: 222092 | B69: Prakas Armando Yuwono | C69: 89669375797 | D69: prakasarmando51@gmail.com | E69: SPG/SPB Toko | F69: Male | G69: 3573011008980005 | H69: 36017 | I69: 796 | J69: Islam | K69: O | L69: Kawin | M69: 15 | N69: 796 | O69: 3900 | P69: Jl. LA. Sucipto Gg. Stasiun No.16 RT.06 RW.10 Kota Malang, 65125 | Q69: Inactive | R69: 46074 | S69: Now | U69: 46265 | Y69: PT. Kita Mitra Indonesia | Z69: 15 | AA69: 796 | AB69: 3900 | AD69: Full-Time | AE69: Kemitraan | AG69: 46167 | AH69: 46265 | AJ69: 13550 | AP69: Inactive | AQ69: Inactive | AU69: Bank | AV69: BCA | AW69: PRAKAS ARMANDO YUWONO | AX69: 3310069298
A70: 222239 | B70: Mustakim | C70: 85773050498 | D70: mustakimkim522@gmail.com | E70: SPG/SPB MT | F70: Male | G70: 3326070811950002 | H70: 35377 | I70: 758 | J70: Islam | K70: O | L70: Belum Kawin | M70: 16 | N70: 810 | O70: 4107 | P70: Jl.Arjuna parakan pondok benda Rt/002 Rw/008 kec.Pamulang kab.Tangerang selatan | Q70: Inactive | R70: 46077 | S70: Now | U70: 46265 | Y70: PT. Kita Mitra Indonesia | Z70: 11 | AA70: 697 | AB70: 1973 | AD70: Full-Time | AE70: Kemitraan | AG70: 46167 | AH70: 46265 | AJ70: 13551 | AP70: Inactive | AQ70: Inactive | AU70: Bank | AV70: BCA | AW70: Mustakim | AX70: 6763031361 | AY70: Purwati | AZ70: 85717255118 | BA70: Jl.Arjuna parakan pondok benda Rt/002 Rw/008 Kec.Pamulang Kab.Tangerang Selatan | BB70: Saudara Kandung
A71: 222521 | B71: Rekha Riakiah | C71: 81385983711 | D71: raikaece4@gmail.com | E71: Promotor Live | F71: Female | G71: 3172037105040004 | H71: 38138 | I71: 697 | J71: Islam | K71: O | L71: Belum Kawin | M71: 11 | N71: 697 | O71: 1975 | P71: Jl. cikijang 1 no 2 RT 001/RW 011 Koja Jakarta Utara | Q71: Inactive | R71: 46079 | S71: Now | U71: 46265 | Y71: PT. Kita Mitra Indonesia | Z71: 11 | AA71: 697 | AB71: 1973 | AD71: Full-Time | AE71: Kemitraan | AG71: 46167 | AH71: 46265 | AJ71: 13348 | AN71: 2040067732 | AP71: Inactive | AQ71: Inactive | AU71: Bank | AV71: BCA | AW71: Rekha Riakiah | AX71: 930183628
A72: 223064 | B72: Utami Septi Cahyani | C72: 82213650585 | D72: Utamisepticahyani120902@gmail.com | E72: SPG/SPB Toko | F72: Female | G72: 6310065209020002 | H72: 37511 | I72: 889 | J72: Islam | K72: O | L72: Cerai hidup | M72: 22 | N72: 889 | O72: 5039 | P72: Jl Usaha Bersama Rt 05,Desa Gunung Besar | Q72: Inactive | R72: 46083 | S72: Now | U72: 46265 | Y72: PT. Kita Mitra Indonesia | Z72: 22 | AA72: 889 | AD72: Full-Time | AE72: Kemitraan | AG72: 46198 | AH72: 46265 | AJ72: 12738 | AN72: 2746506115 | AP72: Inactive | AQ72: Inactive | AT72: TK/1 | AU72: Bank | AV72: BRI | AW72: Utami Septi Cahyani | AX72: 450101007823504 | AY72: Aditya Rizki Anto | AZ72: 83121259582 | BA72: Jl Usaha Bersama Rt 05,Desa Gunung Besar | BB72: Saudara Kandung
A73: 223072 | B73: Rizky Nanda Karunia | C73: 85231231536 | D73: rizkynandakarunia712@gmail.com | E73: SPG/SPB Toko | F73: Female | G73: 3510034712020001 | H73: 37232 | I73: 774 | J73: Islam | K73: A | L73: Belum Kawin | M73: 17 | N73: 819 | O73: 4162 | P73: Jl Pulau Saelus no 22 | Q73: Inactive | R73: 46084 | S73: Now | U73: 46265 | Y73: PT. Kita Mitra Indonesia | Z73: 17 | AA73: 819 | AB73: 4162 | AD73: Full-Time | AE73: Kemitraan | AG73: 46198 | AH73: 46265 | AJ73: 13573 | AN73: 3120617946 | AP73: Inactive | AQ73: Inactive | AU73: Bank | AV73: BCA | AW73: Rizky Nanda Karunia | AX73: 3510460391
A74: 223204 | B74: Marni Dwi widiyaningsih | C74: 89528646100 | D74: marniwidiyaningsih@gmail.com | E74: SPG/SPB Toko | F74: Female | G74: 3578174503960002 | H74: 35129 | I74: 768 | J74: Islam | K74: A | L74: Kawin | M74: 15 | N74: 801 | O74: 3936 | P74: jl kedinding lor GG manggis no 26 | Q74: Inactive | R74: 46084 | S74: Now | U74: 46265 | Y74: PT. Kita Mitra Indonesia | Z74: 15 | AA74: 801 | AB74: 3927 | AD74: Full-Time | AE74: Kemitraan | AF74: oke | AG74: 46198 | AH74: 46265 | AJ74: 11158 | AN74: 1394073595 | AO74: 901723981619000 | AP74: Inactive | AQ74: Inactive | AT74: K/I/2 | AU74: Bank | AV74: BCA | AW74: Marni Dwi widiyaningsih | AX74: 1011824809 | AY74: totok trismanto | AZ74: 895353750803 | BA74: jl kedinding lor GG manggis no 26 | BB74: Suami
A75: 224303 | B75: Tendy Anugerah Saputro | C75: 85693115913 | D75: tendyabas@gmail.com | E75: SPG/SPB Toko | F75: Male | G75: 3174042501000009 | H75: 36550 | I75: 693 | J75: Islam | K75: B | L75: Belum Kawin | M75: 11 | N75: 693 | O75: 1989 | P75: Jl Mampang Prapatan VIII, Gang ABC No 6, Rt.004 Rw.001, Kel. Tegal Parang, Kec. Mampang Prapatan, Jakarta Selatan 12790 | Q75: Inactive | R75: 46085 | S75: Now | U75: 46265 | Y75: PT. Kita Mitra Indonesia | Z75: 11 | AA75: 693 | AB75: 1991 | AD75: Full-Time | AE75: Kemitraan | AG75: 46198 | AH75: 46265 | AJ75: 13598 | AM75: 25097801762 | AN75: 2087418982 | AO75: 945682458017000 | AP75: Inactive | AQ75: Inactive | AT75: TK/0 | AU75: Bank | AV75: BCA | AW75: Tendy Anugerah Saputro | AX75: 2860229580 | AY75: Afif Ubaidilla | AZ75: 81809699669 | BA75: Jl Mampang Prapatan VIII, Gang ABC No 6 | BB75: Kerabat Dekat Lainnya
A76: 224929 | B76: M. Gedy Kolipatuloh | C76: 85959534528 | D76: natusvincere230794@gmail.com | E76: GTM | F76: Male | G76: 3578012307940003 | H76: 34538 | I76: 801 | J76: Islam | K76: Tidak Tahu | L76: Belum Kawin | M76: 15 | N76: 801 | O76: 3920 | P76: Kebraon 2 durian no 1 RT 3 RW 2 Karangpilang surabaya | Q76: Inactive | R76: 46083 | S76: Now | U76: 46265 | Y76: PT. Kita Mitra Indonesia | Z76: 15 | AA76: 801 | AB76: 3923 | AD76: Full-Time | AE76: Kemitraan | AG76: 46198 | AH76: 46265 | AJ76: 11181 | AM76: 23123892491 | AN76: 1394418047 | AP76: Inactive | AQ76: Inactive | AT76: TK/0 | AU76: Bank | AV76: BRI | AW76: M Gedy Kolipatuloh | AX76: 9601180420509
A77: 230339 | B77: Eza Adela | C77: 85656271235 | D77: adelaeza021@gmail.com | E77: SPG/SPB Toko | F77: Female | G77: 6101074605030005 | H77: 37717 | I77: 852 | J77: Islam | K77: Tidak Tahu | L77: Belum Kawin | M77: 20 | N77: 865 | O77: 4770 | P77: Sungai Naram, Ambassador Residence 3 | Q77: Inactive | R77: 46119 | S77: Now | U77: 46265 | W77: selesai project | Y77: PT. Kita Mitra Indonesia | Z77: 20 | AA77: 865 | AB77: 4767 | AD77: Full-Time | AE77: Kemitraan | AG77: 46228 | AH77: 46265 | AJ77: 13722 | AP77: Inactive | AQ77: Inactive | AU77: Bank | AV77: BCA | AW77: EZA ADELA | AX77: 8171876893 | AY77: Fitri | AZ77: 83199474587 | BA77: Kalimantan Barat, Kab Sambas , Selakau Kuala | BB77: Ibu
A78: 233463 | B78: Fatra Laily | C78: 89684056159 | D78: fatralaily98@gmail.com | E78: SPG/SPB Toko | F78: Female | G78: 7371086504980001 | H78: 35910 | I78: 957 | J78: Islam | K78: O | L78: Belum Kawin | M78: 27 | N78: 957 | O78: 5860 | P78: jalan barukang 5 no 2 | Q78: Inactive | R78: 46128 | S78: Now | U78: 46265 | W78: selesai project | Y78: PT. Kita Mitra Indonesia | Z78: 27 | AA78: 957 | AD78: Full-Time | AE78: Kemitraan | AG78: 46228 | AH78: 46265 | AJ78: 11090 | AP78: Inactive | AQ78: Inactive | AU78: Bank | AV78: BCA | AW78: fatra laily | AX78: 7685985489
A79: 236267 | B79: Yunita Eka Anggraeni | C79: 85647144195 | D79: yunita.anggraeni64@gmail.com | E79: SPG/SPB Toko | F79: Female | G79: 3323034106950002 | H79: 34851 | I79: 747 | J79: Islam | K79: B | L79: Kawin | M79: 13 | N79: 747 | O79: 3053 | P79: Sayangan Rt 01 Rw 04, Butuh | Q79: Inactive | R79: 46141 | S79: Now | U79: 46265 | Y79: PT. Kita Mitra Indonesia | Z79: 13 | AA79: 747 | AD79: Full-Time | AE79: Kemitraan | AG79: 46228 | AH79: 46265 | AJ79: 11214 | AO79: 391400389533000 | AP79: Inactive | AQ79: Inactive | AT79: K/3 | AU79: Bank | AV79: BRI | AW79: Yunita Eka Anggraeni | AX79: 691801040371539 | AY79: Novan Yales Saputra | AZ79: 81280583134 | BA79: Sayangan Rt 01 Rw 04, Butuh Temanggung | BB79: Suami
A80: 236271 | B80: Arenta putri Widyaningsih | C80: 8973123823 | D80: arentaputriwidyaningsih@gmail.com | E80: SPG/SPB Toko | F80: Female | G80: 3374156007040001 | H80: 38188 | I80: 757 | J80: Islam | K80: B | L80: Belum Kawin | M80: 13 | N80: 757 | O80: 3200 | P80: jl margoyoso IV rt 006/rw 004 | Q80: Inactive | R80: 46146 | S80: Now | U80: 46265 | W80: selesai project | Y80: PT. Kita Mitra Indonesia | Z80: 13 | AA80: 757 | AB80: 3192 | AD80: Full-Time | AE80: Kemitraan | AG80: 46146 | AH80: 46265 | AJ80: 13050 | AN80: 1697940358 | AO80: 3374156007040001 | AP80: Inactive | AQ80: Inactive | AT80: TK/0 | AU80: Bank | AV80: BCA | AW80: Arenta Putri Widyaningsih | AX80: 8715675648 | AY80: purwanto | AZ80: 89516162662 | BA80: jalan margoyoso IV | BB80: Ayah
A81: 236272 | B81: Yeremia Alexander | C81: 81910263671 | D81: yeremiaalexander03@gmail.com | E81: SPG/SPB Toko | F81: Male | G81: 3375030306070002 | H81: 39236 | I81: 758 | J81: Protestan | L81: Belum Kawin | M81: 13 | N81: 750 | P81: Perumahan Taman Seruni Jl Nusa indah No 48 Gamer | Q81: Inactive | R81: 46141 | S81: Now | U81: 46265 | Y81: PT. Kita Mitra Indonesia | Z81: 13 | AA81: 758 | AB81: 3202 | AD81: Full-Time | AE81: Kemitraan | AG81: 46228 | AH81: 46265 | AJ81: 12345 | AP81: Inactive | AQ81: Inactive | AU81: Bank | AV81: BCA | AW81: Yeremia Alexander | AX81: 3820378155 | AY81: Edhi Yohanes Hartono | AZ81: 87748942848 | BA81: Perumahan Taman Seruni Jl Nusa indah no 48 gamer. | BB81: Ayah
A82: 236709 | B82: Sisi septiana | C82: 89527950590 | D82: septianasisi45@gmail.com | E82: SPG/SPB Toko | F82: Female | G82: 6112054709980001 | H82: 36045 | I82: 863 | J82: Islam | K82: A | L82: Belum Kawin | M82: 22 | N82: 892 | O82: 5059 | P82: jl. bhayangkara 2 komp. pesona bhayangkara jalur 2 no.65 | Q82: Inactive | R82: 46153 | S82: Now | U82: 46265 | Y82: PT. Kita Mitra Indonesia | Z82: 22 | AA82: 892 | AB82: 5061 | AD82: Full-Time | AE82: Kemitraan | AG82: 46153 | AH82: 46265 | AJ82: 11062 | AO82: 416129427704000 | AP82: Inactive | AQ82: Inactive | AU82: Bank | AV82: MANDIRI | AW82: sisi septiana | AX82: 310022305919 | AY82: afrizal | AZ82: 82299939390 | BA82: landasan ulin | BB82: Kerabat Dekat Lainnya
A83: 242328 | B83: Sabila Fadillah | C83: 85624685906 | D83: sblfdllh@gmail.com | E83: SPG/SPB Toko | F83: Female | G83: 3204054903000004 | H83: 36594 | I83: 701 | J83: Islam | K83: O | L83: Kawin | Q83: Inactive | R83: 46161 | S83: Now | U83: 46265 | Y83: PT. Kita Mitra Indonesia | Z83: 12 | AA83: 718 | AB83: 2584 | AD83: Full-Time | AE83: Kemitraan | AG83: 46161 | AH83: 46265 | AJ83: 13946 | AO83: 851714915444000 | AP83: Inactive | AQ83: Inactive | AU83: Bank | AV83: BCA | AW83: SABILA FADILLAH | AX83: 2831985111 | AY83: Dicka Hermawan | AZ83: 81462211599 | BA83: CILENGKRANG II GG. PALASATI V RT 01/07 KEC. COBIRU KEL. PALASARI KOT. BANDUNG | BB83: Suami
A84: 242771 | B84: Nur Rahmah | C84: 87760225284 | D84: nurrahmahhh11@gmail.com | E84: Promotor Live | F84: Female | G84: 3671034307040002 | H84: 38171 | I84: 807 | J84: Islam | L84: Belum Kawin | M84: 16 | N84: 807 | O84: 4077 | P84: kebon besar batu ceper tangerang | Q84: Inactive | R84: 46164 | S84: Now | U84: 46265 | Y84: PT. Kita Mitra Indonesia | Z84: 11 | AA84: 696 | AB84: 1984 | AD84: Full-Time | AE84: Kemitraan | AG84: 46164 | AH84: 46265 | AJ84: 13405 | AN84: 3271481842 | AP84: Inactive | AQ84: Inactive | AT84: TK/0 | AU84: Bank | AV84: BCA | AW84: Nur Rahmah | AX84: 5940898368 | AY84: Abdul Hakim | AZ84: 8159456767 | BA84: Batu Ceper Tangerang | BB84: Ayah
A85: 247414 | B85: Helen Budi Yana | C85: 82377054696 | D85: hellenby889@gmail.com | E85: SPG/SPB Toko | F85: Female | G85: 1871036605950003 | H85: 35211 | I85: 676 | J85: Islam | K85: A | L85: Kawin | M85: 8 | N85: 677 | O85: 1836 | P85: banjar sari | Q85: Inactive | R85: 46174 | S85: Now | U85: 46265 | W85: selesai project | Y85: PT. Kita Mitra Indonesia | Z85: 8 | AA85: 677 | AD85: Full-Time | AE85: Kemitraan | AG85: 46174 | AH85: 46265 | AJ85: 11219 | AP85: Inactive | AQ85: Inactive | AU85: Bank | AV85: BCA | AW85: helen budi yana | AX85: 231574629
A86: 247429 | B86: Ferdinand Anthonius Harianja | C86: 85190611181 | D86: ferdinandah.19@icloud.com | E86: GTM | F86: Male | G86: 1207191909990004 | H86: 36422 | I86: 611 | J86: Protestan | K86: O | L86: Belum Kawin | M86: 2 | N86: 572 | O86: 404 | P86: Dusun III Perum Johar II Jl Semangka No 11 | Q86: Inactive | R86: 46174 | S86: Now | U86: 46265 | W86: selesai project | Y86: PT. Kita Mitra Indonesia | Z86: 2 | AA86: 590 | AB86: 687 | AD86: Full-Time | AE86: Kemitraan | AG86: 46174 | AH86: 46265 | AJ86: 11038 | AM86: 25127664321 | AN86: 1107737267 | AO86: 1207191909990004 | AP86: Inactive | AQ86: Inactive | AT86: TK/0 | AU86: Bank | AV86: BCA | AW86: Ferdinand Anthonius Harianja | AX86: 2421392678 | AY86: H. Harianja | AZ86: 81361339292 | BA86: Dusun III Perum Johar II Jl Semangka No 11 | BB86: Ayah
A87: 247512 | B87: Wahyu Septi Dwi Utari | C87: 895320596740 | D87: fahrezag548@gmail.com | E87: SPG/SPB Toko | F87: Female | G87: 2171116701019003 | H87: 36918 | I87: 773 | J87: Islam | K87: O | L87: Belum Kawin | M87: 15 | N87: 773 | O87: 3468 | P87: jln gajah mada gg hj syujur no.38 rambipuji | Q87: Inactive | R87: 46177 | S87: Now | U87: 46265 | Y87: PT. Kita Mitra Indonesia | Z87: 15 | AA87: 773 | AB87: 3468 | AD87: Full-Time | AE87: Kemitraan | AG87: 46177 | AH87: 46265 | AJ87: 14026 | AP87: Inactive | AQ87: Inactive | AU87: Bank | AV87: BCA | AW87: WAHYU SEPTI DWI UTARI | AX87: 3330641044 | AY87: Mutiana | AZ87: 81333786574 | BA87: jln gajah mada gg hj.syujur no.38 | BB87: Ibu
A88: 251960 | B88: Ardi Basri | C88: 85151005619 | D88: ardibasri948@gmail.com | E88: GTM | F88: Male | G88: 7371061009930002 | H88: 34283 | I88: 957 | J88: Islam | K88: Tidak Tahu | L88: Belum Kawin | M88: 27 | N88: 957 | O88: 5863 | P88: Jl. Ir sutami ( villa mutiara asri 7 no 12 ) | Q88: Inactive | R88: 46175 | S88: Now | U88: 46265 | W88: selesai project | Z88: 27 | AA88: 957 | AD88: Full-Time | AE88: Kemitraan | AG88: 46175 | AH88: 46265 | AJ88: 11188 | AP88: Inactive | AQ88: Inactive | AU88: Bank | AV88: BCA | AW88: Ardi Basri | AX88: 251548799
A89: 253928 | B89: Fathir Aula Ni'am | C89: 89677241516 | D89: ftraula@gmail.com | E89: SPG/SPB Toko | F89: Male | G89: 3318152910060001 | H89: 39019 | I89: 742 | J89: Islam | K89: Tidak Tahu | L89: Belum Kawin | M89: 13 | N89: 742 | O89: 2986 | P89: Dk Rames Rt3/Rw4 Ds Sukoharjo | Q89: Inactive | R89: 46195 | S89: Now | U89: 46265 | W89: selesai project | Y89: PT. Kita Mitra Indonesia | Z89: 13 | AA89: 742 | AB89: 2981 | AD89: Full-Time | AE89: Kemitraan | AG89: 46195 | AH89: 46265 | AJ89: 12550 | AP89: Inactive | AQ89: Inactive | AU89: Bank | AV89: BCA | AW89: Fathir Aula Niam | AX89: 980987531 | AY89: dani prayoga | AZ89: 83144893920 | BA89: karangdowo Kutoharjo | BB89: Kerabat Dekat Lainnya
A90: 254768 | B90: Mualling | C90: 87890300301 | D90: muallinglim@gmail.com | E90: SPG/SPB Toko | F90: Male | G90: 7311021209010002 | H90: 37599 | I90: 945 | J90: Islam | K90: Tidak Tahu | L90: Belum Kawin | M90: 27 | N90: 957 | O90: 5861 | P90: Jl. Sukaria 12 | Q90: Inactive | R90: 46198 | S90: Now | U90: 46265 | Y90: PT. Kita Mitra Indonesia | Z90: 27 | AA90: 957 | AD90: Full-Time | AE90: Kemitraan | AG90: 46198 | AH90: 46265 | AJ90: 11092 | AP90: Inactive | AQ90: Inactive | AU90: Bank | AV90: BCA | AW90: Mualling | AX90: 8260425260 | AY90: Fera ferohnika | AZ90: 8979632074 | BA90: Jl. Polejiwa pesisir | BB90: Kerabat Dekat Lainnya
A91: 255195 | B91: Ferdiyan | C91: 87773201795 | D91: ferdiiiaaannn@gmail.com | E91: SPG/SPB Toko | F91: Male | G91: 6471041802030002 | H91: 37670 | I91: 900 | J91: Islam | K91: A | L91: Belum Kawin | M91: 23 | N91: 900 | O91: 5153 | P91: Jl.Di.Panjaitan Rt.04 Kel. Sumber Rejo | Q91: Inactive | R91: 46202 | S91: Now | U91: 46265 | W91: selesai project | Y91: PT. Kita Mitra Indonesia | Z91: 23 | AA91: 900 | AB91: 5152 | AD91: Full-Time | AE91: Kemitraan | AG91: 46202 | AH91: 46265 | AJ91: 14125 | AM91: 24027008804 | AN91: 1174249574 | AO91: 6471041802030002 | AP91: Inactive | AQ91: Inactive | AT91: TK/0 | AU91: Bank | AV91: MANDIRI | AW91: Ferdian | AX91: 1490014116893 | AY91: Rahmawati | AZ91: 85952824512 | BA91: Jl.Di.Panjaitan Rt.04 Ke. Sumber Rejo | BB91: Ibu
A92: 263097 | B92: Heri Suprihatin | C92: 83122638000 | D92: heryfriska97@gmail.com | E92: SPG/SPB Toko | F92: Male | G92: 3403080209920001 | H92: 33849 | J92: Islam | L92: Kawin | M92: 14 | N92: 762 | O92: 3246 | P92: Semuluh kidul RT/RW 003/015 ,Ngeposari ,Semanu ,Gunung Kidul | Q92: Inactive | R92: 46224 | S92: Now | U92: 46265 | W92: selesai project | Y92: PT. Kita Mitra Indonesia | Z92: 13 | AA92: 757 | AD92: Full-Time | AE92: Kemitraan | AG92: 46224 | AH92: 46265 | AJ92: 11283 | AP92: Inactive | AQ92: Inactive | AU92: Bank | AV92: BCA | AW92: Heri Suprihatin | AX92: 375170910
A93: 264602 | B93: Balqis Ayudia Pramesti | C93: 89514649794 | D93: balqisayudia123@gmail.com | E93: SPG/SPB Stein | F93: Female | G93: 3515176702040001 | H93: 38044 | I93: 779 | J93: Islam | K93: O | L93: Belum Kawin | M93: 15 | N93: 801 | O93: 3923 | P93: jl Pulo Tegalsari GG 4 no.2 Wonokromo SBY | Q93: Inactive | R93: 46239 | S93: Now | U93: 46265 | W93: selesai project | Y93: PT. Kita Mitra Indonesia | Z93: 15 | AA93: 801 | AB93: 3940 | AD93: Full-Time | AE93: Kemitraan | AG93: 46239 | AH93: 46265 | AJ93: 14308 | AP93: Inactive | AQ93: Inactive | AU93: Bank | AV93: BCA | AW93: Balqis Ayudia Pramesti | AX93: 5065480881
A94: 265197 | B94: Fiqri Nur Arfindiyani Putri | C94: 85604913433 | D94: findyptr024@gmail.com | E94: SPG/SPB Toko | F94: Female | G94: 3578252412020003 | H94: 37614 | I94: 801 | J94: Islam | K94: Tidak Tahu | L94: Belum Kawin | M94: 15 | N94: 796 | O94: 3900 | Q94: Inactive | R94: 46240 | S94: Now | U94: 46265 | W94: selesai project | Y94: PT. Kita Mitra Indonesia | Z94: 15 | AA94: 796 | AB94: 3900 | AD94: Full-Time | AE94: Kemitraan | AG94: 46240 | AH94: 46265 | AJ94: 11151 | AN94: 2162236026 | AP94: Inactive | AQ94: Inactive | AT94: TK/1 | AU94: Bank | AV94: MANDIRI | AW94: FIQRI NUR ARFINDIYANI PUTRI | AX94: 1420024289133 | AY94: DANI | AZ94: 89687196782 | BA94: JL Gunung Anyar Kidul 1 | BB94: Kerabat Dekat Lainnya
A95: 265300 | B95: Indriyani | C95: 82218621312 | D95: awdodotig@gmail.com | E95: SPG/SPB Stein | F95: Female | G95: 3211066003980002 | H95: 35874 | I95: 708 | J95: Islam | K95: AB | L95: Belum Kawin | M95: 12 | N95: 718 | O95: 2570 | P95: jl sekelimus utara no.5 batununggal bandung kidul | Q95: Inactive | R95: 46239 | S95: Now | U95: 46265 | Y95: PT. Kita Mitra Indonesia | Z95: 12 | AA95: 718 | AB95: 2567 | AD95: Full-Time | AE95: Kemitraan | AG95: 46239 | AH95: 46265 | AJ95: 14316 | AP95: Inactive | AQ95: Inactive | AU95: Bank | AV95: BCA | AW95: indriyani | AX95: 2031154997 | AY95: enok wihaeti | AZ95: 81214235568 | BA95: sumedang | BB95: Ibu
A96: 265504 | B96: Gabriella Marchelline Blandina Romkeny | C96: 88217641516 | D96: gabriellaromkeny8@gmail.com | E96: SPG/SPB Stein | F96: Female | G96: 3578186103010005 | H96: 36971 | I96: 801 | J96: Protestan | K96: O | L96: Kawin | M96: 15 | N96: 801 | O96: 3937 | P96: Wisma Lidah Kulon XB 38 | Q96: Inactive | R96: 46239 | S96: Now | U96: 46265 | W96: selesai project | Y96: PT. Kita Mitra Indonesia | Z96: 15 | AA96: 801 | AB96: 3928 | AD96: Full-Time | AE96: Kemitraan | AG96: 46239 | AH96: 46265 | AJ96: 14321 | AP96: Inactive | AQ96: Inactive | AU96: Bank | AV96: BCA | AW96: Gabriella Marchelline Blandina Romkeny | AX96: 8291068537
A97: 265510 | B97: Chamida Ananda Septiani | C97: 85298512206 | D97: chamidaananda@gmail.com | E97: SPG/SPB Toko | F97: Female | G97: 7208086609990002 | H97: 36429 | I97: 930 | J97: Islam | K97: B | L97: Belum Kawin | M97: 26 | N97: 935 | O97: 5564 | P97: Jl. Banteng 4 | Q97: Inactive | R97: 46240 | S97: Now | U97: 46265 | W97: selesai project | Y97: PT. Kita Mitra Indonesia | Z97: 26 | AA97: 935 | AB97: 5564 | AD97: Full-Time | AE97: Kemitraan | AG97: 46240 | AH97: 46265 | AJ97: 11095 | AP97: Inactive | AQ97: Inactive | AU97: Bank | AV97: BRI | AW97: Chamida Ananda Septiani | AX97: 519801009763530
A98: 266419 | B98: Uun Yanuarti | C98: 89513420390 | D98: uunyanuarti2425@gmail.com | E98: SPG/SPB Toko | F98: Female | G98: 7306076401040002 | H98: 38010 | I98: 957 | J98: Islam | K98: B | L98: Belum Kawin | M98: 27 | N98: 941 | O98: 5626 | P98: BTN Griya Ning Citra Lestari Blok A No 5 | Q98: Inactive | R98: 46242 | S98: Now | U98: 46265 | Y98: PT. Kita Mitra Indonesia | Z98: 27 | AA98: 957 | AD98: Full-Time | AE98: Kemitraan | AG98: 46242 | AH98: 46265 | AJ98: 13472 | AM98: 26041331161 | AO98: 7306076401040002 | AP98: Inactive | AQ98: Inactive | AT98: TK/0 | AU98: Bank | AV98: MAYBANK | AW98: Uun Yanuarti | AX98: 8791073361 | AY98: Iin Oktavianingsih | AZ98: 8281262499169 | BA98: BTN Griya Ning Citra Lestrai | BB98: Saudara Kandung
A99: 266738 | B99: Fransiskus Xaverius K Koten | C99: 81239754529 | D99: fxaverius048@gmail.com | E99: SPG/SPB Toko | F99: Male | G99: 5306032705960001 | H99: 35212 | I99: 838 | J99: Protestan | K99: O | L99: Belum Kawin | M99: 23 | N99: 900 | O99: 5154 | P99: Jl. BANTIMURUNG NO. 92 RT/RW : 042/000 Kel. GUNUNG BAHAGIA | Q99: Inactive | R99: 46247 | S99: Now | U99: 46265 | W99: selesai project | Y99: PT. Kita Mitra Indonesia | Z99: 23 | AA99: 900 | AB99: 5152 | AD99: Full-Time | AE99: Kemitraan | AG99: 46247 | AH99: 46265 | AJ99: 11123 | AP99: Inactive | AQ99: Inactive | AU99: Bank | AV99: BNI | AW99: FRANSISKUS XAVERIUS KUDA KOTEN | AX99: 1192838885 | AY99: MERRY | AZ99: 81250334517 | BA99: Balikpapan | BB99: Kerabat Dekat Lainnya
A100: 268600 | B100: Luh Yoni Kamala | C100: 8211304807 | D100: canyonikamala@gmail.com | E100: Promotor Live | F100: Female | G100: 5108024302080002 | H100: 39481 | I100: 818 | J100: Hindu | K100: O | L100: Belum Kawin | M100: 17 | N100: 819 | O100: 4164 | P100: Padangsambian, Jl. Kebo Iwa Utara | Q100: Inactive | R100: 46258 | S100: Now | U100: 46265 | Y100: PT. Kita Mitra Indonesia | Z100: 17 | AA100: 819 | AD100: Full-Time | AE100: Kemitraan | AG100: 46258 | AH100: 46265 | AJ100: 14124 | AP100: Inactive | AQ100: Inactive | AU100: Bank | AV100: BRI | AW100: LUH YONI KAMALA | AX100: 12401018067539 | AY100: Denny Candra | AZ100: 881037675722 | BA100: Jl. Tukad Barito No. 38, Panjer, Denpasar Selatan | BB100: Kerabat Dekat Lainnya
...

Sheet Data StaffInc_2
A1: Name* | B1: Join Date | C1: Active Contract start date | D1: Active Contract end date
A2: Anggiza Gana Pawestri | B2: 43409 | C2: 46167 | D2: 46265
A3: Annisa | B3: 42826 | C3: 46167 | D3: 46265
A4: Firda Duri Yatinal Ulya | B4: 43777 | C4: 46167 | D4: 46265
A5: Elisa Putra Afdiono | B5: 44077 | C5: 46167 | D5: 46265
A6: I Ketut Sugiarta | B6: 44753 | C6: 46198 | D6: 46265
A7: Adelina Astuti | B7: 44852 | C7: 46167 | D7: 46265
A8: Ari Kusumawati | B8: 44844 | C8: 46167 | D8: 46265
A9: Firda Nur Agustin Cahyani | B9: 44858 | C9: 46167 | D9: 46265
A10: Habib Mustopa | B10: 44911 | C10: 46198 | D10: 46265
A11: Faisol Adha | B11: 45147 | C11: 46167 | D11: 46265
A12: Fitri Wulandari | B12: 45323 | C12: 46228 | D12: 46265
A13: Hendrika Buwa | B13: 45327 | C13: 46167 | D13: 46258
... A101: Dewi Pramudita | B101: 46256 | C101: 46256 | D101: 46265

Sheet Sheet2
A1: EMPLOYEE ID | B1: Nama Karyawan | C1: Posisi Jabatan | D1: NAMA TOKO | E1: LIST CABANG | F1: COST CENTER
A2: DM20260001 | B2: Abel Saskia Putri | C2: SPG/SPB Toko | D2: MAMASUKA | E2: SAMARINDA | F2: SAMARINDA
A3: DM20260002 | B3: Adelina Astuti | C3: SPG/SPB MT | D3: MALL KELAPA GADING | E3: JAKARTA | F3: JAKARTA
A4: DM20260003 | B4: Agustia Ningrum | C4: SPG/SPB Toko | D4: NUANSA PANGKALANBUN | E4: KOTAWARINGIN BARAT | F4: BANJARMASIN
A5: DM20260004 | B5: Agustina Galuh Prihaningtyas | C5: SPG/SPB Toko | D5: UFO YOGYAKARTA JOKTENG | E5: YOGYAKARTA | F5: SEMARANG
A6: DM20260005 | B6: Ainun Jariah | C6: SPG/SPB Toko | D6: GOLDEN 10 | E6: BANJARMASIN | F6: BANJARMASIN
A7: DM20260006 | B7: Anggiza Gana Pawestri | C7: SPG/SPB Toko | D7: HARAPAN BARU | E7: DEPOK | F7: JAKARTA
A8: DM20260007 | B8: Anisa Nurajijah | C8: SPG/SPB Toko | D8: OSCAR GEMILANG | E8: KETAPANG | F8: PONTIANAK
A9: DM20260008 | B9: Annisa | C9: SPG/SPB Toko | D9: POS ELEKTRONIK | E9: BANJARMASIN | F9: BANJARMASIN
A10: DM20260009 | B10: Ardi Basri | C10: SPG/SPB Toko | D10: MAKASSAR | E10: MAKASSAR | F10: MAKASSAR
A11: DM20260010 | B11: Arenta putri Widyaningsih | C11: SPG/SPB Toko | D11: ADA SILIWANGI | E11: SEMARANG | F11: SEMARANG
A12: DM20260011 | B12: Ari Kusumawati | C12: SPG/SPB MT | D12: MALL KELAPA GADING | E12: JAKARTA | F12: JAKARTA
... A124: DM20260123 | B124: Yustika Kaimuddin | C124: SPG/SPB Toko | D124: MAXI ALAUDDIN | E124: MAKASSAR | F124: MAKASSAR

Sheet Sheet3
A1: Nama Kota Penempatan | B1: NAMA SESUAI KTP | C1: Alamat sesuai ktp | D1: Tgl Lahir | E1: Column 14 | F1: Kota Kelahiran | G1: TTL | H1: Pendidikan Terakhir | I1: No WA yang bisa di hubungi | J1: Alamat Email | K1: Lokasi Toko Penempatan Kerja | L1: No Rekening Bank BCA | M1: Column 1 | N1: Cek | O1: scan pkwt | P1: cek dg database
A2: BANJARMASIN | B2: Annisa | C2: Jl.keramat gg satu dua rt.10 no.37d kelurahan sungai bilu kecamatan banjarmasin timur banjarmasin 70236 | D2: 33553 | E2: =TEXT(D2,"DD MMMM YYY") -> 11 November 1991 | F2: Banjarmasin | G2: =F2&","&E2 -> Banjarmasin,11 November 1991 | H2: SLTA | I2: 085754771101 | J2: Annisaauliani11@gmail.com | K2: Kayutangi banjarmasin | L2: 0511915910 | N2: BANJARMASIN | O2: done | P2: =vlookup(B2,'RAW DATA'!B:U,14,0) -> 46265
A3: JAKARTA | B3: Moh Nurdiansah | C3: Kp curugaru RT/RW : 001/001 Kel, Kadugembong Kec, kaduhejo kab Pandeglang Banten | D3: 37975 | E3: =TEXT(D3,"DD MMMM YYY") -> 20 Desember 2003 | F3: Pandeglang | G3: =F3&","&E3 -> Pandeglang ,20 Desember 2003 | H3: SLTA | I3: 085774109821 | J3: iyann201203@gmail.com | K3: Jabodetabek | L3: 7125610072 | N3: #N/A | O3: done | P3: =vlookup(B3,'RAW DATA'!B:U,14,0) -> 46265
A4: DENPASAR | B4: Rizky Nanda Karunia | C4: Dsn Ngadimulyo RT/RW 002/002, Ds Bulurejo, Kec Purwoharjo, Kab Banyuwangi | D4: 37232 | E4: =TEXT(D4,"DD MMMM YYY") -> 07 Desember 2001 | F4: Banyuwangi | G4: =F4&","&E4 -> Banyuwangi,07 Desember 2001 | H4: S1 | I4: 085231231536 | J4: rizkynandakarunia712@gmail.com | K4: Toko Media Elektronik Denpasar | L4: 3510460391 | N4: SURABAYA | O4: done | P4: =vlookup(B4,'RAW DATA'!B:U,14,0) -> 46265
A5: MAKASSAR | B5: YUSTIKA KAIMUDDIN | C5: BTN JENEMADINGING BLOK A 2 | D5: 35874 | E5: =TEXT(D5,"DD MMMM YYY") -> 20 Maret 1998 | F5: Ujung pandang | G5: =F5&","&E5 -> Ujung pandang ,20 Maret 1998 | H5: SLTA | I5: 088245137660 | J5: yustikatika50@gmail.com | K5: MAXI STORE ALAUDDIN MAKASSAR | L5: 7991303573 | N5: MAKASSAR | O5: done | P5: =vlookup(B5,'RAW DATA'!B:U,14,0) -> 46265
A6: BANJARMASIN | B6: Ainun jariah | C6: Jl. Kelayan A | Gang Sidodadi RT.11 RW.01 No.18 | D6: 34822 | E6: =TEXT(D6,"DD MMMM YYY") -> 03 Mei 1995 | F6: Banjarmasin | G6: =F6&","&E6 -> Banjarmasin ,03 Mei 1995 | H6: SLTA | I6: 0895608199789 | J6: program.ainun@gmail.com | K6: Golden 10 Banjarmasin | L6: 7820819785 | N6: #N/A | O6: done | P6: =vlookup(B6,'RAW DATA'!B:U,14,0) -> 46265
A7: JAKARTA | B7: Anggiza Gana pawestri | C7: Jl.Buni Malaka Rt06/08 no 15 kel.munjul kec. Cipayung Jakarta Timur | D7: 31659 | E7: =TEXT(D7,"DD MMMM YYY") -> 04 September 1986 | F7: Jakarta | G7: =F7&","&E7 -> Jakarta ,04 September 1986 | H7: SLTA | I7: 087887345099 | J7: Anggipawestri04@gmail.com | K7: Depok | L7: 8691115984 | N7: DEPOK | O7: done | P7: =vlookup(B7,'RAW DATA'!B:U,14,0) -> 46265
A8: PONOROGO | B8: Ayu novitaningsih | C8: Dusun bringin RT02 RW01 Desa Karangwaluh kecamatan Sampung Kabupaten Ponorogo | D8: 35012 | E8: =TEXT(D8,"DD MMMM YYY") -> 09 November 1995 | F8: Ponorogo | G8: =F8&","&E8 -> Ponorogo,09 November 1995 | H8: SLTA | I8: 082141638390 | J8: ayumamay09@gmail.com | K8: Ponorogo | L8: 2891046822 | M8: keliru | N8: PONOROGO | O8: done | P8: =vlookup(B8,'RAW DATA'!B:U,14,0) -> 46265
A9: SAMARINDA | B9: FIRDA DURI YATINAL ULYA | C9: JL.PEMUDA 2 GG.PENDAWA BLOK.E NO.86 RT.012 KEL.TEMINDUNG PERMAI KEC.SUNGAI PINANG | D9: 8/27/0095 | E9: =TEXT(D9,"DD MMMM YYY") -> 27 Agustus 0095 | F9: SAMARINDA | G9: =F9&","&E9 -> SAMARINDA,27 Agustus 0095 | H9: SLTA | I9: 082128843818 | J9: firdaduriatinalulya@gmail.com | K9: NUANSA SUPERSTORE ELECTRONIK SAMARINDA (JL.IMAM BONJOL NO.20 | L9: 7935297133 | N9: SAMARINDA | O9: done | P9: =vlookup(B9,'RAW DATA'!B:U,14,0) -> 46265
A10: MAKASSAR | B10: SULAIMAN | C10: JATIA, KELURAHAN MATA ALLO, KECAMATAN BAJENG, KABUPATEN GOWA | D10: 34603 | E10: =TEXT(D10,"DD MMMM YYY") -> 26 September 1994 | F10: MAKASSAR | G10: =F10&","&E10 -> MAKASSAR,26 September 1994 | H10: SLTA | I10: 087845027416 | J10: aimanslipknot123@gmail.com | K10: TOKO SEMERU PERINTIS ( MAKASSAR ) | L10: 6485307366 | N10: MAKASSAR | O10: done | P10: =vlookup(B10,'RAW DATA'!B:U,14,0) -> 46265
A11: SURABAYA | B11: MOY YUSTIWA RAHAYU PUTRI KARTIKA | C11: DSN. GROPYOK, DS. TANON, RT/RW : 002/003, KEC. PAPAR, KAB. KEDIRI | D11: 37492 | E11: =TEXT(D11,"DD MMMM YYY") -> 24 Agustus 2002 | F11: KEDIRI | G11: =F11&","&E11 -> KEDIRI ,24 Agustus 2002 | H11: S1 | I11: 081335885943 | J11: moyyustiwa24@gmail.com | K11: HARTONO BGJ | L11: 6123069515 | N11: #N/A | O11: done | P11: =vlookup(B11,'RAW DATA'!B:U,14,0) -> 46265
A12: MAKASSAR | B12: Irma Fitriani | C12: Bukit Hartaco indah blok 1B | D12: 32993 | E12: =TEXT(D12,"DD MMMM YYY") -> 30 April 1990 | F12: Soppeng | G12: =F12&","&E12 -> Soppeng ,30 April 1990 | H12: SLTA | I12: 085346312661 | J12: irmafitr3004@gmail.com | K12: Maxi perintis | L12: 0251311616 | N12: #N/A | O12: done | P12: =vlookup(B12,'RAW DATA'!B:U,14,0) -> 46265
A13: JAKARTA | B13: Nur Rahmah | C13: kebon besar rt02 rw 03 kecamatan batu ceper tangerang | D13: 38171 | E13: =TEXT(D13,"DD MMMM YYY") -> 03 Juli 2004 | F13: Tangerang | G13: =F13&","&E13 -> Tangerang ,03 Juli 2004 | H13: SLTA | I13: 087760225284 | J13: nurrahmahhh11@gmail.com | K13: Emetal Asia Jaya | L13: 5940898368 | N13: JABO | O13: done | P13: =vlookup(B13,'RAW DATA'!B:U,14,0) -> 46265
A14: SURABAYA | B14: Nany Maria Panjaitan | C14: Mrutukalianyar 165 | D14: 32016 | E14: =TEXT(D14,"DD MMMM YYY") -> 27 Agustus 1987 | F14: SURABAYA | G14: =F14&","&E14 -> SURABAYA,27 Agustus 1987 | H14: SLTA | I14: 08132230318 | J14: nanymariap@gmail.com | K14: PERDANA ELEKTRONIK MANYAR | L14: 1020482849 | N14: SURABAYA | O14: done | P14: =vlookup(B14,'RAW DATA'!B:U,14,0) -> 46265
A15: JAKARTA | B15: Liya NataLiya | C15: PT MII RT/RW 001/005 Kel. Pamesi Kec. Bathin Solapan Kab. Bengkalis Riau | D15: 37253 | E15: =TEXT(D15,"DD MMMM YYY") -> 28 Desember 2001 | F15: Pasaman, Sumatera Barat | G15: =F15&","&E15 -> Pasaman, Sumatera Barat,28 Desember 2001 | H15: SLTA | I15: 082385625202 | J15: liyanalita1120@gmail.com | K15: Toko Atria Kelapa Gading | L15: 8520379852 | N15: JAKARTA | O15: done | P15: =vlookup(B15,'RAW DATA'!B:U,14,0) -> 46265
A16: JAKARTA | B16: Fahrur Reza | C16: Kalibata Selatan no 41, RT 002 RW 009 Kelurahan Kalibata Kecamatan Pancoran Jakarta Selatan 12740 | D16: 34895 | E16: =TEXT(D16,"DD MMMM YYY") -> 15 Juli 1995 | F16: Jakarta | G16: =F16&","&E16 -> Jakarta ,15 Juli 1995 | H16: S1 | I16: 087851843056 | J16: ezaenii@gmail.com | K16: SPN Housware (Jakarta Utara) & Sinar Terang (Jakarta Selatan) | L16: 1280346540 | N16: #N/A | O16: done | P16: =vlookup(B16,'RAW DATA'!B:U,14,0) -> 46265
A17: YOGYAKARTA | B17: CHRISTIANA DWI JAYANTI | C17: KARANGPUTIH TLOGO PRAMBANAN KLATEN RT 009 RW 006 | D17: 35980 | E17: =TEXT(D17,"DD MMMM YYY") -> 04 Juli 1998 | F17: KLATEN | G17: =F17&","&E17 -> KLATEN,04 Juli 1998 | H17: SLTA | I17: 085174367440 | J17: christianadwijayanti78@gmail.com | K17: ATAKRIB ELECTRONICS LIFESTYLE | L17: 0601290102 | N17: YOGYAKARTA | O17: done | P17: =vlookup(B17,'RAW DATA'!B:U,14,0) -> 46265
A18: KETAPANG | B18: anisa nurajijah | C18: jl.lingkar kota | D18: 38319 | E18: =TEXT(D18,"DD MMMM YYY") -> 28 November 2004 | F18: subang, jawa barat | G18: =F18&","&E18 -> subang, jawa barat,28 November 2004 | H18: SLTA | I18: 089524367514 | J18: uchanel1983@gmail.com | K18: ketapang | L18: 1234567890 | N18: KETAPANG | O18: done | P18: =vlookup(B18,'RAW DATA'!B:U,14,0) -> 46265
A19: SURABAYA | B19: Elisa putra afdiono | C19: Margorejo 2G nomer 32 | D19: 35132 | E19: =TEXT(D19,"DD MMMM YYY") -> 08 Maret 1996 | F19: Surabaya | G19: =F19&","&E19 -> Surabaya,08 Maret 1996 | H19: SLTA | I19: 089686949505 | J19: zolla041123@gmail.com | K19: Toeng market | L19: 5600289308 | N19: #N/A | O19: done | P19: =vlookup(B19,'RAW DATA'!B:U,14,0) -> 46265
A20: JAKARTA | B20: Yahya | C20: Dusun Rukem Rt/Rw 001/005 Kelurahan Pamutih desa pamutih, kecamatan ulujami ,kabupaten Pemalang Jawa Tengah | D20: 33392 | E20: =TEXT(D20,"DD MMMM YYY") -> 03 Juni 1991 | F20: jakarta | G20: =F20&","&E20 -> jakarta,03 Juni 1991 | H20: SLTA | I20: 085179986982 | J20: yahyaharita2017@gmail.com | K20: Jawa Electrik/Elektronik Jl wijaya kusuma no.38 jakarta Timur | L20: 1080388914 | N20: JABO | O20: done | P20: =vlookup(B20,'RAW DATA'!B:U,14,0) -> 46265
A21: JEMBER | B21: Hagai Hendrik Yonathan | C21: Dusun Babatan RT 003 RW 018 Sidomekar Semboro Jember | D21: 31317 | E21: =TEXT(D21,"DD MMMM YYY") -> 27 September 1985 | F21: Lumajang | G21: =F21&","&E21 -> Lumajang,27 September 1985 | H21: SLTA | I21: 081235652785 | J21: joetozeta@gmail.com | K21: Ramai Jaya Jember | L21: 1250894160 | M21: keliru | N21: JEMBER | O21: done | P21: =vlookup(B21,'RAW DATA'!B:U,14,0) -> 46265
A22: BOGOR | B22: Siti Maryam | C22: Bumi pesanggrahan indah Blok C6 no.6 rt/rw 005/010 kel. Cilebut barat kec. Sukaraja kab. Bogor | D22: 31546 | E22: =TEXT(D22,"DD MMMM YYY") -> 14 Mei 1986 | F22: Ciamis | G22: =F22&","&E22 -> Ciamis,14 Mei 1986 | H22: SLTA | I22: 085211110630 | J22: sitimaryam140586@gmail.com | K22: Cahaya baru bogor | L22: 4210353190 | N22: BOGOR | O22: done | P22: =vlookup(B22,'RAW DATA'!B:U,14,0) -> 46265
A23: JAKARTA | B23: TENDY ANUGERAH SAPUTRO | C23: Jl Jeruk Purut No 15 RT.007 RW.003, Kelurahan Cilandak Timur, Kecamatan Pasar Minggu, Jakarta Selatan, 12560 | D23: 36550 | E23: =TEXT(D23,"DD MMMM YYY") -> 25 Januari 2000 | F23: Jakarta | G23: =F23&","&E23 -> Jakarta,25 Januari 2000 | H23: SLTA | I23: 085693115913 | J23: tendyabas@gmail.com | K23: JABO - HARTONO PONDOK INDAH | L23: 2860229580 | N23: JAKARTA SELATAN | O23: done | P23: =vlookup(B23,'RAW DATA'!B:U,14,0) -> 46265
A24: KEDIRI | B24: Imelda Febri Christina | C24: Jl. Kaliombo Raya 93 | D24: 37308 | E24: =TEXT(D24,"DD MMMM YYY") -> 21 Februari 2002 | F24: Kediri | G24: =F24&","&E24 -> Kediri,21 Februari 2002 | H24: SLTA | I24: 081217248277 | J24: imeldamito0612@gmail.com | K24: Ufo Elektronik Kediri | L24: 2980820818 | N24: #N/A | O24: done | P24: =vlookup(B24,'RAW DATA'!B:U,14,0) -> 46265
A25: SAMPIT | B25: MUNJIYAH AGUS CANCETTA | C25: JL WALTER CONDRAD GG LOMBOK | D25: 38092 | E25: =TEXT(D25,"DD MMMM YYY") -> 15 April 2004 | F25: SAMPIT | G25: =F25&","&E25 -> SAMPIT,15 April 2004 | H25: SLTA | I25: 082255195399 | J25: cancetta4@gmail.com | K25: SAMPIT, KOTAWARINGIN TUMUR | L25: 6695618313 | N25: SAMPIT | O25: done | P25: =vlookup(B25,'RAW DATA'!B:U,14,0) -> 46265
A26: PALANGKARAYA | B26: Khoirunnisa Yuliana | C26: Jl. Danau Rangas VII No. 32 | D26: 36349 | E26: =TEXT(D26,"DD MMMM YYY") -> 08 Juli 1999 | F26: Palangkaraya | G26: =F26&","&E26 -> Palangkaraya,08 Juli 1999 | H26: SLTA | I26: 083150001212 | J26: Khoirunnisayuliana39@gmail.com | K26: Sentra Palangkaraya | L26: 6575189966 | M26: keliru | N26: BANJARMASIN | O26: done | P26: =vlookup(B26,'RAW DATA'!B:U,14,0) -> 46265
A27: PONTIANAK | B27: CHARLES SETIAWAN | C27: DUSUN TERATAI INDAH | D27: 34794 | E27: =TEXT(D27,"DD MMMM YYY") -> 05 April 1995 | F27: KETAPANG | G27: =F27&","&E27 -> KETAPANG ,05 April 1995 | H27: SLTA | I27: 085651034052 | J27: cs5657394@gmail.com | K27: Toko Putra Elektronik, Pontianak,Kalbar. | L27: 1711654599 | N27: #N/A | O27: done | P27: =vlookup(B27,'RAW DATA'!B:U,14,0) -> 46265
A28: MAKASSAR | B28: I KETUT SUGIARTA | C28: Desa : TOLAI BARAT, Kecamatan: TORUE | D28: 35682 | E28: =TEXT(D28,"DD MMMM YYY") -> 09 September 1997 | F28: TOLAI | G28: =F28&","&E28 -> TOLAI,09 September 1997 | H28: SLTA | I28: 082193339184 | J28: sugiartha445566@gmail.com | K28: Palu, Jl.Jenderal Basuki Rahmat No.181, Birobuli Utara | L28: 7795175946 | M28: pake UMK Makassar | N28: PALU | O28: done | P28: =vlookup(B28,'RAW DATA'!B:U,14,0) -> 46265
A29: MAKASSAR | B29: Uun Yanuarti | C29: BTN Griya Ning Citra Lestari Blok A No 5 | D29: 38010 | E29: =TEXT(D29,"DD MMMM YYY") -> 24 Januari 2004 | F29: Makassar | G29: =F29&","&E29 -> Makassar,24 Januari 2004 | H29: SLTA | I29: 089513420390 | J29: uunyanuarti2425@gmail.com | K29: Iwata Store | L29: 7327362737 | N29: MAKASSAR | O29: done | P29: =vlookup(B29,'RAW DATA'!B:U,14,0) -> 46265
A30: SURABAYA | B30: Rista bellawati basuki | C30: Jalan Ploso 1 no 16 a | D30: 35238 | E30: =TEXT(D30,"DD MMMM YYY") -> 22 Juni 1996 | F30: Surabaya | G30: =F30&","&E30 -> Surabaya,22 Juni 1996 | H30: SLTA | I30: 089678564827 | J30: ristabella274@gmail.com | K30: Hartono Kertajaya indah surabaya | L30: 5190184422 | N30: SURABAYA | O30: done | P30: =vlookup(B30,'RAW DATA'!B:U,14,0) -> 46265
A31: JAKARTA | B31: Siti arimah | C31: Kp.kelapa 012/002 Kel.Rahayu, kec.patia, kab.Pandeglang, prov banten | D31: 37652 | E31: =TEXT(D31,"DD MMMM YYY") -> 31 Januari 2003 | F31: Pandeglang | G31: =F31&","&E31 -> Pandeglang ,31 Januari 2003 | H31: SLTA | I31: 085691568762 | J31: arimaaaa31@gmail.com | K31: Tangerang | L31: 4900427021 | N31: TANGERANG | O31: done | P31: =vlookup(B31,'RAW DATA'!B:U,14,0) -> 46265
A32: SURABAYA | B32: Owen Jehezkiel Wijaya | C32: Kedung Anyar 5/42 | D32: 39026 | E32: =TEXT(D32,"DD MMMM YYY") -> 05 November 2006 | F32: Surabaya | G32: =F32&","&E32 -> Surabaya,05 November 2006 | H32: SLTA | I32: 0882009923236 | J32: Goowen36@gmail.com | K32: Super Murah Surabaya Kenjeran | L32: 1030769631 | N32: SURABAYA | O32: done | P32: =vlookup(B32,'RAW DATA'!B:U,14,0) -> 46265
A33: SURABAYA | B33: BAGUS DWI ARDIANSYAH | C33: PONDOK BENOWO INDAH BO 14 SURABAYA | D33: 35663 | E33: =TEXT(D33,"DD MMMM YYY") -> 21 Agustus 1997 | F33: SURABAYA | G33: =F33&","&E33 -> SURABAYA,21 Agustus 1997 | H33: S1 | I33: 081283148912 | J33: bagusdwiar@gmail.com | K33: HARTONO BUKIT DARMO BOULEVARD SURABAYA | L33: 2582405442 | N33: SURABAYA | O33: done | P33: =vlookup(B33,'RAW DATA'!B:U,14,0) -> 46265
A34: SEMARANG | B34: Paramita Restuningtyas | C34: JL. Watulawang V / 29 | D34: 33239 | E34: =TEXT(D34,"DD MMMM YYY") -> 01 Januari 1991 | F34: Semarang | G34: =F34&","&E34 -> Semarang,01 Januari 1991 | H34: SLTA | I34: 085712040947 | J34: paramitharestu65@gmail.com | K34: Piranti Housware ( Jl. Lamper Tengah No.19 ) | L34: 8165474933 | N34: SEMARANG | O34: done | P34: =vlookup(B34,'RAW DATA'!B:U,14,0) -> 46265
A35: BALIKPAPAN | B35: DEVI ISVARADILLA AGRULLY | C35: Jl MINANGKABAU NO 101 RT 04 BATU AMPAR | D35: 37134 | E35: =TEXT(D35,"DD MMMM YYY") -> 31 Agustus 2001 | F35: Balikpapan | G35: =F35&","&E35 -> Balikpapan,31 Agustus 2001 | H35: SLTA | I35: 085656950939 | J35: deviisvaradilla16@gmail.com | K35: Balikpapan , nuansa gunung malang | L35: 7810287131 | N35: BALIKPAPAN | O35: done | P35: =vlookup(B35,'RAW DATA'!B:U,14,0) -> 46265
A36: PONTIANAK | B36: Eza Adela | C36: Dusun Danau Kuala Selakau | D36: 37747 | E36: =TEXT(D36,"DD MMMM YYY") -> 06 Mei 2003 | F36: Selakau , Kalimantan barat Kabupaten Sambas | G36: =F36&","&E36 -> Selakau , Kalimantan barat Kabupaten Sambas,06 Mei 2003 | H36: SLTA | I36: 085656271235 | J36: adelaeza021@gmail.com | K36: PD HIBURAN BARU KOTA SINGKAWANG | L36: 8171876893 | N36: PONTIANAK | O36: done | P36: =vlookup(B36,'RAW DATA'!B:U,14,0) -> 46265
A37: PALEMBANG | B37: AFRIZAL ADINATA | C37: Jl. Radial lrg. Dahlia No 12, RT 20, RW 05, 24 Ilir, Kec. Bukit kecil, Palembang, Sumatera Selatan | D37: 30064 | E37: =TEXT(D37,"DD MMMM YYY") -> 23 April 1982 | F37: Palembang | G37: =F37&","&E37 -> Palembang ,23 April 1982 | H37: SLTA | I37: 081271892394 | J37: afrizal.adinata@gmail.com | K37: GTM Palembang | L37: 0214271334 | N37: #N/A | O37: move ke sales | P37: =vlookup(B37,'RAW DATA'!B:U,14,0) -> #N/A
A38: SURABAYA | B38: MOCHAMAD ABDI AKBAR | C38: Jl.Arismunandar 7a/821 | D38: 30067 | E38: =TEXT(D38,"DD MMMM YYY") -> 26 April 1982 | F38: MALANG | G38: =F38&","&E38 -> MALANG,26 April 1982 | H38: SLTA | I38: 081252153824 | J38: abdi.akbarr@gmail.com | K38: TOKO OGAN MALANG | L38: 8161203041 | N38: #N/A | O38: done | P38: =vlookup(B38,'RAW DATA'!B:U,14,0) -> 46265
A39: MAKASSAR | B39: Chamida Ananda Septiani | C39: Dusun 1 Kasimbar Tengah Desa Kasimbar Kecamatan Kasimbar | D39: 36429 | E39: =TEXT(D39,"DD MMMM YYY") -> 26 September 1999 | F39: Parigi | G39: =F39&","&E39 -> Parigi,26 September 1999 | H39: SLTA | I39: 085298512206 | J39: chamidaananda@gmail.com | K39: Jl. I Gusti Ngurah Rai | L39: 1234567890 | M39: pake UMK Makassar | N39: PALU | O39: done | P39: =vlookup(B39,'RAW DATA'!B:U,14,0) -> 46265
